Workbook

Sheet Sunday WK1 (1)
B1: Freight | C1: Grocery | E1: Meat | F1: Bakery | G1: Bake off | H1: Deli | I1: Produce | J1: Produce Shrink | K1: Dairy | L1: Pharmacy | M1: Receiving Totals | N1: Total
B2: Name: | C2: =1-E2-F2-G2-H2-I2-J2-K2-L2 -> 0.478 | E2: 0.099 | F2: 0 | G2: 0 | H2: 0 | I2: 0.159 | J2: 0.122 | K2: 0.142 | L2: 0 | N2: =SUM(C2:M2) -> 1
B3: SHANNON | C3: =C2*$N$3 -> 123.79722 | E3: =E2*$N$3 -> 25.64001 | F3: =F2*$N$3 -> 0 | G3: =G2*$N$3 -> 0 | H3: =H2*$N$3 -> 0 | I3: =I2*$N$3 -> 41.17941 | J3: =J2*$N$3 -> 31.59678 | K3: =K2*$N$3 -> 36.77658 | L3: =L2*$N$3 -> 0 | N3: 258.99
A4: Receiving Date: | B4: 46194
A5: Invoice Number | B5: Supplier Name | C5: Grocery Purchases | D5: Tobacco Purchases | E5: Meat Purchases | F5: Bakery Purchases | G5: Bakery In Store | H5: Deli Purchases | I5: Produce Purchases | J5: Produce Shrink | K5: Dairy Purchases | L5: Pharmacy Purchases | M5: GST | N5: Total Invoice**
A6: 126281 | B6: ITALIAN BAKERY | C6: =N6-D6-E6-F6-G6-H6-I6-J6-K6-L6-M6-D60-E60-F60-G60-H60-I60-J60-K60-L60-C60 -> 246.09 | N6: 246.09
A7: 4003652120 | B7: SAPUTO DAIRY PRODUCTS | C7: =N7-D7-E7-F7-G7-H7-I7-J7-K7-L7-M7-D61-E61-F61-G61-H61-I61-J61-K61-L61-C61 -> 1.8207658e-14 | K7: 2699.31 | M7: 0.48 | N7: 2699.79
A8: SO185613 | B8: STAR PRODUCE | C8: =N8-D8-E8-F8-G8-H8-I8-J8-K8-L8-M8-D62-E62-F62-G62-H62-I62-J62-K62-L62-C62 -> -1.7763568e-15 | I8: 250.1 | M8: 8.97 | N8: 259.07
A9: 771176 | B9: PACIFIC FRESH FISH | C9: =N9-D9-E9-F9-G9-H9-I9-J9-K9-L9-M9-D63-E63-F63-G63-H63-I63-J63-K63-L63-C63 -> 93 | N9: 93
A10: 3278879 | B10: LILYDALE SOFINA FOODS | C10: =N10-D10-E10-F10-G10-H10-I10-J10-K10-L10-M10-D64-E64-F64-G64-H64-I64-J64-K64-L64-C64 -> 0 | E10: 47.02 | N10: 47.02
A11: 6644176 | B11: THE GROCERY PEOPLE | C11: =N11-D11-E11-F11-G11-H11-I11-J11-K11-L11-M11-D65-E65-F65-G65-H65-I65-J65-K65-L65-C65 -> 0 | E11: 2034.75 | N11: 2034.75
A12: 6644717 | B12: THE GROCERY PEOPLE | C12: =N12-D12-E12-F12-G12-H12-I12-J12-K12-L12-M12-D66-E66-F66-G66-H66-I66-J66-K66-L66-C66 -> 0 | E12: 436.05 | N12: 436.05
A13: 6647609 | B13: THE GROCERY PEOPLE | C13: =N13-D13-E13-F13-G13-H13-I13-J13-K13-L13-M13-D67-E67-F67-G67-H67-I67-J67-K67-L67-C67 -> 61.72 | N13: 61.72
A14: 6644304 | B14: THE GROCERY PEOPLE | C14: =N14-D14-E14-F14-G14-H14-I14-J14-K14-L14-M14-D68-E68-F68-G68-H68-I68-J68-K68-L68-C68 -> 148.32 | N14: 148.32
A15: 6644306 | B15: THE GROCERY PEOPLE | C15: =N15-D15-E15-F15-G15-H15-I15-J15-K15-L15-M15-D69-E69-F69-G69-H69-I69-J69-K69-L69-C69 -> 552.57 | N15: 552.57
A16: 6645036 | B16: THE GROCERY PEOPLE | C16: =N16-D16-E16-F16-G16-H16-I16-J16-K16-L16-M16-D70-E70-F70-G70-H70-I70-J70-K70-L70-C70 -> 0 | N16: 101.34 | O16: MEAT SUPPLIES - DIGI SCALE LABELS
A17: 6445919 | B17: THE GROCERY PEOPLE | C17: =N17-D17-E17-F17-G17-H17-I17-J17-K17-L17-M17-D71-E71-F71-G71-H71-I71-J71-K71-L71-C71 -> 325.68 | N17: 325.68
A18: 6646756 | B18: THE GROCERY PEOPLE | C18: =N18-D18-E18-F18-G18-H18-I18-J18-K18-L18-M18-D72-E72-F72-G72-H72-I72-J72-K72-L72-C72 -> 0 | E18: 73.59 | N18: 73.59
A19: 6646757 | B19: THE GROCERY PEOPLE | C19: =N19-D19-E19-F19-G19-H19-I19-J19-K19-L19-M19-D73-E73-F73-G73-H73-I73-J73-K73-L73-C73 -> 0 | E19: 61.66 | N19: 61.66
A20: 6647235 | B20: THE GROCERY PEOPLE | C20: =N20-D20-E20-F20-G20-H20-I20-J20-K20-L20-M20-D74-E74-F74-G74-H74-I74-J74-K74-L74-C74 -> 422.16 | N20: 422.16
A21: 6650196 | B21: THE GROCERY PEOPLE | C21: =N21-D21-E21-F21-G21-H21-I21-J21-K21-L21-M21-D75-E75-F75-G75-H75-I75-J75-K75-L75-C75 -> 0 | K21: 36.37 | N21: 36.37
A22: 6650197 | B22: THE GROCERY PEOPLE | C22: =N22-D22-E22-F22-G22-H22-I22-J22-K22-L22-M22-D76-E76-F76-G76-H76-I76-J76-K76-L76-C76 -> 0 | K22: 17.67 | N22: 17.67
A23: 5624761 | B23: THE GROCERY PEOPLE | C23: =N23-D23-E23-F23-G23-H23-I23-J23-K23-L23-M23-D77-E77-F77-G77-H77-I77-J77-K77-L77-C77 -> 152.44 | N23: 152.44
A24: 5625509 | B24: THE GROCERY PEOPLE | C24: =N24-D24-E24-F24-G24-H24-I24-J24-K24-L24-M24-D78-E78-F78-G78-H78-I78-J78-K78-L78-C78 -> 127.22 | N24: 127.22
A25: 5626052 | B25: THE GROCERY PEOPLE | C25: =N25-D25-E25-F25-G25-H25-I25-J25-K25-L25-M25-D79-E79-F79-G79-H79-I79-J79-K79-L79-C79 -> 0 | N25: 351.91 | O25: MEAT SUPPLIES - FOAM TRAYS, STRETCH FILM
A26: 5626479 | B26: THE GROCERY PEOPLE | C26: =N26-D26-E26-F26-G26-H26-I26-J26-K26-L26-M26-D80-E80-F80-G80-H80-I80-J80-K80-L80-C80 -> 168.81 | N26: 168.81
A27: 5626709 | B27: THE GROCERY PEOPLE | C27: =N27-D27-E27-F27-G27-H27-I27-J27-K27-L27-M27-D81-E81-F81-G81-H81-I81-J81-K81-L81-C81 -> 2333.06 | N27: 2333.06
A28: 5627364 | B28: THE GROCERY PEOPLE | C28: =N28-D28-E28-F28-G28-H28-I28-J28-K28-L28-M28-D82-E82-F82-G82-H82-I82-J82-K82-L82-C82 -> 1780.41 | N28: 1780.41
A29: 5627676 | B29: THE GROCERY PEOPLE | C29: =N29-D29-E29-F29-G29-H29-I29-J29-K29-L29-M29-D83-E83-F83-G83-H83-I83-J83-K83-L83-C83 -> 0 | K29: 1265.91 | N29: 1265.91
A30: 5628111 | B30: THE GROCERY PEOPLE | C30: =N30-D30-E30-F30-G30-H30-I30-J30-K30-L30-M30-D84-E84-F84-G84-H84-I84-J84-K84-L84-C84 -> 14120.7 | N30: 14120.7
A31: 8239352 | B31: THE GROCERY PEOPLE | C31: =N31-D31-E31-F31-G31-H31-I31-J31-K31-L31-M31-D85-E85-F85-G85-H85-I85-J85-K85-L85-C85 -> 0 | E31: 764.27 | N31: 764.27
A32: 8239683 | B32: THE GROCERY PEOPLE | C32: =N32-D32-E32-F32-G32-H32-I32-J32-K32-L32-M32-D86-E86-F86-G86-H86-I86-J86-K86-L86-C86 -> 0 | E32: 974.51 | N32: 974.51
A33: 5624975 | B33: THE GROCERY PEOPLE | C33: =N33-D33-E33-F33-G33-H33-I33-J33-K33-L33-M33-D87-E87-F87-G87-H87-I87-J87-K87-L87-C87 -> 5578.24 | N33: 5578.24
A34: 5625079 | B34: THE GROCERY PEOPLE | C34: =N34-D34-E34-F34-G34-H34-I34-J34-K34-L34-M34-D88-E88-F88-G88-H88-I88-J88-K88-L88-C88 -> 5077.32 | N34: 5077.32
A35: 5627277 | B35: THE GROCERY PEOPLE | C35: =N35-D35-E35-F35-G35-H35-I35-J35-K35-L35-M35-D89-E89-F89-G89-H89-I89-J89-K89-L89-C89 -> 152.44 | E35: 1833.49 | N35: 1985.93
A36: 5627365 | B36: THE GROCERY PEOPLE | C36: =N36-D36-E36-F36-G36-H36-I36-J36-K36-L36-M36-D90-E90-F90-G90-H90-I90-J90-K90-L90-C90 -> 0 | E36: 459.9 | N36: 459.9
A37: 5624976 | B37: THE GROCERY PEOPLE | C37: =N37-D37-E37-F37-G37-H37-I37-J37-K37-L37-M37-D91-E91-F91-G91-H91-I91-J91-K91-L91-C91 -> 1776.7 | N37: 1776.7
A38: 5627404 | B38: THE GROCERY PEOPLE | C38: =N38-D38-E38-F38-G38-H38-I38-J38-K38-L38-M38-D92-E92-F92-G92-H92-I92-J92-K92-L92-C92 -> 43.02 | N38: 43.02
A39: 5627560 | B39: THE GROCERY PEOPLE | C39: =N39-D39-E39-F39-G39-H39-I39-J39-K39-L39-M39-D93-E93-F93-G93-H93-I93-J93-K93-L93-C93 -> 829.78 | E39: 364.59 | N39: 1194.37
A40: 5627677 | B40: THE GROCERY PEOPLE | C40: =N40-D40-E40-F40-G40-H40-I40-J40-K40-L40-M40-D94-E94-F94-G94-H94-I94-J94-K94-L94-C94 -> 0 | K40: 534.04 | N40: 534.04
A41: 5628243 | B41: THE GROCERY PEOPLE | C41: =N41-D41-E41-F41-G41-H41-I41-J41-K41-L41-M41-D95-E95-F95-G95-H95-I95-J95-K95-L95-C95 -> 0 | E41: 55.14 | K41: 169.82 | N41: 224.96
A42: 5628265 | B42: THE GROCERY PEOPLE | C42: =N42-D42-E42-F42-G42-H42-I42-J42-K42-L42-M42-D96-E96-F96-G96-H96-I96-J96-K96-L96-C96 -> 0 | I42: 575.3 | N42: 575.3
A43: 5628266 | B43: THE GROCERY PEOPLE | C43: =N43-D43-E43-F43-G43-H43-I43-J43-K43-L43-M43-D97-E97-F97-G97-H97-I97-J97-K97-L97-C97 -> 0 | I43: 72.45 | N43: 72.45
A44: 5628288 | B44: THE GROCERY PEOPLE | C44: =N44-D44-E44-F44-G44-H44-I44-J44-K44-L44-M44-D98-E98-F98-G98-H98-I98-J98-K98-L98-C98 -> 0 | I44: 5506.23 | N44: 5506.23
A45: 5628408 | B45: THE GROCERY PEOPLE | C45: =N45-D45-E45-F45-G45-H45-I45-J45-K45-L45-M45-D99-E99-F99-G99-H99-I99-J99-K99-L99-C99 -> 0 | I45: 267.8 | N45: 267.8
A46: 6637875 | B46: FEDERATED CO-OPERATIVES | C46: =N46-D46-E46-F46-G46-H46-I46-J46-K46-L46-M46-D100-E100-F100-G100-H100-I100-J100-K100-L100-C100 -> 29.49 | N46: 29.49
A47: 6637876 | B47: FEDERATED CO-OPERATIVES | C47: =N47-D47-E47-F47-G47-H47-I47-J47-K47-L47-M47-D101-E101-F101-G101-H101-I101-J101-K101-L101-C101 -> 33.64 | N47: 33.64
A48: 6648548 | B48: FEDERATED CO-OPERATIVES | C48: =N48-D48-E48-F48-G48-H48-I48-J48-K48-L48-M48-D102-E102-F102-G102-H102-I102-J102-K102-L102-C102 -> 1257.19 | N48: 1257.19
A49: 6648549 | B49: FEDERATED CO-OPERATIVES | C49: =N49-D49-E49-F49-G49-H49-I49-J49-K49-L49-M49-D103-E103-F103-G103-H103-I103-J103-K103-L103-C103 -> 120.9 | N49: 120.9
A50: 6647654 | B50: FEDERATED CO-OPERATIVES | C50: =N50-D50-E50-F50-G50-H50-I50-J50-K50-L50-M50-D104-E104-F104-G104-H104-I104-J104-K104-L104-C104 -> 153.96 | N50: 153.96
C51: =N51-D51-E51-F51-G51-H51-I51-J51-K51-L51-M51-D105-E105-F105-G105-H105-I105-J105-K105-L105-C105 -> 0
C52: =N52-D52-E52-F52-G52-H52-I52-J52-K52-L52-M52-D106-E106-F106-G106-H106-I106-J106-K106-L106-C106 -> 0
C53: =N53-D53-E53-F53-G53-H53-I53-J53-K53-L53-M53-D107-E107-F107-G107-H107-I107-J107-K107-L107-C107 -> 0
C54: =N54-D54-E54-F54-G54-H54-I54-J54-K54-L54-M54-D108-E108-F108-G108-H108-I108-J108-K108-L108-C108 -> 0
C55: =N55-D55-E55-F55-G55-H55-I55-J55-K55-L55-M55-D109-E109-F109-G109-H109-I109-J109-K109-L109-C109 -> 0
A56: Freight | B56: THE GROCERY PEOPLE | C56: =C3 -> 123.79722 | E56: =E3 -> 25.64001 | F56: =F3 -> 0 | G56: =G3 -> 0 | H56: =H3 -> 0 | I56: =I3 -> 41.17941 | J56: =J3 -> 31.59678 | K56: =K3 -> 36.77658 | L56: =L3 -> 0 | N56: =SUM(C56:M56)+SUM(C118:J118) -> 258.99 | O56: BM#8454174, BOL REF#4834913,4834912,4834914,4834915,4834911
A57: Department Totals | C57: =SUM(C6:C56) -> 35708.657 | D57: =SUM(D6:D56) -> 0 | E57: =SUM(E6:E56) -> 7130.61 | F57: =SUM(F6:F56) -> 0 | G57: =SUM(G6:G56) -> 0 | H57: =SUM(H6:H56) -> 0 | I57: =SUM(I6:I56) -> 6713.0594 | J57: =SUM(J6:J56) -> 31.59678 | ... N57: =SUM(N6:N56) -> 54806.52
N58: =IF(SUM(N6:N56)=SUM(C57:M57)+SUM(C110:L110),"","Sum error")
A59: =A5 -> Invoice Number | B59: =B5 -> Supplier Name | C59: Grocery Supplies | D59: Tobacco Supplies | E59: Meat Supplies | F59: Bakery Supplies | G59: B.In store Supplies | H59: Deli Supplies | I59: Produce Supplies | K59: Dairy Supplies | L59: Pharmacy Supplies
A60: =A6 -> 126281 | B60: =B6 -> ITALIAN BAKERY
A61: =A7 -> 4003652120 | B61: =B7 -> SAPUTO DAIRY PRODUCTS
A62: =A8 -> SO185613 | B62: =B8 -> STAR PRODUCE
A63: =A9 -> 771176 | B63: =B9 -> PACIFIC FRESH FISH
A64: =A10 -> 3278879 | B64: =B10 -> LILYDALE SOFINA FOODS
A65: =A11 -> 6644176 | B65: =B11 -> THE GROCERY PEOPLE
A66: =A12 -> 6644717 | B66: =B12 -> THE GROCERY PEOPLE
A67: =A13 -> 6647609 | B67: =B13 -> THE GROCERY PEOPLE
A68: =A14 -> 6644304 | B68: =B14 -> THE GROCERY PEOPLE
A69: =A15 -> 6644306 | B69: =B15 -> THE GROCERY PEOPLE
A70: =A16 -> 6645036 | B70: =B16 -> THE GROCERY PEOPLE | E70: 101.34 | M70: MEAT SUPPLIES - DIGISCALE LABELS
A71: =A17 -> 6445919 | B71: =B17 -> THE GROCERY PEOPLE
A72: =A18 -> 6646756 | B72: =B18 -> THE GROCERY PEOPLE
A73: =A19 -> 6646757 | B73: =B19 -> THE GROCERY PEOPLE
A74: =A20 -> 6647235 | B74: =B20 -> THE GROCERY PEOPLE
A75: =A21 -> 6650196 | B75: =B21 -> THE GROCERY PEOPLE
A76: =A22 -> 6650197 | B76: =B22 -> THE GROCERY PEOPLE
A77: =A23 -> 5624761 | B77: =B23 -> THE GROCERY PEOPLE
A78: =A24 -> 5625509 | B78: =B24 -> THE GROCERY PEOPLE
A79: =A25 -> 5626052 | B79: =B25 -> THE GROCERY PEOPLE | E79: 351.91 | M79: MEAT SUPPLIES - FOAM TRAYS, STRETCH FILM
A80: =A26 -> 5626479 | B80: =B26 -> THE GROCERY PEOPLE
A81: =A27 -> 5626709 | B81: =B27 -> THE GROCERY PEOPLE
A82: =A28 -> 5627364 | B82: =B28 -> THE GROCERY PEOPLE
A83: =A29 -> 5627676 | B83: =B29 -> THE GROCERY PEOPLE
A84: =A30 -> 5628111 | B84: =B30 -> THE GROCERY PEOPLE
A85: =A31 -> 8239352 | B85: =B31 -> THE GROCERY PEOPLE
A86: =A32 -> 8239683 | B86: =B32 -> THE GROCERY PEOPLE
A87: =A33 -> 5624975 | B87: =B33 -> THE GROCERY PEOPLE
A88: =A34 -> 5625079 | B88: =B34 -> THE GROCERY PEOPLE
A89: =A35 -> 5627277 | B89: =B35 -> THE GROCERY PEOPLE
A90: =A36 -> 5627365 | B90: =B36 -> THE GROCERY PEOPLE
A91: =A37 -> 5624976 | B91: =B37 -> THE GROCERY PEOPLE
... A109: =A55 | B109: =B55
A110: =A57 -> Department Totals | C110: =SUM(C60:C109) -> 0 | D110: =SUM(D60:D109) -> 0 | E110: =SUM(E60:E109) -> 453.25 | F110: =SUM(F60:F109) -> 0 | G110: =SUM(G60:G109) -> 0 | H110: =SUM(H60:H109) -> 0 | I110: =SUM(I60:I109) -> 0 | J110: =SUM(J60:J109) -> 0 | ... L110: =SUM(L60:L109) -> 0

Sheet Monday WK1 (2)
B1: Freight | C1: Grocery | E1: Meat | F1: Bakery | G1: Bake off | H1: Deli | I1: Produce | J1: Produce Shrink | K1: Dairy | L1: Pharmacy | M1: Receiving Totals | N1: Total
B2: Name: | C2: =1-E2-F2-G2-H2-I2-J2-K2-L2 -> 0.478 | E2: ='Sunday WK1 (1)'!E2 -> 0.099 | F2: ='Sunday WK1 (1)'!F2 -> 0 | G2: ='Sunday WK1 (1)'!G2 -> 0 | H2: ='Sunday WK1 (1)'!H2 -> 0 | I2: ='Sunday WK1 (1)'!I2 -> 0.159 | J2: ='Sunday WK1 (1)'!J2 -> 0.122 | K2: ='Sunday WK1 (1)'!$K$2 -> 0.142 | L2: ='Sunday WK1 (1)'!L2 -> 0 | N2: =SUM(C2:M2) -> 1
B3: SHANNON | C3: =C2*$N$3 -> 0 | E3: =E2*$N$3 -> 0 | F3: =F2*$N$3 -> 0 | G3: =G2*$N$3 -> 0 | H3: =H2*$N$3 -> 0 | I3: =I2*$N$3 -> 0 | J3: =J2*$N$3 -> 0 | K3: =K2*$N$3 -> 0 | L3: =L2*$N$3 -> 0
A4: Receiving Date: | B4: ='Sunday WK1 (1)'!B4+1 -> 46195
A5: Invoice Number | B5: Supplier Name | C5: Grocery Purchases | D5: Tobacco Purchases | E5: Meat Purchases | F5: Bakery Purchases | G5: Bakery In Store | H5: Deli Purchases | I5: Produce Purchases | J5: Produce Shrink | K5: Dairy Purchases | L5: Pharmacy Purchases | M5: GST | N5: Total Invoice**
A6: 9597126 | B6: THE GROCERY PEOPLE | C6: =N6-D6-E6-F6-G6-H6-I6-J6-K6-L6-M6-D60-E60-F60-G60-H60-I60-J60-K60-L60-C60 -> 0 | K6: -35.02 | N6: -35.02 | O6: DAMAGED - INTL DELIGHT
A7: 9597117 | B7: THE GROCERY PEOPLE | C7: =N7-D7-E7-F7-G7-H7-I7-J7-K7-L7-M7-D61-E61-F61-G61-H61-I61-J61-K61-L61-C61 -> 0 | K7: -20.34 | N7: -20.34 | O7: DAMAGED - SPARKS EGGS
A8: 9598881 | B8: THE GROCERY PEOPLE | C8: =N8-D8-E8-F8-G8-H8-I8-J8-K8-L8-M8-D62-E62-F62-G62-H62-I62-J62-K62-L62-C62 -> 0 | K8: -22.33 | N8: -22.33 | O8: SHORTED - DANONE OIKOS
A9: 9598880 | B9: THE GROCERY PEOPLE | C9: =N9-D9-E9-F9-G9-H9-I9-J9-K9-L9-M9-D63-E63-F63-G63-H63-I63-J63-K63-L63-C63 -> 0 | K9: -62 | M9: 0 | N9: -62 | O9: SHORTED - CG XL EGGS
A10: 52933821006 | B10: COCA COLA CANADA BOTTLING | C10: =N10-D10-E10-F10-G10-H10-I10-J10-K10-L10-M10-D64-E64-F64-G64-H64-I64-J64-K64-L64-C64 -> 5954.68 | M10: 247.06 | N10: 6201.74
A11: 53927300 | B11: PEPSICO | C11: =N11-D11-E11-F11-G11-H11-I11-J11-K11-L11-M11-D65-E65-F65-G65-H65-I65-J65-K65-L65-C65 -> 6843.37 | M11: 192.53 | N11: 7035.9
A12: 32698 | B12: NELLA WEST | C12: =N12-D12-E12-F12-G12-H12-I12-J12-K12-L12-M12-D66-E66-F66-G66-H66-I66-J66-K66-L66-C66 -> 3172.5 | M12: 158.63 | N12: 3331.13
A13: 2306 | B13: NELLA WEST | C13: =N13-D13-E13-F13-G13-H13-I13-J13-K13-L13-M13-D67-E67-F67-G67-H67-I67-J67-K67-L67-C67 -> -19.41 | M13: -0.97 | N13: -20.38
A14: 126301 | B14: ITALIAN BAKERY | C14: =N14-D14-E14-F14-G14-H14-I14-J14-K14-L14-M14-D68-E68-F68-G68-H68-I68-J68-K68-L68-C68 -> 290.94 | N14: 290.94
A15: 2031031154 | B15: RED BULL CANADA | C15: =N15-D15-E15-F15-G15-H15-I15-J15-K15-L15-M15-D69-E69-F69-G69-H69-I69-J69-K69-L69-C69 -> 8801.4 | M15: 422.34 | N15: 9223.74
A16: 2031031155 | B16: RED BULL CANADA | C16: =N16-D16-E16-F16-G16-H16-I16-J16-K16-L16-M16-D70-E70-F70-G70-H70-I70-J70-K70-L70-C70 -> -4801.8 | M16: -231.81 | N16: -5033.61
A17: 82849759 | B17: OLD DUTCH FOODS | C17: =N17-D17-E17-F17-G17-H17-I17-J17-K17-L17-M17-D71-E71-F71-G71-H71-I71-J71-K71-L71-C71 -> 463.47 | M17: 13.63 | N17: 477.1
A18: 82849760 | B18: OLD DUTCH FOODS | C18: =N18-D18-E18-F18-G18-H18-I18-J18-K18-L18-M18-D72-E72-F72-G72-H72-I72-J72-K72-L72-C72 -> -76.48 | M18: -3.82 | N18: -80.3
A19: 226650717304 | B19: CANADA BREAD COMPANY | C19: =N19-D19-E19-F19-G19-H19-I19-J19-K19-L19-M19-D73-E73-F73-G73-H73-I73-J73-K73-L73-C73 -> 1238.29 | M19: 1.87 | N19: 1240.16
A20: 226650717305 | B20: CANADA BREAD COMPANY | C20: =N20-D20-E20-F20-G20-H20-I20-J20-K20-L20-M20-D74-E74-F74-G74-H74-I74-J74-K74-L74-C74 -> -318.43 | N20: -318.43
A21: 00020604 | B21: SEVEN SEAS FISH CO | C21: =N21-D21-E21-F21-G21-H21-I21-J21-K21-L21-M21-D75-E75-F75-G75-H75-I75-J75-K75-L75-C75 -> 388 | N21: 388
A22: 91205735 | B22: FRITO LAY CANADA VENDING | C22: =N22-D22-E22-F22-G22-H22-I22-J22-K22-L22-M22-D76-E76-F76-G76-H76-I76-J76-K76-L76-C76 -> 3014.44 | M22: 149.27 | N22: 3163.71
A23: 9501286 | B23: RECALL CLAIM | C23: =N23-D23-E23-F23-G23-H23-I23-J23-K23-L23-M23-D77-E77-F77-G77-H77-I77-J77-K77-L77-C77 -> -37.2 | N23: -37.2
C24: =N24-D24-E24-F24-G24-H24-I24-J24-K24-L24-M24-D78-E78-F78-G78-H78-I78-J78-K78-L78-C78 -> 0
C25: =N25-D25-E25-F25-G25-H25-I25-J25-K25-L25-M25-D79-E79-F79-G79-H79-I79-J79-K79-L79-C79 -> 0
C26: =N26-D26-E26-F26-G26-H26-I26-J26-K26-L26-M26-D80-E80-F80-G80-H80-I80-J80-K80-L80-C80 -> 0
C27: =N27-D27-E27-F27-G27-H27-I27-J27-K27-L27-M27-D81-E81-F81-G81-H81-I81-J81-K81-L81-C81 -> 0
C28: =N28-D28-E28-F28-G28-H28-I28-J28-K28-L28-M28-D82-E82-F82-G82-H82-I82-J82-K82-L82-C82 -> 0
C29: =N29-D29-E29-F29-G29-H29-I29-J29-K29-L29-M29-D83-E83-F83-G83-H83-I83-J83-K83-L83-C83 -> 0
C30: =N30-D30-E30-F30-G30-H30-I30-J30-K30-L30-M30-D84-E84-F84-G84-H84-I84-J84-K84-L84-C84 -> 0
C31: =N31-D31-E31-F31-G31-H31-I31-J31-K31-L31-M31-D85-E85-F85-G85-H85-I85-J85-K85-L85-C85 -> 0
C32: =N32-D32-E32-F32-G32-H32-I32-J32-K32-L32-M32-D86-E86-F86-G86-H86-I86-J86-K86-L86-C86 -> 0
C33: =N33-D33-E33-F33-G33-H33-I33-J33-K33-L33-M33-D87-E87-F87-G87-H87-I87-J87-K87-L87-C87 -> 0
C34: =N34-D34-E34-F34-G34-H34-I34-J34-K34-L34-M34-D88-E88-F88-G88-H88-I88-J88-K88-L88-C88 -> 0
C35: =N35-D35-E35-F35-G35-H35-I35-J35-K35-L35-M35-D89-E89-F89-G89-H89-I89-J89-K89-L89-C89 -> 0
... C55: =N55-D55-E55-F55-G55-H55-I55-J55-K55-L55-M55-D109-E109-F109-G109-H109-I109-J109-K109-L109-C109 -> 0
A56: Freight | B56: THE GROCERY PEOPLE | C56: =C3 -> 0 | E56: =E3 -> 0 | F56: =F3 -> 0 | G56: =G3 -> 0 | H56: =H3 -> 0 | I56: =I3 -> 0 | J56: =J3 -> 0 | K56: =K3 -> 0 | L56: =L3 -> 0 | N56: =SUM(C56:M56)+SUM(C118:J118) -> 0
A57: Department Totals | C57: =SUM(C6:C56) -> 24913.77 | D57: =SUM(D6:D56) -> 0 | E57: =SUM(E6:E56) -> 0 | F57: =SUM(F6:F56) -> 0 | G57: =SUM(G6:G56) -> 0 | H57: =SUM(H6:H56) -> 0 | I57: =SUM(I6:I56) -> 0 | J57: =SUM(J6:J56) -> 0 | ... N57: =SUM(N6:N56) -> 25722.81
N58: =IF(SUM(N6:N56)=SUM(C57:M57)+SUM(D110:L110),"","Sum error")
A59: =A5 -> Invoice Number | B59: =B5 -> Supplier Name | C59: Grocery Supplies | D59: Tobacco Supplies | E59: Meat Supplies | F59: Bakery Supplies | G59: B.In store Supplies | H59: Deli Supplies | I59: Produce Supplies | K59: Dairy Supplies | L59: Pharmacy Supplies
A60: =A6 -> 9597126 | B60: =B6 -> THE GROCERY PEOPLE
A61: =A7 -> 9597117 | B61: =B7 -> THE GROCERY PEOPLE
A62: =A8 -> 9598881 | B62: =B8 -> THE GROCERY PEOPLE
A63: =A9 -> 9598880 | B63: =B9 -> THE GROCERY PEOPLE
A64: =A10 -> 52933821006 | B64: =B10 -> COCA COLA CANADA BOTTLING
A65: =A11 -> 53927300 | B65: =B11 -> PEPSICO
A66: =A12 -> 32698 | B66: =B12 -> NELLA WEST
A67: =A13 -> 2306 | B67: =B13 -> NELLA WEST
A68: =A14 -> 126301 | B68: =B14 -> ITALIAN BAKERY
A69: =A15 -> 2031031154 | B69: =B15 -> RED BULL CANADA
A70: =A16 -> 2031031155 | B70: =B16 -> RED BULL CANADA
A71: =A17 -> 82849759 | B71: =B17 -> OLD DUTCH FOODS
... A109: =A55 | B109: =B55
A110: =A57 -> Department Totals | C110: =SUM(C60:C109) -> 0 | D110: =SUM(D60:D109) -> 0 | E110: =SUM(E60:E109) -> 0 | F110: =SUM(F60:F109) -> 0 | G110: =SUM(G60:G109) -> 0 | H110: =SUM(H60:H109) -> 0 | I110: =SUM(I60:I109) -> 0 | J110: =SUM(J60:J109) -> 0 | ... L110: =SUM(L60:L109) -> 0

Sheet Tuesday WK1 (3)
B1: Freight | C1: Grocery | E1: Meat | F1: Bakery | G1: Bake off | H1: Deli | I1: Produce | J1: Produce Shrink | K1: Dairy | L1: Pharmacy | M1: Receiving Totals | N1: Total
B2: Name: | C2: ='Sunday WK1 (1)'!C2 -> 0.478 | E2: ='Sunday WK1 (1)'!E2 -> 0.099 | F2: ='Sunday WK1 (1)'!F2 -> 0 | G2: ='Sunday WK1 (1)'!G2 -> 0 | H2: ='Sunday WK1 (1)'!H2 -> 0 | I2: ='Sunday WK1 (1)'!I2 -> 0.159 | J2: ='Sunday WK1 (1)'!J2 -> 0.122 | K2: ='Sunday WK1 (1)'!$K$2 -> 0.142 | L2: ='Sunday WK1 (1)'!L2 -> 0 | N2: =SUM(C2:M2) -> 1
B3: SHANNON | C3: =C2*$N$3 -> 136.79882 | E3: =E2*$N$3 -> 28.33281 | F3: =F2*$N$3 -> 0 | G3: =G2*$N$3 -> 0 | H3: =H2*$N$3 -> 0 | I3: =I2*$N$3 -> 45.50421 | J3: =J2*$N$3 -> 34.91518 | K3: =K2*$N$3 -> 40.63898 | L3: =L2*$N$3 -> 0 | N3: 286.19
A4: Receiving Date: | B4: ='Monday WK1 (2)'!B4+1 -> 46196
A5: Invoice Number | B5: Supplier Name | C5: Grocery Purchases | D5: Tobacco Purchases | E5: Meat Purchases | F5: Bakery Purchases | G5: Bakery In Store | H5: Deli Purchases | I5: Produce Purchases | J5: Produce Shrink | K5: Dairy Purchases | L5: Pharmacy Purchases | M5: GST | N5: Total Invoice**
A6: 4003658983 | B6: SAPUTO DAIRY PRODUCTS | C6: =N6-D6-E6-F6-G6-H6-I6-J6-K6-L6-M6-D60-E60-F60-G60-H60-I60-J60-K60-L60-C60 -> -1.0913492e-13 | K6: 2872.12 | M6: 0.37 | N6: 2872.49
A7: 4003658984 | B7: SAPUTO DAIRY PRODUCTS | C7: =N7-D7-E7-F7-G7-H7-I7-J7-K7-L7-M7-D61-E61-F61-G61-H61-I61-J61-K61-L61-C61 -> 0 | K7: 27.3 | N7: 27.3
A8: 6651868 | B8: THE GROCERY PEOPLE | C8: =N8-D8-E8-F8-G8-H8-I8-J8-K8-L8-M8-D62-E62-F62-G62-H62-I62-J62-K62-L62-C62 -> 0 | E8: 3583.6 | N8: 3583.6
A9: 6651869 | B9: THE GROCERY PEOPLE | C9: =N9-D9-E9-F9-G9-H9-I9-J9-K9-L9-M9-D63-E63-F63-G63-H63-I63-J63-K63-L63-C63 -> 0 | E9: 868.06 | N9: 868.06
A10: 6652458 | B10: THE GROCERY PEOPLE | C10: =N10-D10-E10-F10-G10-H10-I10-J10-K10-L10-M10-D64-E64-F64-G64-H64-I64-J64-K64-L64-C64 -> 0 | E10: 468.47 | N10: 468.47
A11: 6652237 | B11: THE GROCERY PEOPLE | C11: =N11-D11-E11-F11-G11-H11-I11-J11-K11-L11-M11-D65-E65-F65-G65-H65-I65-J65-K65-L65-C65 -> 0 | E11: 40.37 | N11: 40.37
A12: 6654306 | B12: THE GROCERY PEOPLE | C12: =N12-D12-E12-F12-G12-H12-I12-J12-K12-L12-M12-D66-E66-F66-G66-H66-I66-J66-K66-L66-C66 -> 1461.28 | E12: 67.6 | N12: 1528.88
A13: 6654307 | B13: THE GROCERY PEOPLE | C13: =N13-D13-E13-F13-G13-H13-I13-J13-K13-L13-M13-D67-E67-F67-G67-H67-I67-J67-K67-L67-C67 -> 53.56 | N13: 53.56
A14: 6655847 | B14: THE GROCERY PEOPLE | C14: =N14-D14-E14-F14-G14-H14-I14-J14-K14-L14-M14-D68-E68-F68-G68-H68-I68-J68-K68-L68-C68 -> 0 | K14: 238.18 | N14: 238.18
A15: 6655848 | B15: THE GROCERY PEOPLE | C15: =N15-D15-E15-F15-G15-H15-I15-J15-K15-L15-M15-D69-E69-F69-G69-H69-I69-J69-K69-L69-C69 -> 0 | K15: 17.67 | N15: 17.67
A16: 6652880 | B16: THE GROCERY PEOPLE | C16: =N16-D16-E16-F16-G16-H16-I16-J16-K16-L16-M16-D70-E70-F70-G70-H70-I70-J70-K70-L70-C70 -> 17.82 | N16: 17.82
A17: 6654592 | B17: THE GROCERY PEOPLE | C17: =N17-D17-E17-F17-G17-H17-I17-J17-K17-L17-M17-D71-E71-F71-G71-H71-I71-J71-K71-L71-C71 -> 0 | K17: 61.96 | N17: 61.96
A18: 5628412 | B18: THE GROCERY PEOPLE | C18: =N18-D18-E18-F18-G18-H18-I18-J18-K18-L18-M18-D72-E72-F72-G72-H72-I72-J72-K72-L72-C72 -> 146.06 | N18: 146.06
A19: 5629476 | B19: THE GROCERY PEOPLE | C19: =N19-D19-E19-F19-G19-H19-I19-J19-K19-L19-M19-D73-E73-F73-G73-H73-I73-J73-K73-L73-C73 -> 751.57 | E19: 227.62 | N19: 979.19
A20: 5629477 | B20: THE GROCERY PEOPLE | C20: =N20-D20-E20-F20-G20-H20-I20-J20-K20-L20-M20-D74-E74-F74-G74-H74-I74-J74-K74-L74-C74 -> 2602.53 | K20: 81.23 | N20: 2683.76
A21: 5629583 | B21: THE GROCERY PEOPLE | C21: =N21-D21-E21-F21-G21-H21-I21-J21-K21-L21-M21-D75-E75-F75-G75-H75-I75-J75-K75-L75-C75 -> 93.33 | K21: 1997.11 | N21: 2090.44
A22: 8240446 | B22: THE GROCERY PEOPLE | C22: =N22-D22-E22-F22-G22-H22-I22-J22-K22-L22-M22-D76-E76-F76-G76-H76-I76-J76-K76-L76-C76 -> 0 | E22: 912.24 | N22: 912.24
A23: 8240459 | B23: THE GROCERY PEOPLE | C23: =N23-D23-E23-F23-G23-H23-I23-J23-K23-L23-M23-D77-E77-F77-G77-H77-I77-J77-K77-L77-C77 -> 0 | E23: 574.25 | N23: 574.25
A24: 5629081 | B24: THE GROCERY PEOPLE | C24: =N24-D24-E24-F24-G24-H24-I24-J24-K24-L24-M24-D78-E78-F78-G78-H78-I78-J78-K78-L78-C78 -> 229.87 | E24: 2288.86 | N24: 2518.73
A25: 5628411 | B25: THE GROCERY PEOPLE | C25: =N25-D25-E25-F25-G25-H25-I25-J25-K25-L25-M25-D79-E79-F79-G79-H79-I79-J79-K79-L79-C79 -> 564.1 | N25: 564.1
A26: 5628458 | B26: THE GROCERY PEOPLE | C26: =N26-D26-E26-F26-G26-H26-I26-J26-K26-L26-M26-D80-E80-F80-G80-H80-I80-J80-K80-L80-C80 -> 107.9 | N26: 107.9
A27: 5628794 | B27: THE GROCERY PEOPLE | C27: =N27-D27-E27-F27-G27-H27-I27-J27-K27-L27-M27-D81-E81-F81-G81-H81-I81-J81-K81-L81-C81 -> 0 | K27: 4914.09 | N27: 4914.09
A28: 5629380 | B28: THE GROCERY PEOPLE | C28: =N28-D28-E28-F28-G28-H28-I28-J28-K28-L28-M28-D82-E82-F82-G82-H82-I82-J82-K82-L82-C82 -> 54.26 | N28: 54.26
A29: 5629381 | B29: THE GROCERY PEOPLE | C29: =N29-D29-E29-F29-G29-H29-I29-J29-K29-L29-M29-D83-E83-F83-G83-H83-I83-J83-K83-L83-C83 -> 23204.51 | N29: 23204.51
A30: 5629424 | B30: THE GROCERY PEOPLE | C30: =N30-D30-E30-F30-G30-H30-I30-J30-K30-L30-M30-D84-E84-F84-G84-H84-I84-J84-K84-L84-C84 -> 0 | E30: 40.21 | N30: 40.21
A31: 5629562 | B31: THE GROCERY PEOPLE | C31: =N31-D31-E31-F31-G31-H31-I31-J31-K31-L31-M31-D85-E85-F85-G85-H85-I85-J85-K85-L85-C85 -> 66.62 | K31: 1062.81 | N31: 1129.43
A32: 5630086 | B32: THE GROCERY PEOPLE | C32: =N32-D32-E32-F32-G32-H32-I32-J32-K32-L32-M32-D86-E86-F86-G86-H86-I86-J86-K86-L86-C86 -> 0 | N32: 0.01 | O32: PRODUCE SUPPLIES - POS MATERIAL HALOS BINS
A33: 5630111 | B33: THE GROCERY PEOPLE | C33: =N33-D33-E33-F33-G33-H33-I33-J33-K33-L33-M33-D87-E87-F87-G87-H87-I87-J87-K87-L87-C87 -> 0 | I33: 333.25 | N33: 333.25
A34: 5630112 | B34: THE GROCERY PEOPLE | C34: =N34-D34-E34-F34-G34-H34-I34-J34-K34-L34-M34-D88-E88-F88-G88-H88-I88-J88-K88-L88-C88 -> 0 | I34: 4529.83 | N34: 4529.83
A35: 5630113 | B35: THE GROCERY PEOPLE | C35: =N35-D35-E35-F35-G35-H35-I35-J35-K35-L35-M35-D89-E89-F89-G89-H89-I89-J89-K89-L89-C89 -> 0 | I35: 1286.71 | N35: 1286.71
A36: 117986 | B36: KENNELLI SPRINGS | C36: =N36-D36-E36-F36-G36-H36-I36-J36-K36-L36-M36-D90-E90-F90-G90-H90-I90-J90-K90-L90-C90 -> 205 | M36: 0.75 | N36: 205.75
A37: INV26-04375 | B37: CAPITAL FINE MEATS | C37: =N37-D37-E37-F37-G37-H37-I37-J37-K37-L37-M37-D91-E91-F91-G91-H91-I91-J91-K91-L91-C91 -> 0 | E37: 778.94 | N37: 778.94
A38: 91458496 | B38: FRITO LAY CANADA RETAIL | C38: =N38-D38-E38-F38-G38-H38-I38-J38-K38-L38-M38-D92-E92-F92-G92-H92-I92-J92-K92-L92-C92 -> 536.1 | M38: 24.04 | N38: 560.14
A39: 77683973 | B39: FRITO LAY CANADA RETAIL | C39: =N39-D39-E39-F39-G39-H39-I39-J39-K39-L39-M39-D93-E93-F93-G93-H93-I93-J93-K93-L93-C93 -> -102.01 | M39: -5.1 | N39: -107.11
A40: 7726174002 | B40: UNITED DISTRIBUTION NETWORK | C40: =N40-D40-E40-F40-G40-H40-I40-J40-K40-L40-M40-D94-E94-F94-G94-H94-I94-J94-K94-L94-C94 -> 2309.78 | M40: 115.49 | N40: 2425.27
A41: 7726174001 | B41: UNITED DISTRIBUTION NETWORK | C41: =N41-D41-E41-F41-G41-H41-I41-J41-K41-L41-M41-D95-E95-F95-G95-H95-I95-J95-K95-L95-C95 -> 4776.32 | E41: 47.53 | M41: 203.41 | N41: 5027.26
C42: =N42-D42-E42-F42-G42-H42-I42-J42-K42-L42-M42-D96-E96-F96-G96-H96-I96-J96-K96-L96-C96 -> 0
C43: =N43-D43-E43-F43-G43-H43-I43-J43-K43-L43-M43-D97-E97-F97-G97-H97-I97-J97-K97-L97-C97 -> 0
C44: =N44-D44-E44-F44-G44-H44-I44-J44-K44-L44-M44-D98-E98-F98-G98-H98-I98-J98-K98-L98-C98 -> 0
C45: =N45-D45-E45-F45-G45-H45-I45-J45-K45-L45-M45-D99-E99-F99-G99-H99-I99-J99-K99-L99-C99 -> 0
C46: =N46-D46-E46-F46-G46-H46-I46-J46-K46-L46-M46-D100-E100-F100-G100-H100-I100-J100-K100-L100-C100 -> 0
C47: =N47-D47-E47-F47-G47-H47-I47-J47-K47-L47-M47-D101-E101-F101-G101-H101-I101-J101-K101-L101-C101 -> 0
C48: =N48-D48-E48-F48-G48-H48-I48-J48-K48-L48-M48-D102-E102-F102-G102-H102-I102-J102-K102-L102-C102 -> 0
C49: =N49-D49-E49-F49-G49-H49-I49-J49-K49-L49-M49-D103-E103-F103-G103-H103-I103-J103-K103-L103-C103 -> 0
C50: =N50-D50-E50-F50-G50-H50-I50-J50-K50-L50-M50-D104-E104-F104-G104-H104-I104-J104-K104-L104-C104 -> 0
C51: =N51-D51-E51-F51-G51-H51-I51-J51-K51-L51-M51-D105-E105-F105-G105-H105-I105-J105-K105-L105-C105 -> 0
C52: =N52-D52-E52-F52-G52-H52-I52-J52-K52-L52-M52-D106-E106-F106-G106-H106-I106-J106-K106-L106-C106 -> 0
C53: =N53-D53-E53-F53-G53-H53-I53-J53-K53-L53-M53-D107-E107-F107-G107-H107-I107-J107-K107-L107-C107 -> 0
... C55: =N55-D55-E55-F55-G55-H55-I55-J55-K55-L55-M55-D109-E109-F109-G109-H109-I109-J109-K109-L109-C109 -> 0
A56: Freight | B56: THE GROCERY PEOPLE | C56: =C3 -> 136.79882 | E56: =E3 -> 28.33281 | F56: =F3 -> 0 | G56: =G3 -> 0 | H56: =H3 -> 0 | I56: =I3 -> 45.50421 | J56: =J3 -> 34.91518 | K56: =K3 -> 40.63898 | L56: =L3 -> 0 | N56: =SUM(C56:M56)+SUM(C116:J116) -> 286.19 | O56: BM#8458982, BOL REF #4835421,4835423,4835422,4835419,4835420
A57: Department Totals | C57: =SUM(C6:C56) -> 37215.399 | D57: =SUM(D6:D56) -> 0 | E57: =SUM(E6:E56) -> 9926.0828 | F57: =SUM(F6:F56) -> 0 | G57: =SUM(G6:G56) -> 0 | H57: =SUM(H6:H56) -> 0 | I57: =SUM(I6:I56) -> 6195.2942 | J57: =SUM(J6:J56) -> 34.91518 | ... M57: =SUM(M6:M56) -> 338.96 | N57: =SUM(C57:M57) -> 65023.76
N58: =IF(SUM(N6:N56)=SUM(C57:M57)+SUM(C110:K110),"","Sum error")
A59: =A5 -> Invoice Number | B59: =B5 -> Supplier Name | C59: Grocery Supplies | D59: Tobacco Supplies | E59: Meat Supplies | F59: Bakery Supplies | G59: B.In store Supplies | H59: Deli Supplies | I59: Produce Supplies | K59: Dairy Supplies | L59: Pharmacy Supplies
A60: =A6 -> 4003658983 | B60: =B6 -> SAPUTO DAIRY PRODUCTS
A61: =A7 -> 4003658984 | B61: =B7 -> SAPUTO DAIRY PRODUCTS
A62: =A8 -> 6651868 | B62: =B8 -> THE GROCERY PEOPLE
A63: =A9 -> 6651869 | B63: =B9 -> THE GROCERY PEOPLE
A64: =A10 -> 6652458 | B64: =B10 -> THE GROCERY PEOPLE
A65: =A11 -> 6652237 | B65: =B11 -> THE GROCERY PEOPLE
A66: =A12 -> 6654306 | B66: =B12 -> THE GROCERY PEOPLE
A67: =A13 -> 6654307 | B67: =B13 -> THE GROCERY PEOPLE
A68: =A14 -> 6655847 | B68: =B14 -> THE GROCERY PEOPLE
A69: =A15 -> 6655848 | B69: =B15 -> THE GROCERY PEOPLE
A70: =A16 -> 6652880 | B70: =B16 -> THE GROCERY PEOPLE
A71: =A17 -> 6654592 | B71: =B17 -> THE GROCERY PEOPLE
... A85: =A31 -> 5629562 | B85: =B31 -> THE GROCERY PEOPLE
A86: =A32 -> 5630086 | B86: =B32 -> THE GROCERY PEOPLE | I86: 0.01 | M86: PRODUCE SUPPLIES - POS MATERIAL HALOS BINS
A87: =A33 -> 5630111 | B87: =B33 -> THE GROCERY PEOPLE
A88: =A34 -> 5630112 | B88: =B34 -> THE GROCERY PEOPLE
A89: =A35 -> 5630113 | B89: =B35 -> THE GROCERY PEOPLE
A90: =A36 -> 117986 | B90: =B36 -> KENNELLI SPRINGS
A91: =A37 -> INV26-04375 | B91: =B37 -> CAPITAL FINE MEATS
A92: =A38 -> 91458496 | B92: =B38 -> FRITO LAY CANADA RETAIL
A93: =A39 -> 77683973 | B93: =B39 -> FRITO LAY CANADA RETAIL
A94: =A40 -> 7726174002 | B94: =B40 -> UNITED DISTRIBUTION NETWORK
A95: =A41 -> 7726174001 | B95: =B41 -> UNITED DISTRIBUTION NETWORK
A96: =A42 | B96: =B42
A97: =A43 | B97: =B43
A98: =A44 | B98: =B44
... A109: =A55 | B109: =B55
A110: =A57 -> Department Totals | C110: =SUM(C60:C109) -> 0 | D110: =SUM(D60:D109) -> 0 | E110: =SUM(E60:E109) -> 0 | F110: =SUM(F60:F109) -> 0 | G110: =SUM(G60:G109) -> 0 | H110: =SUM(H60:H109) -> 0 | I110: =SUM(I60:I109) -> 0.01 | J110: =SUM(J60:J109) -> 0 | ... L110: =SUM(L60:L109) -> 0

Sheet Wednesday WK1 (4)
B1: Freight | C1: Grocery | E1: Meat | F1: Bakery | G1: Bake off | H1: Deli | I1: Produce | J1: Produce Shrink | K1: Dairy | L1: Pharmacy | M1: Receiving Totals | N1: Total
B2: Name: | C2: ='Sunday WK1 (1)'!C2 -> 0.478 | E2: ='Sunday WK1 (1)'!E2 -> 0.099 | F2: ='Sunday WK1 (1)'!F2 -> 0 | G2: ='Sunday WK1 (1)'!G2 -> 0 | H2: ='Sunday WK1 (1)'!H2 -> 0 | I2: ='Sunday WK1 (1)'!I2 -> 0.159 | J2: ='Sunday WK1 (1)'!J2 -> 0.122 | K2: ='Sunday WK1 (1)'!$K$2 -> 0.142 | L2: ='Sunday WK1 (1)'!L2 -> 0 | N2: =SUM(C2:M2) -> 1
B3: SHANNON | C3: =C2*$N$3 -> 81.56114 | E3: =E2*$N$3 -> 16.89237 | F3: =F2*$N$3 -> 0 | G3: =G2*$N$3 -> 0 | H3: =H2*$N$3 -> 0 | I3: =I2*$N$3 -> 27.13017 | J3: =J2*$N$3 -> 20.81686 | K3: =K2*$N$3 -> 24.22946 | L3: =L2*$N$3 -> 0 | N3: 170.63
A4: Receiving Date: | B4: ='Tuesday WK1 (3)'!B4+1 -> 46197
A5: Invoice Number | B5: Supplier Name | C5: Grocery Purchases | D5: Tobacco Purchases | E5: Meat Purchases | F5: Bakery Purchases | G5: Bakery In Store | H5: Deli Purchases | I5: Produce Purchases | J5: Produce Shrink | K5: Dairy Purchases | L5: Pharmacy Purchases | M5: GST | N5: Total Invoice**
A6: 5226135003 | B6: UNITED DISTRIBUTION NETWORK | C6: =N6-D6-E6-F6-G6-H6-I6-J6-K6-L6-M6-D62-E62-F62-G62-H62-I62-J62-K62-L62-C62 -> -40.52 | M6: -1.99 | N6: -42.51
A7: 2474287 | B7: UNFI CANADA | C7: =N7-D7-E7-F7-G7-H7-I7-J7-K7-L7-M7-D63-E63-F63-G63-H63-I63-J63-K63-L63-C63 -> 720.35 | M7: 36.02 | N7: 756.37
A8: 5226142003 | B8: UNITED DISTRIBUTION NETWORK | C8: =N8-D8-E8-F8-G8-H8-I8-J8-K8-L8-M8-D64-E64-F64-G64-H64-I64-J64-K64-L64-C64 -> -51.91 | M8: -2.59 | N8: -54.5
A9: 5226149002 | B9: UNITED DISTRIBUTION NETWORK | C9: =N9-D9-E9-F9-G9-H9-I9-J9-K9-L9-M9-D65-E65-F65-G65-H65-I65-J65-K65-L65-C65 -> -132.5 | M9: -6.63 | N9: -139.13
A10: 6597432A | B10: THE GROCERY PEOPLE | C10: =N10-D10-E10-F10-G10-H10-I10-J10-K10-L10-M10-D66-E66-F66-G66-H66-I66-J66-K66-L66-C66 -> 940.97 | N10: 940.97
A11: 9590413 | B11: THE GROCERY PEOPLE | C11: =N11-D11-E11-F11-G11-H11-I11-J11-K11-L11-M11-D67-E67-F67-G67-H67-I67-J67-K67-L67-C67 -> 0 | E11: -4498.38 | N11: -4498.38 | O11: SHORT SHIPPED INV #8193088
A12: 1809156 | B12: THE GROCERY PEOPLE | C12: =N12-D12-E12-F12-G12-H12-I12-J12-K12-L12-M12-D68-E68-F68-G68-H68-I68-J68-K68-L68-C68 -> -1159.95 | N12: -1159.95 | O12: MAY RECLAMATION
A13: 86528036 | B13: FRITO LAY CANADA | C13: =N13-D13-E13-F13-G13-H13-I13-J13-K13-L13-M13-D69-E69-F69-G69-H69-I69-J69-K69-L69-C69 -> -66.53 | N13: -66.53
A14: 86528546 | B14: FRITO LAY CANADA | C14: =N14-D14-E14-F14-G14-H14-I14-J14-K14-L14-M14-D70-E70-F70-G70-H70-I70-J70-K70-L70-C70 -> 33.16 | N14: 33.16
A15: 10003557263 | B15: SAPUTO DAIRY PRODUCTS | C15: =N15-D15-E15-F15-G15-H15-I15-J15-K15-L15-M15-D71-E71-F71-G71-H71-I71-J71-K71-L71-C71 -> 0 | K15: -42.89 | N15: -42.89
A16: CREDIT MEMO | B16: THE GROCERY PEOPLE | C16: =N16-D16-E16-F16-G16-H16-I16-J16-K16-L16-M16-D72-E72-F72-G72-H72-I72-J72-K72-L72-C72 -> -3527.47 | N16: -3527.47 | O16: CREDIT FOR MIS KEY ISSUE - LEANE ELASCHUK
A17: 82849776 | B17: OLD DUTCH FOODS | C17: =N17-D17-E17-F17-G17-H17-I17-J17-K17-L17-M17-D73-E73-F73-G73-H73-I73-J73-K73-L73-C73 -> 431.09 | M17: 21.55 | N17: 452.64
A18: 82849777 | B18: OLD DUTCH FOODS | C18: =N18-D18-E18-F18-G18-H18-I18-J18-K18-L18-M18-D74-E74-F74-G74-H74-I74-J74-K74-L74-C74 -> -35.42 | M18: -1.77 | N18: -37.19
A19: 371789 | B19: DPB BAKING COMPANY | C19: =N19-D19-E19-F19-G19-H19-I19-J19-K19-L19-M19-D75-E75-F75-G75-H75-I75-J75-K75-L75-C75 -> 11744.88 | M19: 587.25 | N19: 12332.13
C20: =N20-D20-E20-F20-G20-H20-I20-J20-K20-L20-M20-D76-E76-F76-G76-H76-I76-J76-K76-L76-C76 -> 0
C21: =N21-D21-E21-F21-G21-H21-I21-J21-K21-L21-M21-D77-E77-F77-G77-H77-I77-J77-K77-L77-C77 -> 0
C22: =N22-D22-E22-F22-G22-H22-I22-J22-K22-L22-M22-D78-E78-F78-G78-H78-I78-J78-K78-L78-C78 -> 0
C23: =N23-D23-E23-F23-G23-H23-I23-J23-K23-L23-M23-D79-E79-F79-G79-H79-I79-J79-K79-L79-C79 -> 0
C24: =N24-D24-E24-F24-G24-H24-I24-J24-K24-L24-M24-D80-E80-F80-G80-H80-I80-J80-K80-L80-C80 -> 0
C25: =N25-D25-E25-F25-G25-H25-I25-J25-K25-L25-M25-D81-E81-F81-G81-H81-I81-J81-K81-L81-C81 -> 0
C26: =N26-D26-E26-F26-G26-H26-I26-J26-K26-L26-M26-D82-E82-F82-G82-H82-I82-J82-K82-L82-C82 -> 0
C27: =N27-D27-E27-F27-G27-H27-I27-J27-K27-L27-M27-D83-E83-F83-G83-H83-I83-J83-K83-L83-C83 -> 0
C28: =N28-D28-E28-F28-G28-H28-I28-J28-K28-L28-M28-D84-E84-F84-G84-H84-I84-J84-K84-L84-C84 -> 0
C29: =N29-D29-E29-F29-G29-H29-I29-J29-K29-L29-M29-D85-E85-F85-G85-H85-I85-J85-K85-L85-C85 -> 0
C30: =N30-D30-E30-F30-G30-H30-I30-J30-K30-L30-M30-D86-E86-F86-G86-H86-I86-J86-K86-L86-C86 -> 0
C31: =N31-D31-E31-F31-G31-H31-I31-J31-K31-L31-M31-D87-E87-F87-G87-H87-I87-J87-K87-L87-C87 -> 0
... C49: =N49-D49-E49-F49-G49-H49-I49-J49-K49-L49-M49-D105-E105-F105-G105-H105-I105-J105-K105-L105-C105 -> 0
C50: =N50-D50-E50-F50-G50-H50-I50-J50-K50-L50-M50-D105-E105-F105-G105-H105-I105-J105-K105-L105-C105 -> 0
C51: =N51-D51-E51-F51-G51-H51-I51-J51-K51-L51-M51-D106-E106-F106-G106-H106-I106-J106-K106-L106-C106 -> 0
C52: =N52-D52-E52-F52-G52-H52-I52-J52-K52-L52-M52-D107-E107-F107-G107-H107-I107-J107-K107-L107-C107 -> 0
C53: =N53-D53-E53-F53-G53-H53-I53-J53-K53-L53-M53-D108-E108-F108-G108-H108-I108-J108-K108-L108-C108 -> 0
C54: =N54-D54-E54-F54-G54-H54-I54-J54-K54-L54-M54-D109-E109-F109-G109-H109-I109-J109-K109-L109-C109 -> 0
C55: =N55-D55-E55-F55-G55-H55-I55-J55-K55-L55-M55-D110-E110-F110-G110-H110-I110-J110-K110-L110-C110 -> 0
A56: Freight | B56: THE GROCERY PEOPLE | C56: =C3 -> 81.56114 | E56: =E3 -> 16.89237 | F56: =F3 -> 0 | G56: =G3 -> 0 | H56: =H3 -> 0 | I56: =I3 -> 27.13017 | J56: =J3 -> 20.81686 | K56: =K3 -> 24.22946 | L56: =L3 -> 0 | N56: =SUM(C56:M56)+SUM(C116:J116) -> 170.63 | O56: DEBIT MEMO - MISSING FUEL SURCHARGE
A57: Department Totals | C57: =SUM(C6:C56) -> 8937.7111 | D57: =SUM(D6:D56) -> 0 | E57: =SUM(E6:E56) -> -4481.4876 | F57: =SUM(F6:F56) -> 0 | G57: =SUM(G6:G56) -> 0 | H57: =SUM(H6:H56) -> 0 | I57: =SUM(I6:I56) -> 27.13017 | J57: =SUM(J6:J56) -> 20.81686 | ... M57: =SUM(M6:M56) -> 631.84 | N57: =SUM(C57:M57) -> 5117.35
N58: =IF(SUM(N6:N56)=SUM(C57:M57)+SUM(C110:K110),"","Sum error")
A59: =A5 -> Invoice Number | B59: =B5 -> Supplier Name | C59: Grocery Supplies | D59: Tobacco Supplies | E59: Meat Supplies | F59: Bakery Supplies | G59: B.In store Supplies | H59: Deli Supplies | I59: Produce Supplies | K59: Dairy Supplies | L59: Pharmacy Supplies
A60: =A6 -> 5226135003 | B60: =B6 -> UNITED DISTRIBUTION NETWORK
A61: =A7 -> 2474287 | B61: =B7 -> UNFI CANADA
A62: =A8 -> 5226142003 | B62: =B8 -> UNITED DISTRIBUTION NETWORK
A63: =A9 -> 5226149002 | B63: =B9 -> UNITED DISTRIBUTION NETWORK
A64: =A10 -> 6597432A | B64: =B10 -> THE GROCERY PEOPLE
A65: =A11 -> 9590413 | B65: =B11 -> THE GROCERY PEOPLE
A66: =A12 -> 1809156 | B66: =B12 -> THE GROCERY PEOPLE
A67: =A13 -> 86528036 | B67: =B13 -> FRITO LAY CANADA
A68: =A14 -> 86528546 | B68: =B14 -> FRITO LAY CANADA
A69: =A15 -> 10003557263 | B69: =B15 -> SAPUTO DAIRY PRODUCTS
A70: =A16 -> CREDIT MEMO | B70: =B16 -> THE GROCERY PEOPLE
A71: =A17 -> 82849776 | B71: =B17 -> OLD DUTCH FOODS
... A109: =A55 | B109: =B55
A110: =A57 -> Department Totals | C110: =SUM(C60:C109) -> 0 | D110: =SUM(D60:D109) -> 0 | E110: =SUM(E60:E109) -> 0 | F110: =SUM(F60:F109) -> 0 | G110: =SUM(G60:G109) -> 0 | H110: =SUM(H60:H109) -> 0 | I110: =SUM(I60:I109) -> 0 | J110: =SUM(J60:J109) -> 0 | ... L110: =SUM(L60:L109) -> 0

Sheet Thursday WK1 (5)
B1: Freight | C1: Grocery | E1: Meat | F1: Bakery | G1: Bake off | H1: Deli | I1: Produce | J1: Produce Shrink | K1: Dairy | L1: Pharmacy | M1: Receiving Totals | N1: Total
B2: Name: | C2: ='Sunday WK1 (1)'!C2 -> 0.478 | E2: ='Sunday WK1 (1)'!E2 -> 0.099 | F2: ='Sunday WK1 (1)'!F2 -> 0 | G2: ='Sunday WK1 (1)'!G2 -> 0 | H2: ='Sunday WK1 (1)'!H2 -> 0 | I2: ='Sunday WK1 (1)'!I2 -> 0.159 | J2: ='Sunday WK1 (1)'!J2 -> 0.122 | K2: ='Sunday WK1 (1)'!$K$2 -> 0.142 | L2: ='Sunday WK1 (1)'!L2 -> 0 | N2: =SUM(C2:M2) -> 1
B3: SHANNON | C3: =C2*$N$3 -> 186.55384 | E3: =E2*$N$3 -> 38.63772 | F3: =F2*$N$3 -> 0 | G3: =G2*$N$3 -> 0 | H3: =H2*$N$3 -> 0 | I3: =I2*$N$3 -> 62.05452 | J3: =J2*$N$3 -> 47.61416 | K3: =K2*$N$3 -> 55.41976 | L3: =L2*$N$3 -> 0 | N3: 390.28
A4: Receiving Date: | B4: ='Wednesday WK1 (4)'!B4+1 -> 46198
A5: Invoice Number | B5: Supplier Name | C5: Grocery Purchases | D5: Tobacco Purchases | E5: Meat Purchases | F5: Bakery Purchases | G5: Bakery In Store | H5: Deli Purchases | I5: Produce Purchases | J5: Produce Shrink | K5: Dairy Purchases | L5: Pharmacy Purchases | M5: GST | N5: Total Invoice**
A6: 4003676429 | B6: SAPUTO DAIRY PRODUCTS | C6: =N6-D6-E6-F6-G6-H6-I6-J6-K6-L6-M6-D60-E60-F60-G60-H60-I60-J60-K60-L60-C60 -> 3.4561243e-13 | K6: 2353.22 | M6: 0.37 | N6: 2353.59
A7: 962372 | B7: HARVEST MEATS | C7: =N7-D7-E7-F7-G7-H7-I7-J7-K7-L7-M7-D61-E61-F61-G61-H61-I61-J61-K61-L61-C61 -> 0 | E7: 474.62 | N7: 474.62
A8: 962772 | B8: HARVEST MEATS | C8: =N8-D8-E8-F8-G8-H8-I8-J8-K8-L8-M8-D62-E62-F62-G62-H62-I62-J62-K62-L62-C62 -> 0 | E8: 230.43 | N8: 230.43
A9: 6657512 | B9: THE GROCERY PEOPLE | C9: =N9-D9-E9-F9-G9-H9-I9-J9-K9-L9-M9-D63-E63-F63-G63-H63-I63-J63-K63-L63-C63 -> 0 | E9: 2830.76 | N9: 2830.76
A10: 6656802 | B10: THE GROCERY PEOPLE | C10: =N10-D10-E10-F10-G10-H10-I10-J10-K10-L10-M10-D64-E64-F64-G64-H64-I64-J64-K64-L64-C64 -> 169.54 | E10: 49.3 | N10: 218.84
A11: 6658481 | B11: THE GROCERY PEOPLE | C11: =N11-D11-E11-F11-G11-H11-I11-J11-K11-L11-M11-D65-E65-F65-G65-H65-I65-J65-K65-L65-C65 -> 0 | E11: 40.28 | N11: 40.28
A12: 6658482 | B12: THE GROCERY PEOPLE | C12: =N12-D12-E12-F12-G12-H12-I12-J12-K12-L12-M12-D66-E66-F66-G66-H66-I66-J66-K66-L66-C66 -> 0 | E12: 244.1 | N12: 244.1
A13: 5630396 | B13: THE GROCERY PEOPLE | C13: =N13-D13-E13-F13-G13-H13-I13-J13-K13-L13-M13-D67-E67-F67-G67-H67-I67-J67-K67-L67-C67 -> 1381.38 | N13: 1381.38
A14: 5631184 | B14: THE GROCERY PEOPLE | C14: =N14-D14-E14-F14-G14-H14-I14-J14-K14-L14-M14-D68-E68-F68-G68-H68-I68-J68-K68-L68-C68 -> 1567.44 | N14: 1567.44
A15: 5631309 | B15: THE GROCERY PEOPLE | C15: =N15-D15-E15-F15-G15-H15-I15-J15-K15-L15-M15-D69-E69-F69-G69-H69-I69-J69-K69-L69-C69 -> 135.96 | N15: 135.96
A16: 5631563 | B16: THE GROCERY PEOPLE | C16: =N16-D16-E16-F16-G16-H16-I16-J16-K16-L16-M16-D70-E70-F70-G70-H70-I70-J70-K70-L70-C70 -> 0 | N16: 136.65 | O16: MEAT SUPPLIES - FOAM TRAYS, DIGI SCALE LABELS
A17: 5632090 | B17: THE GROCERY PEOPLE | C17: =N17-D17-E17-F17-G17-H17-I17-J17-K17-L17-M17-D71-E71-F71-G71-H71-I71-J71-K71-L71-C71 -> 23731.42 | N17: 23731.42
A18: 5632206 | B18: THE GROCERY PEOPLE | C18: =N18-D18-E18-F18-G18-H18-I18-J18-K18-L18-M18-D72-E72-F72-G72-H72-I72-J72-K72-L72-C72 -> 30.29 | K18: 3177.33 | N18: 3207.62
A19: 5632207 | B19: THE GROCERY PEOPLE | C19: =N19-D19-E19-F19-G19-H19-I19-J19-K19-L19-M19-D73-E73-F73-G73-H73-I73-J73-K73-L73-C73 -> 0 | K19: 153.82 | N19: 153.82
A20: 8241401 | B20: THE GROCERY PEOPLE | C20: =N20-D20-E20-F20-G20-H20-I20-J20-K20-L20-M20-D74-E74-F74-G74-H74-I74-J74-K74-L74-C74 -> 0 | E20: 784.48 | N20: 784.48
A21: 8241504 | B21: THE GROCERY PEOPLE | C21: =N21-D21-E21-F21-G21-H21-I21-J21-K21-L21-M21-D75-E75-F75-G75-H75-I75-J75-K75-L75-C75 -> 0 | E21: 543.46 | N21: 543.46
A22: 5630017 | B22: THE GROCERY PEOPLE | C22: =N22-D22-E22-F22-G22-H22-I22-J22-K22-L22-M22-D76-E76-F76-G76-H76-I76-J76-K76-L76-C76 -> 0 | E22: 80.09 | N22: 80.09
A23: 5631316 | B23: THE GROCERY PEOPLE | C23: =N23-D23-E23-F23-G23-H23-I23-J23-K23-L23-M23-D77-E77-F77-G77-H77-I77-J77-K77-L77-C77 -> 0 | E23: 4276.81 | N23: 4276.81
A24: 5631317 | B24: THE GROCERY PEOPLE | C24: =N24-D24-E24-F24-G24-H24-I24-J24-K24-L24-M24-D78-E78-F78-G78-H78-I78-J78-K78-L78-C78 -> 0 | E24: 413.52 | N24: 413.52
A25: 8241502 | B25: THE GROCERY PEOPLE | C25: =N25-D25-E25-F25-G25-H25-I25-J25-K25-L25-M25-D79-E79-F79-G79-H79-I79-J79-K79-L79-C79 -> 0 | E25: 74.95 | N25: 74.95
A26: 5629864 | B26: THE GROCERY PEOPLE | C26: =N26-D26-E26-F26-G26-H26-I26-J26-K26-L26-M26-D80-E80-F80-G80-H80-I80-J80-K80-L80-C80 -> 38.22 | N26: 38.22
A27: 5630018 | B27: THE GROCERY PEOPLE | C27: =N27-D27-E27-F27-G27-H27-I27-J27-K27-L27-M27-D81-E81-F81-G81-H81-I81-J81-K81-L81-C81 -> 2273.04 | N27: 2273.04
A28: 5630406 | B28: THE GROCERY PEOPLE | C28: =N28-D28-E28-F28-G28-H28-I28-J28-K28-L28-M28-D82-E82-F82-G82-H82-I82-J82-K82-L82-C82 -> 46.24 | N28: 46.24
A29: 5630539 | B29: THE GROCERY PEOPLE | C29: =N29-D29-E29-F29-G29-H29-I29-J29-K29-L29-M29-D83-E83-F83-G83-H83-I83-J83-K83-L83-C83 -> 476.46 | N29: 476.46
A30: 5630540 | B30: THE GROCERY PEOPLE | C30: =N30-D30-E30-F30-G30-H30-I30-J30-K30-L30-M30-D84-E84-F84-G84-H84-I84-J84-K84-L84-C84 -> 462.19 | N30: 462.19
A31: 5630541 | B31: THE GROCERY PEOPLE | C31: =N31-D31-E31-F31-G31-H31-I31-J31-K31-L31-M31-D85-E85-F85-G85-H85-I85-J85-K85-L85-C85 -> 560.1 | N31: 560.1
A32: 5630542 | B32: THE GROCERY PEOPLE | C32: =N32-D32-E32-F32-G32-H32-I32-J32-K32-L32-M32-D86-E86-F86-G86-H86-I86-J86-K86-L86-C86 -> 84 | N32: 84
A33: 5631315 | B33: THE GROCERY PEOPLE | C33: =N33-D33-E33-F33-G33-H33-I33-J33-K33-L33-M33-D87-E87-F87-G87-H87-I87-J87-K87-L87-C87 -> 6205.53 | N33: 6205.53
A34: 5631564 | B34: THE GROCERY PEOPLE | C34: =N34-D34-E34-F34-G34-H34-I34-J34-K34-L34-M34-D88-E88-F88-G88-H88-I88-J88-K88-L88-C88 -> 186.86 | N34: 186.86
A35: 5631565 | B35: THE GROCERY PEOPLE | C35: =N35-D35-E35-F35-G35-H35-I35-J35-K35-L35-M35-D89-E89-F89-G89-H89-I89-J89-K89-L89-C89 -> 573.36 | N35: 573.36
A36: 5631647 | B36: THE GROCERY PEOPLE | C36: =N36-D36-E36-F36-G36-H36-I36-J36-K36-L36-M36-D90-E90-F90-G90-H90-I90-J90-K90-L90-C90 -> 55.43 | N36: 55.43
A37: 5631732 | B37: THE GROCERY PEOPLE | C37: =N37-D37-E37-F37-G37-H37-I37-J37-K37-L37-M37-D91-E91-F91-G91-H91-I91-J91-K91-L91-C91 -> 98.46 | N37: 98.46
... A40: 5632195 | B40: THE GROCERY PEOPLE | C40: =N40-D40-E40-F40-G40-H40-I40-J40-K40-L40-M40-D94-E94-F94-G94-H94-I94-J94-K94-L94-C94 -> 244.08 | N40: 244.08
A41: 5632205 | B41: THE GROCERY PEOPLE | C41: =N41-D41-E41-F41-G41-H41-I41-J41-K41-L41-M41-D95-E95-F95-G95-H95-I95-J95-K95-L95-C95 -> 66.62 | K41: 1974.36 | N41: 2040.98
A42: 5631290 | B42: THE GROCERY PEOPLE | C42: =N42-D42-E42-F42-G42-H42-I42-J42-K42-L42-M42-D96-E96-F96-G96-H96-I96-J96-K96-L96-C96 -> 0 | I42: 12.81 | N42: 12.81
A43: 5631544 | B43: THE GROCERY PEOPLE | C43: =N43-D43-E43-F43-G43-H43-I43-J43-K43-L43-M43-D97-E97-F97-G97-H97-I97-J97-K97-L97-C97 -> 0 | I43: 34.22 | N43: 34.22
A44: 5632780 | B44: THE GROCERY PEOPLE | C44: =N44-D44-E44-F44-G44-H44-I44-J44-K44-L44-M44-D98-E98-F98-G98-H98-I98-J98-K98-L98-C98 -> 0 | I44: 182.35 | N44: 182.35
A45: 5632848 | B45: THE GROCERY PEOPLE | C45: =N45-D45-E45-F45-G45-H45-I45-J45-K45-L45-M45-D99-E99-F99-G99-H99-I99-J99-K99-L99-C99 -> 0 | I45: 3522.3 | N45: 3522.3
A46: 5632967 | B46: THE GROCERY PEOPLE | C46: =N46-D46-E46-F46-G46-H46-I46-J46-K46-L46-M46-D100-E100-F100-G100-H100-I100-J100-K100-L100-C100 -> 0 | I46: 82.46 | N46: 82.46
A47: SO185631 | B47: STAR PRODUCE | C47: =N47-D47-E47-F47-G47-H47-I47-J47-K47-L47-M47-D101-E101-F101-G101-H101-I101-J101-K101-L101-C101 -> 9.2370556e-14 | I47: 670.3 | M47: 22.9 | N47: 693.2
A48: 226650717652 | B48: CANADA BREAD COMPANY | C48: =N48-D48-E48-F48-G48-H48-I48-J48-K48-L48-M48-D102-E102-F102-G102-H102-I102-J102-K102-L102-C102 -> 589.62 | M48: 4.53 | N48: 594.15
A49: 53003562004 | B49: COCA COLA CANADA BOTTLING | C49: =N49-D49-E49-F49-G49-H49-I49-J49-K49-L49-M49-D103-E103-F103-G103-H103-I103-J103-K103-L103-C103 -> 12120.14 | M49: 547.01 | N49: 12667.15
A50: 126396 | B50: ITALIAN BAKERY | C50: =N50-D50-E50-F50-G50-H50-I50-J50-K50-L50-M50-D104-E104-F104-G104-H104-I104-J104-K104-L104-C104 -> 618.54 | N50: 618.54
A51: 0117318 | B51: G & L DISTRIBUTORS | C51: =N51-D51-E51-F51-G51-H51-I51-J51-K51-L51-M51-D105-E105-F105-G105-H105-I105-J105-K105-L105-C105 -> 2144.22 | M51: 107.21 | N51: 2251.43
A52: 226650717653 | B52: CANADA BREAD COMPANY | C52: =N52-D52-E52-F52-G52-H52-I52-J52-K52-L52-M52-D106-E106-F106-G106-H106-I106-J106-K106-L106-C106 -> -237.79 | M52: -2.64 | N52: -240.43
A53: SO2513920 | B53: HARLAN FAIRBANKS | C53: =N53-D53-E53-F53-G53-H53-I53-J53-K53-L53-M53-D107-E107-F107-G107-H107-I107-J107-K107-L107-C107 -> 1332.66 | M53: 58.9 | N53: 1391.56
A54: 91942722 | B54: FRITO LAY CANADA VENDING | C54: =N54-D54-E54-F54-G54-H54-I54-J54-K54-L54-M54-D108-E108-F108-G108-H108-I108-J108-K108-L108-C108 -> 6878.8 | M54: 343.94 | N54: 7222.74
C55: =N55-D55-E55-F55-G55-H55-I55-J55-K55-L55-M55-D109-E109-F109-G109-H109-I109-J109-K109-L109-C109 -> 0
A56: Freight | B56: THE GROCERY PEOPLE | C56: =C3 -> 186.55384 | E56: =E3 -> 38.63772 | F56: =F3 -> 0 | G56: =G3 -> 0 | H56: =H3 -> 0 | I56: =I3 -> 62.05452 | J56: =J3 -> 47.61416 | K56: =K3 -> 55.41976 | L56: =L3 -> 0 | N56: =SUM(C56:M56)+SUM(C118:J118) -> 390.28 | O56: BM#8467521, BOL REF #4836932,4836933,4836934,4836935,4836931
A57: Department Totals | C57: =SUM(C6:C56) -> 62321.504 | D57: =SUM(D6:D56) -> 0 | E57: =SUM(E6:E56) -> 10081.438 | F57: =SUM(F6:F56) -> 0 | G57: =SUM(G6:G56) -> 0 | H57: =SUM(H6:H56) -> 0 | I57: =SUM(I6:I56) -> 4566.4945 | J57: =SUM(J6:J56) -> 47.61416 | ... N57: =SUM(N6:N56) -> 85950.07
N58: =IF(SUM(N6:N56)=SUM(C57:M57)+SUM(C110:K110),"","Sum error")
A59: =A5 -> Invoice Number | B59: =B5 -> Supplier Name | C59: Grocery Supplies | D59: Tobacco Supplies | E59: Meat Supplies | F59: Bakery Supplies | G59: B.In store Supplies | H59: Deli Supplies | I59: Produce Supplies | K59: Dairy Supplies | L59: Pharmacy Supplies
A60: =A6 -> 4003676429 | B60: =B6 -> SAPUTO DAIRY PRODUCTS
A61: =A7 -> 962372 | B61: =B7 -> HARVEST MEATS
A62: =A8 -> 962772 | B62: =B8 -> HARVEST MEATS
A63: =A9 -> 6657512 | B63: =B9 -> THE GROCERY PEOPLE
A64: =A10 -> 6656802 | B64: =B10 -> THE GROCERY PEOPLE
A65: =A11 -> 6658481 | B65: =B11 -> THE GROCERY PEOPLE
A66: =A12 -> 6658482 | B66: =B12 -> THE GROCERY PEOPLE
A67: =A13 -> 5630396 | B67: =B13 -> THE GROCERY PEOPLE
A68: =A14 -> 5631184 | B68: =B14 -> THE GROCERY PEOPLE
A69: =A15 -> 5631309 | B69: =B15 -> THE GROCERY PEOPLE
A70: =A16 -> 5631563 | B70: =B16 -> THE GROCERY PEOPLE | E70: 136.65 | M70: MEAT SUPPLIES - FOAM TRAYS, DIGI SCALE LABELS
A71: =A17 -> 5632090 | B71: =B17 -> THE GROCERY PEOPLE
A72: =A18 -> 5632206 | B72: =B18 -> THE GROCERY PEOPLE
A73: =A19 -> 5632207 | B73: =B19 -> THE GROCERY PEOPLE
A74: =A20 -> 8241401 | B74: =B20 -> THE GROCERY PEOPLE
A75: =A21 -> 8241504 | B75: =B21 -> THE GROCERY PEOPLE
A76: =A22 -> 5630017 | B76: =B22 -> THE GROCERY PEOPLE
A77: =A23 -> 5631316 | B77: =B23 -> THE GROCERY PEOPLE
A78: =A24 -> 5631317 | B78: =B24 -> THE GROCERY PEOPLE
A79: =A25 -> 8241502 | B79: =B25 -> THE GROCERY PEOPLE
A80: =A26 -> 5629864 | B80: =B26 -> THE GROCERY PEOPLE
A81: =A27 -> 5630018 | B81: =B27 -> THE GROCERY PEOPLE
A82: =A28 -> 5630406 | B82: =B28 -> THE GROCERY PEOPLE
... A109: =A55 | B109: =B55
A110: =A57 -> Department Totals | C110: =SUM(C60:C109) -> 0 | D110: =SUM(D60:D109) -> 0 | E110: =SUM(E60:E109) -> 136.65 | F110: =SUM(F60:F109) -> 0 | G110: =SUM(G60:G109) -> 0 | H110: =SUM(H60:H109) -> 0 | I110: =SUM(I60:I109) -> 0 | J110: =SUM(J60:J109) -> 0 | ... L110: =SUM(L60:L109) -> 0

Sheet Friday WK1 (6)
B1: Freight | C1: Grocery | E1: Meat | F1: Bakery | G1: Bake off | H1: Deli | I1: Produce | J1: Produce Shrink | K1: Dairy | L1: Pharmacy | M1: Receiving Totals | N1: Total
B2: Name: | C2: ='Sunday WK1 (1)'!C2 -> 0.478 | E2: ='Sunday WK1 (1)'!E2 -> 0.099 | F2: ='Sunday WK1 (1)'!F2 -> 0 | G2: ='Sunday WK1 (1)'!G2 -> 0 | H2: ='Sunday WK1 (1)'!H2 -> 0 | I2: ='Sunday WK1 (1)'!I2 -> 0.159 | J2: ='Sunday WK1 (1)'!J2 -> 0.122 | K2: ='Sunday WK1 (1)'!$K$2 -> 0.142 | L2: ='Sunday WK1 (1)'!L2 -> 0 | N2: =SUM(C2:M2) -> 1
B3: SHANNON | C3: =C2*$N$3 -> 0 | E3: =E2*$N$3 -> 0 | F3: =F2*$N$3 -> 0 | G3: =G2*$N$3 -> 0 | H3: =H2*$N$3 -> 0 | I3: =I2*$N$3 -> 0 | J3: =J2*$N$3 -> 0 | K3: =K2*$N$3 -> 0 | L3: =L2*$N$3 -> 0
A4: Receiving Date: | B4: ='Thursday WK1 (5)'!$B$4+1 -> 46199
A5: Invoice Number | B5: Supplier Name | C5: Grocery Purchases | D5: Tobacco Purchases | E5: Meat Purchases | F5: Bakery Purchases | G5: Bakery In Store | H5: Deli Purchases | I5: Produce Purchases | J5: Produce Shrink | K5: Dairy Purchases | L5: Pharmacy Purchases | M5: GST | N5: Total Invoice**
A6: 2882617703 | B6: DIRECT PLUS FOOD GROUP | C6: =N6-D6-E6-F6-G6-H6-I6-J6-K6-L6-M6-D60-E60-F60-G60-H60-I60-J60-K60-L60-C60 -> 51.36 | N6: 51.36
A7: 2882617704 | B7: DIRECT PLUS FOOD GROUP | C7: =N7-D7-E7-F7-G7-H7-I7-J7-K7-L7-M7-D61-E61-F61-G61-H61-I61-J61-K61-L61-C61 -> 0 | E7: 1274.02 | M7: 5.5 | N7: 1279.52
A8: 2882617705 | B8: DIRECT PLUS FOOD GROUP | C8: =N8-D8-E8-F8-G8-H8-I8-J8-K8-L8-M8-D62-E62-F62-G62-H62-I62-J62-K62-L62-C62 -> 0 | E8: 63.84 | N8: 63.84
A9: 2882617706 | B9: DIRECT PLUS FOOD GROUP | C9: =N9-D9-E9-F9-G9-H9-I9-J9-K9-L9-M9-D63-E63-F63-G63-H63-I63-J63-K63-L63-C63 -> -34.24 | N9: -34.24
A10: 2034298473 | B10: RED BULL CANADA | C10: =N10-D10-E10-F10-G10-H10-I10-J10-K10-L10-M10-D64-E64-F64-G64-H64-I64-J64-K64-L64-C64 -> 5841.35 | M10: 280.68 | N10: 6122.03
A11: 3285617701 | B11: ARCTIC GLACIER | C11: =N11-D11-E11-F11-G11-H11-I11-J11-K11-L11-M11-D65-E65-F65-G65-H65-I65-J65-K65-L65-C65 -> 2203.2 | N11: 2203.2
A12: 82849789 | B12: OLD DUTCH FOODS | C12: =N12-D12-E12-F12-G12-H12-I12-J12-K12-L12-M12-D66-E66-F66-G66-H66-I66-J66-K66-L66-C66 -> -60.88 | M12: -3.04 | N12: -63.92
A13: 82849788 | B13: OLD DUTCH FOODS | C13: =N13-D13-E13-F13-G13-H13-I13-J13-K13-L13-M13-D67-E67-F67-G67-H67-I67-J67-K67-L67-C67 -> 709.17 | M13: 35.46 | N13: 744.63
A14: 92793699 | B14: FRITO LAY CANADA RETAIL | C14: =N14-D14-E14-F14-G14-H14-I14-J14-K14-L14-M14-D68-E68-F68-G68-H68-I68-J68-K68-L68-C68 -> 521.86 | M14: 26.11 | N14: 547.97
A15: 26808937 | B15: FRITO LAY CANADA RETAIL | C15: =N15-D15-E15-F15-G15-H15-I15-J15-K15-L15-M15-D69-E69-F69-G69-H69-I69-J69-K69-L69-C69 -> -9.89 | M15: -0.49 | N15: -10.38
A16: 80594 | B16: NUTRIFRESH WEST | C16: =N16-D16-E16-F16-G16-H16-I16-J16-K16-L16-M16-D70-E70-F70-G70-H70-I70-J70-K70-L70-C70 -> 917.92 | M16: 39.2 | N16: 957.12
C17: =N17-D17-E17-F17-G17-H17-I17-J17-K17-L17-M17-D71-E71-F71-G71-H71-I71-J71-K71-L71-C71 -> 0
C18: =N18-D18-E18-F18-G18-H18-I18-J18-K18-L18-M18-D72-E72-F72-G72-H72-I72-J72-K72-L72-C72 -> 0
C19: =N19-D19-E19-F19-G19-H19-I19-J19-K19-L19-M19-D73-E73-F73-G73-H73-I73-J73-K73-L73-C73 -> 0
C20: =N20-D20-E20-F20-G20-H20-I20-J20-K20-L20-M20-D74-E74-F74-G74-H74-I74-J74-K74-L74-C74 -> 0
C21: =N21-D21-E21-F21-G21-H21-I21-J21-K21-L21-M21-D75-E75-F75-G75-H75-I75-J75-K75-L75-C75 -> 0
C22: =N22-D22-E22-F22-G22-H22-I22-J22-K22-L22-M22-D76-E76-F76-G76-H76-I76-J76-K76-L76-C76 -> 0
C23: =N23-D23-E23-F23-G23-H23-I23-J23-K23-L23-M23-D77-E77-F77-G77-H77-I77-J77-K77-L77-C77 -> 0
C24: =N24-D24-E24-F24-G24-H24-I24-J24-K24-L24-M24-D78-E78-F78-G78-H78-I78-J78-K78-L78-C78 -> 0
C25: =N25-D25-E25-F25-G25-H25-I25-J25-K25-L25-M25-D79-E79-F79-G79-H79-I79-J79-K79-L79-C79 -> 0
C26: =N26-D26-E26-F26-G26-H26-I26-J26-K26-L26-M26-D80-E80-F80-G80-H80-I80-J80-K80-L80-C80 -> 0
C27: =N27-D27-E27-F27-G27-H27-I27-J27-K27-L27-M27-D81-E81-F81-G81-H81-I81-J81-K81-L81-C81 -> 0
C28: =N28-D28-E28-F28-G28-H28-I28-J28-K28-L28-M28-D82-E82-F82-G82-H82-I82-J82-K82-L82-C82 -> 0
... C55: =N55-D55-E55-F55-G55-H55-I55-J55-K55-L55-M55-D109-E109-F109-G109-H109-I109-J109-K109-L109-C109 -> 0
A56: Freight | B56: THE GROCERY PEOPLE | C56: =C3 -> 0 | E56: =E3 -> 0 | F56: =F3 -> 0 | G56: =G3 -> 0 | H56: =H3 -> 0 | I56: =I3 -> 0 | J56: =J3 -> 0 | K56: =K3 -> 0 | L56: =L3 -> 0 | N56: =SUM(C56:M56)+SUM(C118:J118) -> 0
A57: Department Totals | C57: =SUM(C6:C56) -> 10139.85 | D57: =SUM(D6:D56) -> 0 | E57: =SUM(E6:E56) -> 1337.86 | F57: =SUM(F6:F56) -> 0 | G57: =SUM(G6:G56) -> 0 | H57: =SUM(H6:H56) -> 0 | I57: =SUM(I6:I56) -> 0 | J57: =SUM(J6:J56) -> 0 | ... N57: =SUM(N6:N56) -> 11861.13
N58: =IF(SUM(N6:N56)=SUM(C57:M57)+SUM(D110:L110),"","Sum error")
A59: =A5 -> Invoice Number | B59: =B5 -> Supplier Name | C59: Grocery Supplies | D59: Tobacco Supplies | E59: Meat Supplies | F59: Bakery Supplies | G59: B.In store Supplies | H59: Deli Supplies | I59: Produce Supplies | K59: Dairy Supplies | L59: Pharmacy Supplies
A60: =A6 -> 2882617703 | B60: =B6 -> DIRECT PLUS FOOD GROUP
A61: =A7 -> 2882617704 | B61: =B7 -> DIRECT PLUS FOOD GROUP
A62: =A8 -> 2882617705 | B62: =B8 -> DIRECT PLUS FOOD GROUP
A63: =A9 -> 2882617706 | B63: =B9 -> DIRECT PLUS FOOD GROUP
A64: =A10 -> 2034298473 | B64: =B10 -> RED BULL CANADA
A65: =A11 -> 3285617701 | B65: =B11 -> ARCTIC GLACIER
A66: =A12 -> 82849789 | B66: =B12 -> OLD DUTCH FOODS
A67: =A13 -> 82849788 | B67: =B13 -> OLD DUTCH FOODS
A68: =A14 -> 92793699 | B68: =B14 -> FRITO LAY CANADA RETAIL
A69: =A15 -> 26808937 | B69: =B15 -> FRITO LAY CANADA RETAIL
A70: =A16 -> 80594 | B70: =B16 -> NUTRIFRESH WEST
A71: =A17 | B71: =B17
... A109: =A55 | B109: =B55
A110: =A57 -> Department Totals | C110: =SUM(C60:C109) -> 0 | D110: =SUM(D60:D109) -> 0 | E110: =SUM(E60:E109) -> 0 | F110: =SUM(F60:F109) -> 0 | G110: =SUM(G60:G109) -> 0 | H110: =SUM(H60:H109) -> 0 | I110: =SUM(I60:I109) -> 0 | J110: =SUM(J60:J109) -> 0 | ... L110: =SUM(L60:L109) -> 0

Sheet Saturday WK1 (7)
B1: Freight | C1: Grocery | E1: Meat | F1: Bakery | G1: Bake off | H1: Deli | I1: Produce | J1: Produce Shrink | K1: Dairy | L1: Pharmacy | M1: Receiving Totals | N1: Total
B2: Name: | C2: ='Sunday WK1 (1)'!C2 -> 0.478 | E2: ='Sunday WK1 (1)'!E2 -> 0.099 | F2: ='Sunday WK1 (1)'!F2 -> 0 | G2: ='Sunday WK1 (1)'!G2 -> 0 | H2: ='Sunday WK1 (1)'!H2 -> 0 | I2: ='Sunday WK1 (1)'!I2 -> 0.159 | J2: ='Sunday WK1 (1)'!J2 -> 0.122 | K2: ='Sunday WK1 (1)'!$K$2 -> 0.142 | L2: ='Sunday WK1 (1)'!L2 -> 0 | N2: =SUM(C2:M2) -> 1
B3: SHANNON | C3: =C2*$N$3 -> 0 | E3: =E2*$N$3 -> 0 | F3: =F2*$N$3 -> 0 | G3: =G2*$N$3 -> 0 | H3: =H2*$N$3 -> 0 | I3: =I2*$N$3 -> 0 | J3: =J2*$N$3 -> 0 | K3: =K2*$N$3 -> 0 | L3: =L2*$N$3 -> 0
A4: Receiving Date: | B4: ='Friday WK1 (6)'!$B$4+1 -> 46200
A5: Invoice Number | B5: Supplier Name | C5: Grocery Purchases | D5: Tobacco Purchases | E5: Meat Purchases | F5: Bakery Purchases | G5: Bakery In Store | H5: Deli Purchases | I5: Produce Purchases | J5: Produce Shrink | K5: Dairy Purchases | L5: Pharmacy Purchases | M5: GST | N5: Total Invoice**
A6: 126454 | B6: ITALIAN BAKERY | C6: =N6-D6-E6-F6-G6-H6-I6-J6-K6-L6-M6-D60-E60-F60-G60-H60-I60-J60-K60-L60-C60 -> 126.65 | N6: 126.65
C7: =N7-D7-E7-F7-G7-H7-I7-J7-K7-L7-M7-D61-E61-F61-G61-H61-I61-J61-K61-L61-C61 -> 0
C8: =N8-D8-E8-F8-G8-H8-I8-J8-K8-L8-M8-D62-E62-F62-G62-H62-I62-J62-K62-L62-C62 -> 0
C9: =N9-D9-E9-F9-G9-H9-I9-J9-K9-L9-M9-D63-E63-F63-G63-H63-I63-J63-K63-L63-C63 -> 0
C10: =N10-D10-E10-F10-G10-H10-I10-J10-K10-L10-M10-D64-E64-F64-G64-H64-I64-J64-K64-L64-C64 -> 0
C11: =N11-D11-E11-F11-G11-H11-I11-J11-K11-L11-M11-D65-E65-F65-G65-H65-I65-J65-K65-L65-C65 -> 0
C12: =N12-D12-E12-F12-G12-H12-I12-J12-K12-L12-M12-D66-E66-F66-G66-H66-I66-J66-K66-L66-C66 -> 0
C13: =N13-D13-E13-F13-G13-H13-I13-J13-K13-L13-M13-D67-E67-F67-G67-H67-I67-J67-K67-L67-C67 -> 0
C14: =N14-D14-E14-F14-G14-H14-I14-J14-K14-L14-M14-D68-E68-F68-G68-H68-I68-J68-K68-L68-C68 -> 0
C15: =N15-D15-E15-F15-G15-H15-I15-J15-K15-L15-M15-D69-E69-F69-G69-H69-I69-J69-K69-L69-C69 -> 0
C16: =N16-D16-E16-F16-G16-H16-I16-J16-K16-L16-M16-D70-E70-F70-G70-H70-I70-J70-K70-L70-C70 -> 0
C17: =N17-D17-E17-F17-G17-H17-I17-J17-K17-L17-M17-D71-E71-F71-G71-H71-I71-J71-K71-L71-C71 -> 0
C18: =N18-D18-E18-F18-G18-H18-I18-J18-K18-L18-M18-D72-E72-F72-G72-H72-I72-J72-K72-L72-C72 -> 0
... C55: =N55-D55-E55-F55-G55-H55-I55-J55-K55-L55-M55-D109-E109-F109-G109-H109-I109-J109-K109-L109-C109 -> 0
A56: Freight | B56: THE GROCERY PEOPLE | C56: =C3 -> 0 | E56: =E3 -> 0 | F56: =F3 -> 0 | G56: =G3 -> 0 | H56: =H3 -> 0 | I56: =I3 -> 0 | J56: =J3 -> 0 | K56: =K3 -> 0 | L56: =L3 -> 0 | N56: =SUM(C56:M56)+SUM(C118:J118) -> 0
A57: Department Totals | C57: =SUM(C6:C56) -> 126.65 | D57: =SUM(D6:D56) -> 0 | E57: =SUM(E6:E56) -> 0 | F57: =SUM(F6:F56) -> 0 | G57: =SUM(G6:G56) -> 0 | H57: =SUM(H6:H56) -> 0 | I57: =SUM(I6:I56) -> 0 | J57: =SUM(J6:J56) -> 0 | ... N57: =SUM(N6:N56) -> 126.65
N58: =IF(SUM(N6:N56)=SUM(C57:M57)+SUM(D110:L110),"","Sum error")
A59: =A5 -> Invoice Number | B59: =B5 -> Supplier Name | C59: Grocery Supplies | D59: Tobacco Supplies | E59: Meat Supplies | F59: Bakery Supplies | G59: B.In store Supplies | H59: Deli Supplies | I59: Produce Supplies | K59: Dairy Supplies | L59: Pharmacy Supplies
A60: =A6 -> 126454 | B60: =B6 -> ITALIAN BAKERY
A61: =A7 | B61: =B7
A62: =A8 | B62: =B8
A63: =A9 | B63: =B9
A64: =A10 | B64: =B10
A65: =A11 | B65: =B11
A66: =A12 | B66: =B12
A67: =A13 | B67: =B13
A68: =A14 | B68: =B14
A69: =A15 | B69: =B15
A70: =A16 | B70: =B16
A71: =A17 | B71: =B17
... A109: =A55 | B109: =B55
A110: =A57 -> Department Totals | C110: =SUM(C60:C109) -> 0 | D110: =SUM(D60:D109) -> 0 | E110: =SUM(E60:E109) -> 0 | F110: =SUM(F60:F109) -> 0 | G110: =SUM(G60:G109) -> 0 | H110: =SUM(H60:H109) -> 0 | I110: =SUM(I60:I109) -> 0 | J110: =SUM(J60:J109) -> 0 | ... L110: =SUM(L60:L109) -> 0

Sheet Sunday WK2 (8)
B1: Freight | C1: Grocery | E1: Meat | F1: Bakery | G1: Bake off | H1: Deli | I1: Produce | J1: Produce Shrink | K1: Dairy | L1: Pharmacy | M1: Receiving Totals | N1: Total
B2: Name: | C2: ='Sunday WK1 (1)'!C2 -> 0.478 | E2: ='Sunday WK1 (1)'!E2 -> 0.099 | F2: ='Sunday WK1 (1)'!F2 -> 0 | G2: ='Sunday WK1 (1)'!G2 -> 0 | H2: ='Sunday WK1 (1)'!H2 -> 0 | I2: ='Sunday WK1 (1)'!I2 -> 0.159 | J2: ='Sunday WK1 (1)'!J2 -> 0.122 | K2: ='Sunday WK1 (1)'!$K$2 -> 0.142 | L2: ='Sunday WK1 (1)'!L2 -> 0 | N2: =SUM(C2:M2) -> 1
B3: SHANNON | C3: =C2*$N$3 -> 166.28664 | E3: =E2*$N$3 -> 34.44012 | F3: =F2*$N$3 -> 0 | G3: =G2*$N$3 -> 0 | H3: =H2*$N$3 -> 0 | I3: =I2*$N$3 -> 55.31292 | J3: =J2*$N$3 -> 42.44136 | K3: =K2*$N$3 -> 49.39896 | L3: =L2*$N$3 -> 0 | N3: 347.88
A4: Receiving Date: | B4: ='Saturday WK1 (7)'!B4+1 -> 46201
A5: Invoice Number | B5: Supplier Name | C5: Grocery Purchases | D5: Tobacco Purchases | E5: Meat Purchases | F5: Bakery Purchases | G5: Bakery In Store | H5: Deli Purchases | I5: Produce Purchases | J5: Produce Shrink | K5: Dairy Purchases | L5: Pharmacy Purchases | M5: GST | N5: Total Invoice**
A6: 1003652120 | B6: SAPUTO DAIRY PRODUCTS | C6: =N6-D6-E6-F6-G6-H6-I6-J6-K6-L6-M6-D60-E60-F60-G60-H60-I60-J60-K60-L60-C60 -> 0 | K6: -22.87 | N6: -22.87
A7: 4003701372 | B7: SAPUTO DAIRY PRODUCTS | C7: =N7-D7-E7-F7-G7-H7-I7-J7-K7-L7-M7-D61-E61-F61-G61-H61-I61-J61-K61-L61-C61 -> 1.8207658e-14 | K7: 3683.33 | M7: 0.48 | N7: 3683.81
A8: 4003701374 | B8: SAPUTO DAIRY PRODUCTS | C8: =N8-D8-E8-F8-G8-H8-I8-J8-K8-L8-M8-D62-E62-F62-G62-H62-I62-J62-K62-L62-C62 -> 0 | K8: 243.86 | N8: 243.86
A9: 3280944 | B9: LILYDALE SOFINA FOODS | C9: =N9-D9-E9-F9-G9-H9-I9-J9-K9-L9-M9-D63-E63-F63-G63-H63-I63-J63-K63-L63-C63 -> 0 | E9: 200.05 | N9: 200.05
A10: 100351280 | B10: FREYBE GOURMET FOODS | C10: =N10-D10-E10-F10-G10-H10-I10-J10-K10-L10-M10-D64-E64-F64-G64-H64-I64-J64-K64-L64-C64 -> 0 | E10: 403.86 | N10: 403.86
A11: SO185965 | B11: STAR PRODUCE | C11: =N11-D11-E11-F11-G11-H11-I11-J11-K11-L11-M11-D65-E65-F65-G65-H65-I65-J65-K65-L65-C65 -> -1.7763568e-15 | I11: 250.1 | M11: 8.97 | N11: 259.07
A12: 6660239 | B12: THE GROCERY PEOPLE | C12: =N12-D12-E12-F12-G12-H12-I12-J12-K12-L12-M12-D66-E66-F66-G66-H66-I66-J66-K66-L66-C66 -> 0 | E12: 699.86 | N12: 699.86
A13: 6660588 | B13: THE GROCERY PEOPLE | C13: =N13-D13-E13-F13-G13-H13-I13-J13-K13-L13-M13-D67-E67-F67-G67-H67-I67-J67-K67-L67-C67 -> 0 | E13: 2571.86 | N13: 2571.86
A14: 6665623 | B14: THE GROCERY PEOPLE | C14: =N14-D14-E14-F14-G14-H14-I14-J14-K14-L14-M14-D68-E68-F68-G68-H68-I68-J68-K68-L68-C68 -> 0 | E14: 4774.68 | N14: 4774.68
A15: 6661029 | B15: THE GROCERY PEOPLE | C15: =N15-D15-E15-F15-G15-H15-I15-J15-K15-L15-M15-D69-E69-F69-G69-H69-I69-J69-K69-L69-C69 -> 0 | N15: 101.34 | O15: MEAT SUPPLIES - DIGISCALE LABELS
A16: 6662077 | B16: THE GROCERY PEOPLE | C16: =N16-D16-E16-F16-G16-H16-I16-J16-K16-L16-M16-D70-E70-F70-G70-H70-I70-J70-K70-L70-C70 -> 935.31 | E16: 41.99 | N16: 977.3
A17: 6663371 | B17: THE GROCERY PEOPLE | C17: =N17-D17-E17-F17-G17-H17-I17-J17-K17-L17-M17-D71-E71-F71-G71-H71-I71-J71-K71-L71-C71 -> 0 | N17: 484.98 | O17: STORE SUPPLIES - GARBAGE & WASTE ODOR CONT
A18: 5632856 | B18: THE GROCERY PEOPLE | C18: =N18-D18-E18-F18-G18-H18-I18-J18-K18-L18-M18-D72-E72-F72-G72-H72-I72-J72-K72-L72-C72 -> 10227.84 | N18: 10227.84
A19: 5632861 | B19: THE GROCERY PEOPLE | C19: =N19-D19-E19-F19-G19-H19-I19-J19-K19-L19-M19-D73-E73-F73-G73-H73-I73-J73-K73-L73-C73 -> 20.4 | N19: 20.4
A20: 5633291 | B20: THE GROCERY PEOPLE | C20: =N20-D20-E20-F20-G20-H20-I20-J20-K20-L20-M20-D74-E74-F74-G74-H74-I74-J74-K74-L74-C74 -> 0 | N20: 123.28 | O20: STORE SUPPLIES - 6.5" WHITE SPOONS
A21: 5634754 | B21: THE GROCERY PEOPLE | C21: =N21-D21-E21-F21-G21-H21-I21-J21-K21-L21-M21-D75-E75-F75-G75-H75-I75-J75-K75-L75-C75 -> 66.16 | N21: 66.16
A22: 5635177 | B22: THE GROCERY PEOPLE | C22: =N22-D22-E22-F22-G22-H22-I22-J22-K22-L22-M22-D76-E76-F76-G76-H76-I76-J76-K76-L76-C76 -> 1003.53 | N22: 1003.53
A23: 5635270 | B23: THE GROCERY PEOPLE | C23: =N23-D23-E23-F23-G23-H23-I23-J23-K23-L23-M23-D77-E77-F77-G77-H77-I77-J77-K77-L77-C77 -> 70.56 | N23: 70.56
A24: 5635433 | B24: THE GROCERY PEOPLE | C24: =N24-D24-E24-F24-G24-H24-I24-J24-K24-L24-M24-D78-E78-F78-G78-H78-I78-J78-K78-L78-C78 -> 2030.36 | N24: 2030.36
A25: 5635914 | B25: THE GROCERY PEOPLE | C25: =N25-D25-E25-F25-G25-H25-I25-J25-K25-L25-M25-D79-E79-F79-G79-H79-I79-J79-K79-L79-C79 -> 20659.39 | N25: 20659.39
A26: 5635916 | B26: THE GROCERY PEOPLE | C26: =N26-D26-E26-F26-G26-H26-I26-J26-K26-L26-M26-D80-E80-F80-G80-H80-I80-J80-K80-L80-C80 -> 2687.33 | N26: 2687.33
A27: 5636042 | B27: THE GROCERY PEOPLE | C27: =N27-D27-E27-F27-G27-H27-I27-J27-K27-L27-M27-D81-E81-F81-G81-H81-I81-J81-K81-L81-C81 -> 534.24 | N27: 534.24
A28: 5636044 | B28: THE GROCERY PEOPLE | C28: =N28-D28-E28-F28-G28-H28-I28-J28-K28-L28-M28-D82-E82-F82-G82-H82-I82-J82-K82-L82-C82 -> 70.5 | K28: 3088.08 | N28: 3158.58
A29: 5636045 | B29: THE GROCERY PEOPLE | C29: =N29-D29-E29-F29-G29-H29-I29-J29-K29-L29-M29-D83-E83-F83-G83-H83-I83-J83-K83-L83-C83 -> 0 | K29: 49.56 | N29: 49.56
A30: 8242570 | B30: THE GROCERY PEOPLE | C30: =N30-D30-E30-F30-G30-H30-I30-J30-K30-L30-M30-D84-E84-F84-G84-H84-I84-J84-K84-L84-C84 -> 0 | E30: 252.4 | N30: 252.4
A31: 8242976 | B31: THE GROCERY PEOPLE | C31: =N31-D31-E31-F31-G31-H31-I31-J31-K31-L31-M31-D85-E85-F85-G85-H85-I85-J85-K85-L85-C85 -> 0 | E31: 1286.43 | N31: 1286.43
A32: 8243386 | B32: THE GROCERY PEOPLE | C32: =N32-D32-E32-F32-G32-H32-I32-J32-K32-L32-M32-D86-E86-F86-G86-H86-I86-J86-K86-L86-C86 -> 0 | E32: 663.35 | N32: 663.35
A33: 8243603 | B33: THE GROCERY PEOPLE | C33: =N33-D33-E33-F33-G33-H33-I33-J33-K33-L33-M33-D87-E87-F87-G87-H87-I87-J87-K87-L87-C87 -> 0 | E33: 415.01 | N33: 415.01
A34: 5632862 | B34: THE GROCERY PEOPLE | C34: =N34-D34-E34-F34-G34-H34-I34-J34-K34-L34-M34-D88-E88-F88-G88-H88-I88-J88-K88-L88-C88 -> 0 | N34: 58.64 | O34: STORE SUPPLIES - STRETCH WRAP
A35: 5632970 | B35: THE GROCERY PEOPLE | C35: =N35-D35-E35-F35-G35-H35-I35-J35-K35-L35-M35-D89-E89-F89-G89-H89-I89-J89-K89-L89-C89 -> 108.15 | N35: 108.15
A36: 5633158 | B36: THE GROCERY PEOPLE | C36: =N36-D36-E36-F36-G36-H36-I36-J36-K36-L36-M36-D90-E90-F90-G90-H90-I90-J90-K90-L90-C90 -> 1188.3 | N36: 1188.3
A37: 5633948 | B37: THE GROCERY PEOPLE | C37: =N37-D37-E37-F37-G37-H37-I37-J37-K37-L37-M37-D91-E91-F91-G91-H91-I91-J91-K91-L91-C91 -> 114.66 | N37: 114.66
A38: 5634067 | B38: THE GROCERY PEOPLE | C38: =N38-D38-E38-F38-G38-H38-I38-J38-K38-L38-M38-D92-E92-F92-G92-H92-I92-J92-K92-L92-C92 -> 420.46 | N38: 420.46
A39: 5634483 | B39: THE GROCERY PEOPLE | C39: =N39-D39-E39-F39-G39-H39-I39-J39-K39-L39-M39-D93-E93-F93-G93-H93-I93-J93-K93-L93-C93 -> 281.94 | N39: 281.94
A40: 5635178 | B40: THE GROCERY PEOPLE | C40: =N40-D40-E40-F40-G40-H40-I40-J40-K40-L40-M40-D94-E94-F94-G94-H94-I94-J94-K94-L94-C94 -> 11.76 | N40: 11.76
A41: 5635520 | B41: THE GROCERY PEOPLE | C41: =N41-D41-E41-F41-G41-H41-I41-J41-K41-L41-M41-D95-E95-F95-G95-H95-I95-J95-K95-L95-C95 -> 678.3 | N41: 678.3
A42: 5635521 | B42: THE GROCERY PEOPLE | C42: =N42-D42-E42-F42-G42-H42-I42-J42-K42-L42-M42-D96-E96-F96-G96-H96-I96-J96-K96-L96-C96 -> 104.23 | N42: 104.23
A43: 5635709 | B43: THE GROCERY PEOPLE | C43: =N43-D43-E43-F43-G43-H43-I43-J43-K43-L43-M43-D97-E97-F97-G97-H97-I97-J97-K97-L97-C97 -> 0 | E43: 228.33 | N43: 228.33
A44: 5635828 | B44: THE GROCERY PEOPLE | C44: =N44-D44-E44-F44-G44-H44-I44-J44-K44-L44-M44-D98-E98-F98-G98-H98-I98-J98-K98-L98-C98 -> 131.66 | N44: 131.66
A45: 5636043 | B45: THE GROCERY PEOPLE | C45: =N45-D45-E45-F45-G45-H45-I45-J45-K45-L45-M45-D99-E99-F99-G99-H99-I99-J99-K99-L99-C99 -> 171.28 | N45: 171.28
A46: 5635179 | B46: THE GROCERY PEOPLE | C46: =N46-D46-E46-F46-G46-H46-I46-J46-K46-L46-M46-D100-E100-F100-G100-H100-I100-J100-K100-L100-C100 -> 0 | E46: 4750.13 | N46: 4750.13
A47: 5635603 | B47: THE GROCERY PEOPLE | C47: =N47-D47-E47-F47-G47-H47-I47-J47-K47-L47-M47-D101-E101-F101-G101-H101-I101-J101-K101-L101-C101 -> 0 | E47: 356.6 | N47: 356.6
A48: 5636232 | B48: THE GROCERY PEOPLE | C48: =N48-D48-E48-F48-G48-H48-I48-J48-K48-L48-M48-D102-E102-F102-G102-H102-I102-J102-K102-L102-C102 -> 0 | I48: 137.85 | N48: 137.85
A49: 5636233 | B49: THE GROCERY PEOPLE | C49: =N49-D49-E49-F49-G49-H49-I49-J49-K49-L49-M49-D103-E103-F103-G103-H103-I103-J103-K103-L103-C103 -> 0 | I49: 2818.27 | N49: 2818.27
A50: 5636384 | B50: THE GROCERY PEOPLE | C50: =N50-D50-E50-F50-G50-H50-I50-J50-K50-L50-M50-D104-E104-F104-G104-H104-I104-J104-K104-L104-C104 -> 0 | I50: 338.6 | N50: 338.6
C51: =N51-D51-E51-F51-G51-H51-I51-J51-K51-L51-M51-D105-E105-F105-G105-H105-I105-J105-K105-L105-C105 -> 0
C52: =N52-D52-E52-F52-G52-H52-I52-J52-K52-L52-M52-D106-E106-F106-G106-H106-I106-J106-K106-L106-C106 -> 0
C53: =N53-D53-E53-F53-G53-H53-I53-J53-K53-L53-M53-D107-E107-F107-G107-H107-I107-J107-K107-L107-C107 -> 0
C54: =N54-D54-E54-F54-G54-H54-I54-J54-K54-L54-M54-D108-E108-F108-G108-H108-I108-J108-K108-L108-C108 -> 0
C55: =N55-D55-E55-F55-G55-H55-I55-J55-K55-L55-M55-D109-E109-F109-G109-H109-I109-J109-K109-L109-C109 -> 0
A56: Freight | B56: THE GROCERY PEOPLE | C56: =C3 -> 166.28664 | E56: =E3 -> 34.44012 | F56: =F3 -> 0 | G56: =G3 -> 0 | H56: =H3 -> 0 | I56: =I3 -> 55.31292 | J56: =J3 -> 42.44136 | K56: =K3 -> 49.39896 | L56: =L3 -> 0 | N56: =SUM(C56:M56)+SUM(C118:J118) -> 347.88 | O56: BM#8474904, BOL REF#4838302,4838301,4838300,4838303,4838299
A57: Department Totals | C57: =SUM(C6:C56) -> 41682.647 | D57: =SUM(D6:D56) -> 0 | E57: =SUM(E6:E56) -> 16678.99 | F57: =SUM(F6:F56) -> 0 | G57: =SUM(G6:G56) -> 0 | H57: =SUM(H6:H56) -> 0 | I57: =SUM(I6:I56) -> 3600.1329 | J57: =SUM(J6:J56) -> 42.44136 | ... N57: =SUM(N6:N56) -> 69873.26
N58: =IF(SUM(N6:N56)=SUM(C57:M57)+SUM(C110:L110),"","Sum error") -> Sum error
A59: Invoice Number | B59: Supplier Name | C59: Grocery Supplies | D59: Tobacco Supplies | E59: Meat Supplies | F59: Bakery Supplies | G59: B.In store Supplies | H59: Deli Supplies | I59: Produce Supplies | K59: Dairy Supplies | L59: Pharmacy Supplies
A60: =A6 -> 1003652120 | B60: =B6 -> SAPUTO DAIRY PRODUCTS
A61: =A7 -> 4003701372 | B61: =B7 -> SAPUTO DAIRY PRODUCTS
A62: =A8 -> 4003701374 | B62: =B8 -> SAPUTO DAIRY PRODUCTS
A63: =A9 -> 3280944 | B63: =B9 -> LILYDALE SOFINA FOODS
A64: =A10 -> 100351280 | B64: =B10 -> FREYBE GOURMET FOODS
A65: =A11 -> SO185965 | B65: =B11 -> STAR PRODUCE
A66: =A12 -> 6660239 | B66: =B12 -> THE GROCERY PEOPLE
A67: =A13 -> 6660588 | B67: =B13 -> THE GROCERY PEOPLE
A68: =A14 -> 6665623 | B68: =B14 -> THE GROCERY PEOPLE
A69: =A15 -> 6661029 | B69: =B15 -> THE GROCERY PEOPLE | E69: 101.34 | M69: MEAT SUPPLIE - DIGISCALE LABELS
A70: =A16 -> 6662077 | B70: =B16 -> THE GROCERY PEOPLE
A71: =A17 -> 6663371 | B71: =B17 -> THE GROCERY PEOPLE | C71: 484.98 | M71: STORE SUPPLIES - GARBAGE & WASTE ODOR CONT.
A72: =A18 -> 5632856 | B72: =B18 -> THE GROCERY PEOPLE
A73: =A19 -> 5632861 | B73: =B19 -> THE GROCERY PEOPLE
A74: =A20 -> 5633291 | B74: =B20 -> THE GROCERY PEOPLE | C74: 123.28 | M74: STORE SUPPLIES - 6.5" WHITE SPOONS
A75: =A21 -> 5634754 | B75: =B21 -> THE GROCERY PEOPLE
A76: =A22 -> 5635177 | B76: =B22 -> THE GROCERY PEOPLE
A77: =A23 -> 5635270 | B77: =B23 -> THE GROCERY PEOPLE
A78: =A24 -> 5635433 | B78: =B24 -> THE GROCERY PEOPLE
A79: =A25 -> 5635914 | B79: =B25 -> THE GROCERY PEOPLE
A80: =A26 -> 5635916 | B80: =B26 -> THE GROCERY PEOPLE
A81: =A27 -> 5636042 | B81: =B27 -> THE GROCERY PEOPLE
A82: =A28 -> 5636044 | B82: =B28 -> THE GROCERY PEOPLE
A83: =A29 -> 5636045 | B83: =B29 -> THE GROCERY PEOPLE
A84: =A30 -> 8242570 | B84: =B30 -> THE GROCERY PEOPLE
A85: =A31 -> 8242976 | B85: =B31 -> THE GROCERY PEOPLE
A86: =A32 -> 8243386 | B86: =B32 -> THE GROCERY PEOPLE
A87: =A33 -> 8243603 | B87: =B33 -> THE GROCERY PEOPLE
A88: =A34 -> 5632862 | B88: =B34 -> THE GROCERY PEOPLE | C88: 58.64 | M88: STORE SUPPLIES - STRETCH WRAP
A89: =A35 -> 5632970 | B89: =B35 -> THE GROCERY PEOPLE
A90: =A36 -> 5633158 | B90: =B36 -> THE GROCERY PEOPLE
A91: =A37 -> 5633948 | B91: =B37 -> THE GROCERY PEOPLE
A92: =A38 -> 5634067 | B92: =B38 -> THE GROCERY PEOPLE
A93: =A39 -> 5634483 | B93: =B39 -> THE GROCERY PEOPLE
A94: =A40 -> 5635178 | B94: =B40 -> THE GROCERY PEOPLE
A95: =A41 -> 5635520 | B95: =B41 -> THE GROCERY PEOPLE
A96: =A42 -> 5635521 | B96: =B42 -> THE GROCERY PEOPLE
A97: =A43 -> 5635709 | B97: =B43 -> THE GROCERY PEOPLE
A98: =A44 -> 5635828 | B98: =B44 -> THE GROCERY PEOPLE
A99: =A45 -> 5636043 | B99: =B45 -> THE GROCERY PEOPLE
A100: =A46 -> 5635179 | B100: =B46 -> THE GROCERY PEOPLE
...

Sheet Monday WK2 (9)
B1: Freight | C1: Grocery | E1: Meat | F1: Bakery | G1: Bake off | H1: Deli | I1: Produce | J1: Produce Shrink | K1: Dairy | L1: Pharmacy | M1: Receiving Totals | N1: Total
B2: Name: | C2: ='Sunday WK1 (1)'!C2 -> 0.478 | E2: ='Sunday WK1 (1)'!E2 -> 0.099 | F2: ='Sunday WK1 (1)'!F2 -> 0 | G2: ='Sunday WK1 (1)'!G2 -> 0 | H2: ='Sunday WK1 (1)'!H2 -> 0 | I2: ='Sunday WK1 (1)'!I2 -> 0.159 | J2: ='Sunday WK1 (1)'!J2 -> 0.122 | K2: ='Sunday WK1 (1)'!$K$2 -> 0.142 | L2: ='Sunday WK1 (1)'!L2 -> 0 | N2: =SUM(C2:M2) -> 1
B3: SHANNON | C3: =C2*$N$3 -> 0 | E3: =E2*$N$3 -> 0 | F3: =F2*$N$3 -> 0 | G3: =G2*$N$3 -> 0 | H3: =H2*$N$3 -> 0 | I3: =I2*$N$3 -> 0 | J3: =J2*$N$3 -> 0 | K3: =K2*$N$3 -> 0 | L3: =L2*$N$3 -> 0
A4: Receiving Date: | B4: ='Sunday WK2 (8)'!$B$4+1 -> 46202
A5: Invoice Number | B5: Supplier Name | C5: Grocery Purchases | D5: Tobacco Purchases | E5: Meat Purchases | F5: Bakery Purchases | G5: Bakery In Store | H5: Deli Purchases | I5: Produce Purchases | J5: Produce Shrink | K5: Dairy Purchases | L5: Pharmacy Purchases | M5: GST | N5: Total Invoice**
A6: 92578138 | B6: FRITO LAY CANADA VENDING | C6: =N6-D6-E6-F6-G6-H6-I6-J6-K6-L6-M6-D60-E60-F60-G60-H60-I60-J60-K60-L60-C60 -> 1727.85 | M6: 86.39 | N6: 1814.24
A7: 54132304 | B7: PEPSICO | C7: =N7-D7-E7-F7-G7-H7-I7-J7-K7-L7-M7-D61-E61-F61-G61-H61-I61-J61-K61-L61-C61 -> 2747.84 | M7: 121.75 | N7: 2869.59
A8: 54132303 | B8: PEPSICO | C8: =N8-D8-E8-F8-G8-H8-I8-J8-K8-L8-M8-D62-E62-F62-G62-H62-I62-J62-K62-L62-C62 -> 4446.06 | M8: 168.45 | N8: 4614.51
A9: 226650718099 | B9: CANADA BREAD COMPANY | C9: =N9-D9-E9-F9-G9-H9-I9-J9-K9-L9-M9-D63-E63-F63-G63-H63-I63-J63-K63-L63-C63 -> 1062.23 | N9: 1062.23
A10: 226650718001 | B10: CANADA BREAD COMPANY | C10: =N10-D10-E10-F10-G10-H10-I10-J10-K10-L10-M10-D64-E64-F64-G64-H64-I64-J64-K64-L64-C64 -> -180.32 | N10: -180.32
A11: 82849805 | B11: OLD DUTCH FOODS | C11: =N11-D11-E11-F11-G11-H11-I11-J11-K11-L11-M11-D65-E65-F65-G65-H65-I65-J65-K65-L65-C65 -> 262.61 | M11: 13.13 | N11: 275.74
A12: 126480 | B12: ITALIAN BAKERY | C12: =N12-D12-E12-F12-G12-H12-I12-J12-K12-L12-M12-D66-E66-F66-G66-H66-I66-J66-K66-L66-C66 -> 423.49 | N12: 423.49
A13: INV26-04514 | B13: CAPITAL FINE MEATS | C13: =N13-D13-E13-F13-G13-H13-I13-J13-K13-L13-M13-D67-E67-F67-G67-H67-I67-J67-K67-L67-C67 -> 0 | E13: 2041.15 | N13: 2041.15
C14: =N14-D14-E14-F14-G14-H14-I14-J14-K14-L14-M14-D68-E68-F68-G68-H68-I68-J68-K68-L68-C68 -> 0
C15: =N15-D15-E15-F15-G15-H15-I15-J15-K15-L15-M15-D69-E69-F69-G69-H69-I69-J69-K69-L69-C69 -> 0
C16: =N16-D16-E16-F16-G16-H16-I16-J16-K16-L16-M16-D70-E70-F70-G70-H70-I70-J70-K70-L70-C70 -> 0
C17: =N17-D17-E17-F17-G17-H17-I17-J17-K17-L17-M17-D71-E71-F71-G71-H71-I71-J71-K71-L71-C71 -> 0
C18: =N18-D18-E18-F18-G18-H18-I18-J18-K18-L18-M18-D72-E72-F72-G72-H72-I72-J72-K72-L72-C72 -> 0
C19: =N19-D19-E19-F19-G19-H19-I19-J19-K19-L19-M19-D73-E73-F73-G73-H73-I73-J73-K73-L73-C73 -> 0
C20: =N20-D20-E20-F20-G20-H20-I20-J20-K20-L20-M20-D74-E74-F74-G74-H74-I74-J74-K74-L74-C74 -> 0
C21: =N21-D21-E21-F21-G21-H21-I21-J21-K21-L21-M21-D75-E75-F75-G75-H75-I75-J75-K75-L75-C75 -> 0
C22: =N22-D22-E22-F22-G22-H22-I22-J22-K22-L22-M22-D76-E76-F76-G76-H76-I76-J76-K76-L76-C76 -> 0
C23: =N23-D23-E23-F23-G23-H23-I23-J23-K23-L23-M23-D77-E77-F77-G77-H77-I77-J77-K77-L77-C77 -> 0
C24: =N24-D24-E24-F24-G24-H24-I24-J24-K24-L24-M24-D78-E78-F78-G78-H78-I78-J78-K78-L78-C78 -> 0
C25: =N25-D25-E25-F25-G25-H25-I25-J25-K25-L25-M25-D79-E79-F79-G79-H79-I79-J79-K79-L79-C79 -> 0
... C55: =N55-D55-E55-F55-G55-H55-I55-J55-K55-L55-M55-D109-E109-F109-G109-H109-I109-J109-K109-L109-C109 -> 0
A56: Freight | B56: THE GROCERY PEOPLE | C56: =C3 -> 0 | E56: =E3 -> 0 | F56: =F3 -> 0 | G56: =G3 -> 0 | H56: =H3 -> 0 | I56: =I3 -> 0 | J56: =J3 -> 0 | K56: =K3 -> 0 | L56: =L3 -> 0 | N56: =SUM(C56:M56)+SUM(C118:J118) -> 0
A57: Department Totals | C57: =SUM(C6:C56) -> 10489.76 | D57: =SUM(D6:D56) -> 0 | E57: =SUM(E6:E56) -> 2041.15 | F57: =SUM(F6:F56) -> 0 | G57: =SUM(G6:G56) -> 0 | H57: =SUM(H6:H56) -> 0 | I57: =SUM(I6:I56) -> 0 | J57: =SUM(J6:J56) -> 0 | ... N57: =SUM(N6:N56) -> 12920.63
N58: =IF(SUM(N6:N56)=SUM(C57:M57)+SUM(D110:L110),"","Sum error")
A59: Invoice Number | B59: Supplier Name | C59: Grocery Supplies | D59: Tobacco Supplies | E59: Meat Supplies | F59: Bakery Supplies | G59: B.In store Supplies | H59: Deli Supplies | I59: Produce Supplies | K59: Dairy Supplies | L59: Pharmacy Supplies
A60: =A6 -> 92578138 | B60: =B6 -> FRITO LAY CANADA VENDING
A61: =A7 -> 54132304 | B61: =B7 -> PEPSICO
A62: =A8 -> 54132303 | B62: =B8 -> PEPSICO
A63: =A9 -> 226650718099 | B63: =B9 -> CANADA BREAD COMPANY
A64: =A10 -> 226650718001 | B64: =B10 -> CANADA BREAD COMPANY
A65: =A11 -> 82849805 | B65: =B11 -> OLD DUTCH FOODS
A66: =A12 -> 126480 | B66: =B12 -> ITALIAN BAKERY
A67: =A13 -> INV26-04514 | B67: =B13 -> CAPITAL FINE MEATS
A68: =A14 | B68: =B14
A69: =A15 | B69: =B15
A70: =A16 | B70: =B16
A71: =A17 | B71: =B17
... A109: =A55 | B109: =B55
A110: Department Totals | C110: =SUM(C60:C109) -> 0 | D110: =SUM(D60:D109) -> 0 | E110: =SUM(E60:E109) -> 0 | F110: =SUM(F60:F109) -> 0 | G110: =SUM(G60:G109) -> 0 | H110: =SUM(H60:H109) -> 0 | I110: =SUM(I60:I109) -> 0 | J110: =SUM(J60:J109) -> 0 | K110: =SUM(K60:K109) -> 0 | L110: 0

Sheet Tuesday WK2 (10)
B1: Freight | C1: Grocery | E1: Meat | F1: Bakery | G1: Bake off | H1: Deli | I1: Produce | J1: Produce Shrink | K1: Dairy | L1: Pharmacy | M1: Receiving Totals | N1: Total
B2: Name: | C2: ='Sunday WK1 (1)'!C2 -> 0.478 | E2: ='Sunday WK1 (1)'!E2 -> 0.099 | F2: ='Sunday WK1 (1)'!F2 -> 0 | G2: ='Sunday WK1 (1)'!G2 -> 0 | H2: ='Sunday WK1 (1)'!H2 -> 0 | I2: ='Sunday WK1 (1)'!I2 -> 0.159 | J2: ='Sunday WK1 (1)'!J2 -> 0.122 | K2: ='Sunday WK1 (1)'!$K$2 -> 0.142 | L2: ='Sunday WK1 (1)'!L2 -> 0 | N2: =SUM(C2:M2) -> 1
B3: SHANNON | C3: =C2*$N$3 -> 197.46658 | E3: =E2*$N$3 -> 40.89789 | F3: =F2*$N$3 -> 0 | G3: =G2*$N$3 -> 0 | H3: =H2*$N$3 -> 0 | I3: =I2*$N$3 -> 65.68449 | J3: =J2*$N$3 -> 50.39942 | K3: =K2*$N$3 -> 58.66162 | L3: =L2*$N$3 -> 0 | N3: 413.11
A4: Receiving Date: | B4: ='Monday WK2 (9)'!$B$4+1 -> 46203
A5: Invoice Number | B5: Supplier Name | C5: Grocery Purchases | D5: Tobacco Purchases | E5: Meat Purchases | F5: Bakery Purchases | G5: Bakery In Store | H5: Deli Purchases | I5: Produce Purchases | J5: Produce Shrink | K5: Dairy Purchases | L5: Pharmacy Purchases | M5: GST | N5: Total Invoice**
A6: 32922 | B6: NELLA WEST | C6: =N6-D6-E6-F6-G6-H6-I6-J6-K6-L6-M6-D60-E60-F60-G60-H60-I60-J60-K60-L60-C60 -> 95.52 | M6: 4.78 | N6: 100.3
A7: 4003710022 | B7: SAPUTO DAIRY PRODUCTS | C7: =N7-D7-E7-F7-G7-H7-I7-J7-K7-L7-M7-D61-E61-F61-G61-H61-I61-J61-K61-L61-C61 -> 0 | K7: 2066.77 | M7: 0.5 | N7: 2067.27
A8: 4003710021 | B8: SAPUTO DAIRY PRODUCTS | C8: =N8-D8-E8-F8-G8-H8-I8-J8-K8-L8-M8-D62-E62-F62-G62-H62-I62-J62-K62-L62-C62 -> 0 | K8: 81.29 | N8: 81.29
A9: 6670111 | B9: THE GROCERY PEOPLE | C9: =N9-D9-E9-F9-G9-H9-I9-J9-K9-L9-M9-D63-E63-F63-G63-H63-I63-J63-K63-L63-C63 -> 256.15 | N9: 256.15
A10: 6670958 | B10: THE GROCERY PEOPLE | C10: =N10-D10-E10-F10-G10-H10-I10-J10-K10-L10-M10-D64-E64-F64-G64-H64-I64-J64-K64-L64-C64 -> 1355.42 | N10: 1355.42
A11: 6670959 | B11: THE GROCERY PEOPLE | C11: =N11-D11-E11-F11-G11-H11-I11-J11-K11-L11-M11-D65-E65-F65-G65-H65-I65-J65-K65-L65-C65 -> 37.32 | N11: 37.32
A12: 6671926 | B12: THE GROCERY PEOPLE | C12: =N12-D12-E12-F12-G12-H12-I12-J12-K12-L12-M12-D66-E66-F66-G66-H66-I66-J66-K66-L66-C66 -> 0 | K12: 142.13 | N12: 142.13
A13: 6671927 | B13: THE GROCERY PEOPLE | C13: =N13-D13-E13-F13-G13-H13-I13-J13-K13-L13-M13-D67-E67-F67-G67-H67-I67-J67-K67-L67-C67 -> 0 | K13: 18.47 | N13: 18.47
A14: 6671928 | B14: THE GROCERY PEOPLE | C14: =N14-D14-E14-F14-G14-H14-I14-J14-K14-L14-M14-D68-E68-F68-G68-H68-I68-J68-K68-L68-C68 -> 0 | E14: 119.66 | N14: 119.66
A15: 6669929 | B15: THE GROCERY PEOPLE | C15: =N15-D15-E15-F15-G15-H15-I15-J15-K15-L15-M15-D69-E69-F69-G69-H69-I69-J69-K69-L69-C69 -> 67.34 | N15: 67.34
A16: 5636178 | B16: THE GROCERY PEOPLE | C16: =N16-D16-E16-F16-G16-H16-I16-J16-K16-L16-M16-D70-E70-F70-G70-H70-I70-J70-K70-L70-C70 -> 918.9 | N16: 918.9
A17: 5636320 | B17: THE GROCERY PEOPLE | C17: =N17-D17-E17-F17-G17-H17-I17-J17-K17-L17-M17-D71-E71-F71-G71-H71-I71-J71-K71-L71-C71 -> 309.93 | N17: 309.93
A18: 5636542 | B18: THE GROCERY PEOPLE | C18: =N18-D18-E18-F18-G18-H18-I18-J18-K18-L18-M18-D72-E72-F72-G72-H72-I72-J72-K72-L72-C72 -> 603.08 | N18: 603.08
A19: 5637370 | B19: THE GROCERY PEOPLE | C19: =N19-D19-E19-F19-G19-H19-I19-J19-K19-L19-M19-D73-E73-F73-G73-H73-I73-J73-K73-L73-C73 -> 10914.84 | N19: 10914.84
A20: 5637433 | B20: THE GROCERY PEOPLE | C20: =N20-D20-E20-F20-G20-H20-I20-J20-K20-L20-M20-D74-E74-F74-G74-H74-I74-J74-K74-L74-C74 -> 1858.34 | N20: 1858.34
A21: 5637511 | B21: THE GROCERY PEOPLE | C21: =N21-D21-E21-F21-G21-H21-I21-J21-K21-L21-M21-D75-E75-F75-G75-H75-I75-J75-K75-L75-C75 -> 56.26 | K21: 2196.62 | N21: 2252.88
A22: 5637544 | B22: THE GROCERY PEOPLE | C22: =N22-D22-E22-F22-G22-H22-I22-J22-K22-L22-M22-D76-E76-F76-G76-H76-I76-J76-K76-L76-C76 -> 0 | K22: 678.96 | N22: 678.96
A23: 5636992 | B23: THE GROCERY PEOPLE | C23: =N23-D23-E23-F23-G23-H23-I23-J23-K23-L23-M23-D77-E77-F77-G77-H77-I77-J77-K77-L77-C77 -> 294.72 | E23: 2634.67 | N23: 2929.39
A24: 5636155 | B24: THE GROCERY PEOPLE | C24: =N24-D24-E24-F24-G24-H24-I24-J24-K24-L24-M24-D78-E78-F78-G78-H78-I78-J78-K78-L78-C78 -> 250.38 | N24: 250.38
A25: 5636457 | B25: THE GROCERY PEOPLE | C25: =N25-D25-E25-F25-G25-H25-I25-J25-K25-L25-M25-D79-E79-F79-G79-H79-I79-J79-K79-L79-C79 -> 0 | K25: 2354.24 | N25: 2354.24
A26: 5637011 | B26: THE GROCERY PEOPLE | C26: =N26-D26-E26-F26-G26-H26-I26-J26-K26-L26-M26-D80-E80-F80-G80-H80-I80-J80-K80-L80-C80 -> 175.35 | N26: 175.35
A27: 5637171 | B27: THE GROCERY PEOPLE | C27: =N27-D27-E27-F27-G27-H27-I27-J27-K27-L27-M27-D81-E81-F81-G81-H81-I81-J81-K81-L81-C81 -> 19618.78 | N27: 19618.78
A28: 5637215 | B28: THE GROCERY PEOPLE | C28: =N28-D28-E28-F28-G28-H28-I28-J28-K28-L28-M28-D82-E82-F82-G82-H82-I82-J82-K82-L82-C82 -> 208.1 | N28: 208.1
A29: 5637216 | B29: THE GROCERY PEOPLE | C29: =N29-D29-E29-F29-G29-H29-I29-J29-K29-L29-M29-D83-E83-F83-G83-H83-I83-J83-K83-L83-C83 -> 49.44 | N29: 49.44
A30: 5637995 | B30: THE GROCERY PEOPLE | C30: =N30-D30-E30-F30-G30-H30-I30-J30-K30-L30-M30-D84-E84-F84-G84-H84-I84-J84-K84-L84-C84 -> 0 | I30: 91.9 | N30: 91.9
A31: 5638018 | B31: THE GROCERY PEOPLE | C31: =N31-D31-E31-F31-G31-H31-I31-J31-K31-L31-M31-D85-E85-F85-G85-H85-I85-J85-K85-L85-C85 -> 0 | I31: 554.27 | N31: 554.27
A32: 5638025 | B32: THE GROCERY PEOPLE | C32: =N32-D32-E32-F32-G32-H32-I32-J32-K32-L32-M32-D86-E86-F86-G86-H86-I86-J86-K86-L86-C86 -> 0 | I32: 4267.34 | N32: 4267.34
A33: 5638041 | B33: THE GROCERY PEOPLE | C33: =N33-D33-E33-F33-G33-H33-I33-J33-K33-L33-M33-D87-E87-F87-G87-H87-I87-J87-K87-L87-C87 -> 0 | I33: 544.86 | N33: 544.86
A34: 6652917 | B34: FEDERATED CO-OPERATIVES | C34: =N34-D34-E34-F34-G34-H34-I34-J34-K34-L34-M34-D88-E88-F88-G88-H88-I88-J88-K88-L88-C88 -> 74.28 | N34: 74.28
A35: 6653196 | B35: FEDERATED CO-OPERATIVES | C35: =N35-D35-E35-F35-G35-H35-I35-J35-K35-L35-M35-D89-E89-F89-G89-H89-I89-J89-K89-L89-C89 -> 102.96 | N35: 102.96
A36: 6663764 | B36: FEDERATED CO-OPERATIVES | C36: =N36-D36-E36-F36-G36-H36-I36-J36-K36-L36-M36-D90-E90-F90-G90-H90-I90-J90-K90-L90-C90 -> 0 | N36: 44.69 | O36: STORE SUPPLIES - PENS, DBL TAPE, DRY ERASE
A37: 118511 | B37: KENNELLI SPRINGS | C37: =N37-D37-E37-F37-G37-H37-I37-J37-K37-L37-M37-D91-E91-F91-G91-H91-I91-J91-K91-L91-C91 -> 180 | M37: 0.75 | N37: 180.75
A38: 53048735061 | B38: COCA COLA CANADA BOTTLING | C38: =N38-D38-E38-F38-G38-H38-I38-J38-K38-L38-M38-D92-E92-F92-G92-H92-I92-J92-K92-L92-C92 -> 5865.9 | M38: 240.04 | N38: 6105.94
A39: 53048735062 | B39: COCA COLA CANADA BOTTLING | C39: =N39-D39-E39-F39-G39-H39-I39-J39-K39-L39-M39-D93-E93-F93-G93-H93-I93-J93-K93-L93-C93 -> 487.52 | M39: 22.19 | N39: 509.71
A40: 92794355 | B40: FRITO LAY CANADA RETAIL | C40: =N40-D40-E40-F40-G40-H40-I40-J40-K40-L40-M40-D94-E94-F94-G94-H94-I94-J94-K94-L94-C94 -> 580.75 | M40: 26.29 | N40: 607.04
A41: 77684065 | B41: FRITO LAY CANADA RETAIL | C41: =N41-D41-E41-F41-G41-H41-I41-J41-K41-L41-M41-D95-E95-F95-G95-H95-I95-J95-K95-L95-C95 -> -48.56 | M41: -2.43 | N41: -50.99
A42: 7726181003 | B42: UNITED DISTRIBUTION | C42: =N42-D42-E42-F42-G42-H42-I42-J42-K42-L42-M42-D96-E96-F96-G96-H96-I96-J96-K96-L96-C96 -> 4040.06 | M42: 142.42 | N42: 4182.48
C43: =N43-D43-E43-F43-G43-H43-I43-J43-K43-L43-M43-D97-E97-F97-G97-H97-I97-J97-K97-L97-C97 -> 0
C44: =N44-D44-E44-F44-G44-H44-I44-J44-K44-L44-M44-D98-E98-F98-G98-H98-I98-J98-K98-L98-C98 -> 0
C45: =N45-D45-E45-F45-G45-H45-I45-J45-K45-L45-M45-D99-E99-F99-G99-H99-I99-J99-K99-L99-C99 -> 0
C46: =N46-D46-E46-F46-G46-H46-I46-J46-K46-L46-M46-D100-E100-F100-G100-H100-I100-J100-K100-L100-C100 -> 0
C47: =N47-D47-E47-F47-G47-H47-I47-J47-K47-L47-M47-D101-E101-F101-G101-H101-I101-J101-K101-L101-C101 -> 0
C48: =N48-D48-E48-F48-G48-H48-I48-J48-K48-L48-M48-D102-E102-F102-G102-H102-I102-J102-K102-L102-C102 -> 0
C49: =N49-D49-E49-F49-G49-H49-I49-J49-K49-L49-M49-D103-E103-F103-G103-H103-I103-J103-K103-L103-C103 -> 0
C50: =N50-D50-E50-F50-G50-H50-I50-J50-K50-L50-M50-D104-E104-F104-G104-H104-I104-J104-K104-L104-C104 -> 0
C51: =N51-D51-E51-F51-G51-H51-I51-J51-K51-L51-M51-D105-E105-F105-G105-H105-I105-J105-K105-L105-C105 -> 0
C52: =N52-D52-E52-F52-G52-H52-I52-J52-K52-L52-M52-D106-E106-F106-G106-H106-I106-J106-K106-L106-C106 -> 0
C53: =N53-D53-E53-F53-G53-H53-I53-J53-K53-L53-M53-D107-E107-F107-G107-H107-I107-J107-K107-L107-C107 -> 0
C54: =N54-D54-E54-F54-G54-H54-I54-J54-K54-L54-M54-D108-E108-F108-G108-H108-I108-J108-K108-L108-C108 -> 0
C55: =N55-D55-E55-F55-G55-H55-I55-J55-K55-L55-M55-D109-E109-F109-G109-H109-I109-J109-K109-L109-C109 -> 0
A56: Freight | B56: THE GROCERY PEOPLE | C56: =C3 -> 197.46658 | E56: =E3 -> 40.89789 | F56: =F3 -> 0 | G56: =G3 -> 0 | H56: =H3 -> 0 | I56: =I3 -> 65.68449 | J56: =J3 -> 50.39942 | K56: =K3 -> 58.66162 | L56: =L3 -> 0 | N56: =SUM(C56:M56)+SUM(C118:J118) -> 413.11 | O56: BM#8502093, BOL REF#4852915,4852916,4852914,4852918,4852917
A57: Department Totals | C57: =SUM(C6:C56) -> 48550.247 | D57: =SUM(D6:D56) -> 0 | E57: =SUM(E6:E56) -> 2795.2279 | F57: =SUM(F6:F56) -> 0 | G57: =SUM(G6:G56) -> 0 | H57: =SUM(H6:H56) -> 0 | I57: =SUM(I6:I56) -> 5524.0545 | J57: =SUM(J6:J56) -> 50.39942 | ... N57: =SUM(N6:N56) -> 64996.3
N58: =IF(SUM(N6:N56)=SUM(C57:M57)+SUM(C110:K110),"","Sum error")
A59: Invoice Number | B59: Supplier Name | C59: Grocery Supplies | D59: Tobacco Supplies | E59: Meat Supplies | F59: Bakery Supplies | G59: B.In store Supplies | H59: Deli Supplies | I59: Produce Supplies | K59: Dairy Supplies | L59: Pharmacy Supplies
A60: =A6 -> 32922 | B60: =B6 -> NELLA WEST
A61: =A7 -> 4003710022 | B61: =B7 -> SAPUTO DAIRY PRODUCTS
A62: =A8 -> 4003710021 | B62: =B8 -> SAPUTO DAIRY PRODUCTS
A63: =A9 -> 6670111 | B63: =B9 -> THE GROCERY PEOPLE
A64: =A10 -> 6670958 | B64: =B10 -> THE GROCERY PEOPLE
A65: =A11 -> 6670959 | B65: =B11 -> THE GROCERY PEOPLE
A66: =A12 -> 6671926 | B66: =B12 -> THE GROCERY PEOPLE
A67: =A13 -> 6671927 | B67: =B13 -> THE GROCERY PEOPLE
A68: =A14 -> 6671928 | B68: =B14 -> THE GROCERY PEOPLE
A69: =A15 -> 6669929 | B69: =B15 -> THE GROCERY PEOPLE
A70: =A16 -> 5636178 | B70: =B16 -> THE GROCERY PEOPLE
A71: =A17 -> 5636320 | B71: =B17 -> THE GROCERY PEOPLE
... A89: =A35 -> 6653196 | B89: =B35 -> FEDERATED CO-OPERATIVES
A90: =A36 -> 6663764 | B90: =B36 -> FEDERATED CO-OPERATIVES | C90: 44.69 | M90: STORE SUPPLIES - PENS, DBLE TAPE, DRYLINE CORRECTION
A91: =A37 -> 118511 | B91: =B37 -> KENNELLI SPRINGS
A92: =A38 -> 53048735061 | B92: =B38 -> COCA COLA CANADA BOTTLING
A93: =A39 -> 53048735062 | B93: =B39 -> COCA COLA CANADA BOTTLING
A94: =A40 -> 92794355 | B94: =B40 -> FRITO LAY CANADA RETAIL
A95: =A41 -> 77684065 | B95: =B41 -> FRITO LAY CANADA RETAIL
A96: =A42 -> 7726181003 | B96: =B42 -> UNITED DISTRIBUTION
A97: =A43 | B97: =B43
A98: =A44 | B98: =B44
A99: =A45 | B99: =B45
A100: =A46 | B100: =B46
A101: =A47 | B101: =B47
A102: =A48 | B102: =B48
... A109: =A55 | B109: =B55
A110: Department Totals | C110: =SUM(C60:C109) -> 44.69 | D110: =SUM(D60:D109) -> 0 | E110: =SUM(E60:E109) -> 0 | F110: =SUM(F60:F109) -> 0 | G110: =SUM(G60:G109) -> 0 | H110: =SUM(H60:H109) -> 0 | I110: =SUM(I60:I109) -> 0 | J110: =SUM(J60:J109) -> 0 | K110: =SUM(K60:K109) -> 0 | L110: 0

Sheet Wednesday WK2 (11)
B1: Freight | C1: Grocery | E1: Meat | F1: Bakery | G1: Bake off | H1: Deli | I1: Produce | J1: Produce Shrink | K1: Dairy | L1: Pharmacy | M1: Receiving Totals | N1: Total
B2: Name: | C2: ='Sunday WK1 (1)'!C2 -> 0.478 | E2: ='Sunday WK1 (1)'!E2 -> 0.099 | F2: ='Sunday WK1 (1)'!F2 -> 0 | G2: ='Sunday WK1 (1)'!G2 -> 0 | H2: ='Sunday WK1 (1)'!H2 -> 0 | I2: ='Sunday WK1 (1)'!I2 -> 0.159 | J2: ='Sunday WK1 (1)'!J2 -> 0.122 | K2: ='Sunday WK1 (1)'!$K$2 -> 0.142 | L2: ='Sunday WK1 (1)'!L2 -> 0 | N2: =SUM(C2:M2) -> 1
B3: SHANNON | C3: =C2*$N$3 -> 0 | E3: =E2*$N$3 -> 0 | F3: =F2*$N$3 -> 0 | G3: =G2*$N$3 -> 0 | H3: =H2*$N$3 -> 0 | I3: =I2*$N$3 -> 0 | J3: =J2*$N$3 -> 0 | K3: =K2*$N$3 -> 0 | L3: =L2*$N$3 -> 0
A4: Receiving Date: | B4: ='Tuesday WK2 (10)'!B4+1 -> 46204
A5: Invoice Number | B5: Supplier Name | C5: Grocery Purchases | D5: Tobacco Purchases | E5: Meat Purchases | F5: Bakery Purchases | G5: Bakery In Store | H5: Deli Purchases | I5: Produce Purchases | J5: Produce Shrink | K5: Dairy Purchases | L5: Pharmacy Purchases | M5: GST | N5: Total Invoice**
A6: 82849818 | B6: OLD DUTCH FOODS | C6: =N6-D6-E6-F6-G6-H6-I6-J6-K6-L6-M6-D60-E60-F60-G60-H60-I60-J60-K60-L60-C60 -> 113.58 | M6: 5.68 | N6: 119.26
C7: =N7-D7-E7-F7-G7-H7-I7-J7-K7-L7-M7-D61-E61-F61-G61-H61-I61-J61-K61-L61-C61 -> 0
C8: =N8-D8-E8-F8-G8-H8-I8-J8-K8-L8-M8-D62-E62-F62-G62-H62-I62-J62-K62-L62-C62 -> 0
C9: =N9-D9-E9-F9-G9-H9-I9-J9-K9-L9-M9-D63-E63-F63-G63-H63-I63-J63-K63-L63-C63 -> 0
C10: =N10-D10-E10-F10-G10-H10-I10-J10-K10-L10-M10-D64-E64-F64-G64-H64-I64-J64-K64-L64-C64 -> 0
C11: =N11-D11-E11-F11-G11-H11-I11-J11-K11-L11-M11-D65-E65-F65-G65-H65-I65-J65-K65-L65-C65 -> 0
C12: =N12-D12-E12-F12-G12-H12-I12-J12-K12-L12-M12-D66-E66-F66-G66-H66-I66-J66-K66-L66-C66 -> 0
C13: =N13-D13-E13-F13-G13-H13-I13-J13-K13-L13-M13-D67-E67-F67-G67-H67-I67-J67-K67-L67-C67 -> 0
C14: =N14-D14-E14-F14-G14-H14-I14-J14-K14-L14-M14-D68-E68-F68-G68-H68-I68-J68-K68-L68-C68 -> 0
C15: =N15-D15-E15-F15-G15-H15-I15-J15-K15-L15-M15-D69-E69-F69-G69-H69-I69-J69-K69-L69-C69 -> 0
C16: =N16-D16-E16-F16-G16-H16-I16-J16-K16-L16-M16-D70-E70-F70-G70-H70-I70-J70-K70-L70-C70 -> 0
C17: =N17-D17-E17-F17-G17-H17-I17-J17-K17-L17-M17-D71-E71-F71-G71-H71-I71-J71-K71-L71-C71 -> 0
C18: =N18-D18-E18-F18-G18-H18-I18-J18-K18-L18-M18-D72-E72-F72-G72-H72-I72-J72-K72-L72-C72 -> 0
... C55: =N55-D55-E55-F55-G55-H55-I55-J55-K55-L55-M55-D109-E109-F109-G109-H109-I109-J109-K109-L109-C109 -> 0
A56: Freight | B56: THE GROCERY PEOPLE | C56: =C3 -> 0 | E56: =E3 -> 0 | F56: =F3 -> 0 | G56: =G3 -> 0 | H56: =H3 -> 0 | I56: =I3 -> 0 | J56: =J3 -> 0 | K56: =K3 -> 0 | L56: =L3 -> 0 | N56: =SUM(C56:M56)+SUM(C118:J118) -> 0 | O56: BM#7931352, BOL REF#4601404
A57: Department Totals | C57: =SUM(C6:C56) -> 113.58 | D57: =SUM(D6:D56) -> 0 | E57: =SUM(E6:E56) -> 0 | F57: =SUM(F6:F56) -> 0 | G57: =SUM(G6:G56) -> 0 | H57: =SUM(H6:H56) -> 0 | I57: =SUM(I6:I56) -> 0 | J57: =SUM(J6:J56) -> 0 | ... N57: =SUM(N6:N56) -> 119.26
N58: =IF(SUM(N6:N56)=SUM(C57:M57)+SUM(D110:L110),"","Sum error")
A59: Invoice Number | B59: Supplier Name | C59: Grocery Supplies | D59: Tobacco Supplies | E59: Meat Supplies | F59: Bakery Supplies | G59: B.In store Supplies | H59: Deli Supplies | I59: Produce Supplies | K59: Dairy Supplies | L59: Pharmacy Supplies
A60: =A6 -> 82849818 | B60: =B6 -> OLD DUTCH FOODS
A61: =A7 | B61: =B7
A62: =A8 | B62: =B8
A63: =A9 | B63: =B9
A64: =A10 | B64: =B10
A65: =A11 | B65: =B11
A66: =A12 | B66: =B12
A67: =A13 | B67: =B13
A68: =A14 | B68: =B14
A69: =A15 | B69: =B15
A70: =A16 | B70: =B16
A71: =A17 | B71: =B17
... A109: =A55 | B109: =B55
A110: Department Totals | C110: =SUM(C60:C109) -> 0 | D110: =SUM(D60:D109) -> 0 | E110: =SUM(E60:E109) -> 0 | F110: =SUM(F60:F109) -> 0 | G110: =SUM(G60:G109) -> 0 | H110: =SUM(H60:H109) -> 0 | I110: =SUM(I60:I109) -> 0 | J110: =SUM(J60:J109) -> 0 | K110: =SUM(K60:K109) -> 0 | L110: 0

Sheet Thursday WK2 (12)
B1: Freight | C1: Grocery | E1: Meat | F1: Bakery | G1: Bake off | H1: Deli | I1: Produce | J1: Produce Shrink | K1: Dairy | L1: Pharmacy | M1: Receiving Totals | N1: Total
B2: Name: | C2: ='Sunday WK1 (1)'!C2 -> 0.478 | E2: ='Sunday WK1 (1)'!E2 -> 0.099 | F2: ='Sunday WK1 (1)'!F2 -> 0 | G2: ='Sunday WK1 (1)'!G2 -> 0 | H2: ='Sunday WK1 (1)'!H2 -> 0 | I2: ='Sunday WK1 (1)'!I2 -> 0.159 | J2: ='Sunday WK1 (1)'!J2 -> 0.122 | K2: ='Sunday WK1 (1)'!$K$2 -> 0.142 | L2: ='Sunday WK1 (1)'!L2 -> 0 | N2: =SUM(C2:M2) -> 1
B3: SHANNON | C3: =C2*$N$3 -> 121.75616 | E3: =E2*$N$3 -> 25.21728 | F3: =F2*$N$3 -> 0 | G3: =G2*$N$3 -> 0 | H3: =H2*$N$3 -> 0 | I3: =I2*$N$3 -> 40.50048 | J3: =J2*$N$3 -> 31.07584 | K3: =K2*$N$3 -> 36.17024 | L3: =L2*$N$3 -> 0 | N3: 254.72
A4: Receiving Date: | B4: ='Wednesday WK2 (11)'!$B$4+1 -> 46205
A5: Invoice Number | B5: Supplier Name | C5: Grocery Purchases | D5: Tobacco Purchases | E5: Meat Purchases | F5: Bakery Purchases | G5: Bakery In Store | H5: Deli Purchases | I5: Produce Purchases | J5: Produce Shrink | K5: Dairy Purchases | L5: Pharmacy Purchases | M5: GST | N5: Total Invoice**
A6: 4003725681 | B6: SAPUTO DAIRY PRODUCTS | C6: =N6-D6-E6-F6-G6-H6-I6-J6-K6-L6-M6-D60-E60-F60-G60-H60-I60-J60-K60-L60-C60 -> 0 | K6: 2407.1 | N6: 2407.1
A7: 6672805 | B7: THE GROCERY PEOPLE | C7: =N7-D7-E7-F7-G7-H7-I7-J7-K7-L7-M7-D61-E61-F61-G61-H61-I61-J61-K61-L61-C61 -> 409.24 | E7: 41.99 | N7: 451.23
A8: 6674089 | B8: THE GROCERY PEOPLE | C8: =N8-D8-E8-F8-G8-H8-I8-J8-K8-L8-M8-D62-E62-F62-G62-H62-I62-J62-K62-L62-C62 -> 0 | K8: 118.44 | N8: 118.44
A9: 6672317 | B9: THE GROCERY PEOPLE | C9: =N9-D9-E9-F9-G9-H9-I9-J9-K9-L9-M9-D63-E63-F63-G63-H63-I63-J63-K63-L63-C63 -> 0 | E9: 1966.47 | N9: 1966.47
A10: 5638271 | B10: THE GROCERY PEOPLE | C10: =N10-D10-E10-F10-G10-H10-I10-J10-K10-L10-M10-D64-E64-F64-G64-H64-I64-J64-K64-L64-C64 -> 346.62 | N10: 346.62
A11: 5638389 | B11: THE GROCERY PEOPLE | C11: =N11-D11-E11-F11-G11-H11-I11-J11-K11-L11-M11-D65-E65-F65-G65-H65-I65-J65-K65-L65-C65 -> 123.84 | N11: 123.84
A12: 5639394 | B12: THE GROCERY PEOPLE | C12: =N12-D12-E12-F12-G12-H12-I12-J12-K12-L12-M12-D66-E66-F66-G66-H66-I66-J66-K66-L66-C66 -> 155.71 | E12: 702.98 | N12: 858.69
A13: 5639528 | B13: THE GROCERY PEOPLE | C13: =N13-D13-E13-F13-G13-H13-I13-J13-K13-L13-M13-D67-E67-F67-G67-H67-I67-J67-K67-L67-C67 -> 0 | E13: 1196.54 | N13: 1196.54
A14: 5639615 | B14: THE GROCERY PEOPLE | C14: =N14-D14-E14-F14-G14-H14-I14-J14-K14-L14-M14-D68-E68-F68-G68-H68-I68-J68-K68-L68-C68 -> 0 | E14: 1588.44 | N14: 1588.44
A15: 5639857 | B15: THE GROCERY PEOPLE | C15: =N15-D15-E15-F15-G15-H15-I15-J15-K15-L15-M15-D69-E69-F69-G69-H69-I69-J69-K69-L69-C69 -> 0 | K15: 880.57 | N15: 880.57
A16: 5640349 | B16: THE GROCERY PEOPLE | C16: =N16-D16-E16-F16-G16-H16-I16-J16-K16-L16-M16-D70-E70-F70-G70-H70-I70-J70-K70-L70-C70 -> 2329.06 | E16: 115.33 | N16: 2444.39
A17: 5640350 | B17: THE GROCERY PEOPLE | C17: =N17-D17-E17-F17-G17-H17-I17-J17-K17-L17-M17-D71-E71-F71-G71-H71-I71-J71-K71-L71-C71 -> 4600.88 | N17: 4600.88
A18: 5640351 | B18: THE GROCERY PEOPLE | C18: =N18-D18-E18-F18-G18-H18-I18-J18-K18-L18-M18-D72-E72-F72-G72-H72-I72-J72-K72-L72-C72 -> 560.69 | N18: 560.69
A19: 8245664 | B19: THE GROCERY PEOPLE | C19: =N19-D19-E19-F19-G19-H19-I19-J19-K19-L19-M19-D73-E73-F73-G73-H73-I73-J73-K73-L73-C73 -> 0 | E19: 532.06 | N19: 532.06
A20: 5637937 | B20: THE GROCERY PEOPLE | C20: =N20-D20-E20-F20-G20-H20-I20-J20-K20-L20-M20-D74-E74-F74-G74-H74-I74-J74-K74-L74-C74 -> 0 | E20: 897.24 | N20: 897.24
A21: 5638269 | B21: THE GROCERY PEOPLE | C21: =N21-D21-E21-F21-G21-H21-I21-J21-K21-L21-M21-D75-E75-F75-G75-H75-I75-J75-K75-L75-C75 -> 0 | E21: 641.88 | N21: 641.88
A22: 5638270 | B22: THE GROCERY PEOPLE | C22: =N22-D22-E22-F22-G22-H22-I22-J22-K22-L22-M22-D76-E76-F76-G76-H76-I76-J76-K76-L76-C76 -> 53.56 | N22: 53.56
A23: 5639276 | B23: THE GROCERY PEOPLE | C23: =N23-D23-E23-F23-G23-H23-I23-J23-K23-L23-M23-D77-E77-F77-G77-H77-I77-J77-K77-L77-C77 -> 178.32 | N23: 178.32
A24: 5639614 | B24: THE GROCERY PEOPLE | C24: =N24-D24-E24-F24-G24-H24-I24-J24-K24-L24-M24-D78-E78-F78-G78-H78-I78-J78-K78-L78-C78 -> 97.64 | N24: 97.64
A25: 5639856 | B25: THE GROCERY PEOPLE | C25: =N25-D25-E25-F25-G25-H25-I25-J25-K25-L25-M25-D79-E79-F79-G79-H79-I79-J79-K79-L79-C79 -> 0 | K25: 693.6 | N25: 693.6
A26: 5640151 | B26: THE GROCERY PEOPLE | C26: =N26-D26-E26-F26-G26-H26-I26-J26-K26-L26-M26-D80-E80-F80-G80-H80-I80-J80-K80-L80-C80 -> 259.96 | N26: 259.96
A27: 5639221 | B27: THE GROCERY PEOPLE | C27: =N27-D27-E27-F27-G27-H27-I27-J27-K27-L27-M27-D81-E81-F81-G81-H81-I81-J81-K81-L81-C81 -> 0 | I27: 146 | N27: 146
A28: 5639264 | B28: THE GROCERY PEOPLE | C28: =N28-D28-E28-F28-G28-H28-I28-J28-K28-L28-M28-D82-E82-F82-G82-H82-I82-J82-K82-L82-C82 -> 0 | I28: 132.9 | N28: 132.9
A29: 5640622 | B29: THE GROCERY PEOPLE | C29: =N29-D29-E29-F29-G29-H29-I29-J29-K29-L29-M29-D83-E83-F83-G83-H83-I83-J83-K83-L83-C83 -> 0 | E29: 26.7 | N29: 26.7
A30: 5640769 | B30: THE GROCERY PEOPLE | C30: =N30-D30-E30-F30-G30-H30-I30-J30-K30-L30-M30-D84-E84-F84-G84-H84-I84-J84-K84-L84-C84 -> 0 | I30: 187.85 | N30: 187.85
A31: 5640780 | B31: THE GROCERY PEOPLE | C31: =N31-D31-E31-F31-G31-H31-I31-J31-K31-L31-M31-D85-E85-F85-G85-H85-I85-J85-K85-L85-C85 -> 0 | I31: 2469.61 | N31: 2469.61
A32: 5640791 | B32: THE GROCERY PEOPLE | C32: =N32-D32-E32-F32-G32-H32-I32-J32-K32-L32-M32-D86-E86-F86-G86-H86-I86-J86-K86-L86-C86 -> 0 | I32: 301.16 | N32: 301.16
A33: 5638048 | B33: THE GROCERY PEOPLE | C33: =N33-D33-E33-F33-G33-H33-I33-J33-K33-L33-M33-D87-E87-F87-G87-H87-I87-J87-K87-L87-C87 -> 6578.7 | E33: 495.9 | K33: 114.2 | N33: 7188.8 | O33: TGP C&C KAMLOOPS
A34: 5638263 | B34: THE GROCERY PEOPLE | C34: =N34-D34-E34-F34-G34-H34-I34-J34-K34-L34-M34-D88-E88-F88-G88-H88-I88-J88-K88-L88-C88 -> 5641.07 | E34: 6254.54 | K34: 1416.11 | N34: 13311.72 | O34: TGP C&C KAMLOOPS
A35: 5638386 | B35: THE GROCERY PEOPLE | C35: =N35-D35-E35-F35-G35-H35-I35-J35-K35-L35-M35-D89-E89-F89-G89-H89-I89-J89-K89-L89-C89 -> 2024.26 | K35: 54.86 | N35: 2079.12 | O35: TGP C&C KAMLOOPS
A36: 5638387 | B36: THE GROCERY PEOPLE | C36: =N36-D36-E36-F36-G36-H36-I36-J36-K36-L36-M36-D90-E90-F90-G90-H90-I90-J90-K90-L90-C90 -> 130.18 | K36: 40 | N36: 170.18 | O36: TGP C&C KAMLOOPS
A37: 5639458 | B37: THE GROCERY PEOPLE | C37: =N37-D37-E37-F37-G37-H37-I37-J37-K37-L37-M37-D91-E91-F91-G91-H91-I91-J91-K91-L91-C91 -> 0 | I37: 1482.8 | N37: 1482.8 | O37: TGP C&C KAMLOOPS
A38: 6658229 | B38: FEDERATED CO-OPERATIVES | C38: =N38-D38-E38-F38-G38-H38-I38-J38-K38-L38-M38-D92-E92-F92-G92-H92-I92-J92-K92-L92-C92 -> 47.58 | N38: 47.58 | O38: TGP C&C KAMLOOPS
A39: 6658230 | B39: FEDERATED CO-OPERATIVES | C39: =N39-D39-E39-F39-G39-H39-I39-J39-K39-L39-M39-D93-E93-F93-G93-H93-I93-J93-K93-L93-C93 -> 50.16 | N39: 50.16 | O39: TGP C&C KAMLOOPS
A40: 6668860 | B40: FEDERATED CO-OPERATIVES | C40: =N40-D40-E40-F40-G40-H40-I40-J40-K40-L40-M40-D94-E94-F94-G94-H94-I94-J94-K94-L94-C94 -> 25 | N40: 25 | O40: TGP C&C KAMLOOPS
A41: 6669395 | B41: FEDERATED CO-OPERATIVES | C41: =N41-D41-E41-F41-G41-H41-I41-J41-K41-L41-M41-D95-E95-F95-G95-H95-I95-J95-K95-L95-C95 -> 23.71 | N41: 23.71 | O41: TGP C&C KAMLOOPS
A42: 126552 | B42: ITALIAN BAKERY | C42: =N42-D42-E42-F42-G42-H42-I42-J42-K42-L42-M42-D96-E96-F96-G96-H96-I96-J96-K96-L96-C96 -> 349.02 | N42: 349.02
A43: 226650718381 | B43: CANADA BREAD COMPANY | C43: =N43-D43-E43-F43-G43-H43-I43-J43-K43-L43-M43-D97-E97-F97-G97-H97-I97-J97-K97-L97-C97 -> 87.13 | N43: 87.13
A44: 1120443 | B44: CALAHOO MEATS | C44: =N44-D44-E44-F44-G44-H44-I44-J44-K44-L44-M44-D98-E98-F98-G98-H98-I98-J98-K98-L98-C98 -> 0 | E44: 3024.7 | N44: 3024.7
A45: 2882618305 | B45: DIRECT PLUS FOOD GROUP | C45: =N45-D45-E45-F45-G45-H45-I45-J45-K45-L45-M45-D99-E99-F99-G99-H99-I99-J99-K99-L99-C99 -> 0 | E45: 1140.7 | N45: 1140.7
A46: 2882618307 | B46: DIRECT PLUS FOOD GROUP | C46: =N46-D46-E46-F46-G46-H46-I46-J46-K46-L46-M46-D100-E100-F100-G100-H100-I100-J100-K100-L100-C100 -> 330.76 | N46: 330.76
A47: 2882618306 | B47: DIRECT PLUS FOOD GROUP | C47: =N47-D47-E47-F47-G47-H47-I47-J47-K47-L47-M47-D101-E101-F101-G101-H101-I101-J101-K101-L101-C101 -> 0 | E47: 37.28 | N47: 37.28
C48: =N48-D48-E48-F48-G48-H48-I48-J48-K48-L48-M48-D102-E102-F102-G102-H102-I102-J102-K102-L102-C102 -> 0
C49: =N49-D49-E49-F49-G49-H49-I49-J49-K49-L49-M49-D103-E103-F103-G103-H103-I103-J103-K103-L103-C103 -> 0
C50: =N50-D50-E50-F50-G50-H50-I50-J50-K50-L50-M50-D104-E104-F104-G104-H104-I104-J104-K104-L104-C104 -> 0
C51: =N51-D51-E51-F51-G51-H51-I51-J51-K51-L51-M51-D105-E105-F105-G105-H105-I105-J105-K105-L105-C105 -> 0
C52: =N52-D52-E52-F52-G52-H52-I52-J52-K52-L52-M52-D106-E106-F106-G106-H106-I106-J106-K106-L106-C106 -> 0
C53: =N53-D53-E53-F53-G53-H53-I53-J53-K53-L53-M53-D107-E107-F107-G107-H107-I107-J107-K107-L107-C107 -> 0
C54: =N54-D54-E54-F54-G54-H54-I54-J54-K54-L54-M54-D108-E108-F108-G108-H108-I108-J108-K108-L108-C108 -> 0
C55: =N55-D55-E55-F55-G55-H55-I55-J55-K55-L55-M55-D109-E109-F109-G109-H109-I109-J109-K109-L109-C109 -> 0
A56: Freight | B56: THE GROCERY PEOPLE | C56: =C3 -> 121.75616 | E56: =E3 -> 25.21728 | F56: =F3 -> 0 | G56: =G3 -> 0 | H56: =H3 -> 0 | I56: =I3 -> 40.50048 | J56: =J3 -> 31.07584 | K56: =K3 -> 36.17024 | L56: =L3 -> 0 | N56: =SUM(C56:M56)+SUM(C118:J118) -> 254.72 | O56: BM#8508718, BOL REF#4854140,4854137,4854139,4854138,4854141, BM#8505398, BOL REF#4853675,4853674,4853673
A57: Department Totals | C57: =SUM(C6:C56) -> 24524.846 | D57: =SUM(D6:D56) -> 0 | E57: =SUM(E6:E56) -> 18687.967 | F57: =SUM(F6:F56) -> 0 | G57: =SUM(G6:G56) -> 0 | H57: =SUM(H6:H56) -> 0 | I57: =SUM(I6:I56) -> 4760.8205 | J57: =SUM(J6:J56) -> 31.07584 | ... N57: =SUM(N6:N56) -> 53765.76
N58: =IF(SUM(N6:N56)=SUM(C57:M57)+SUM(D110:L110),"","Sum error")
A59: Invoice Number | B59: Supplier Name | C59: Grocery Supplies | D59: Tobacco Supplies | E59: Meat Supplies | F59: Bakery Supplies | G59: B.In store Supplies | H59: Deli Supplies | I59: Produce Supplies | K59: Dairy Supplies | L59: Pharmacy Supplies
A60: =A6 -> 4003725681 | B60: =B6 -> SAPUTO DAIRY PRODUCTS
A61: =A7 -> 6672805 | B61: =B7 -> THE GROCERY PEOPLE
A62: =A8 -> 6674089 | B62: =B8 -> THE GROCERY PEOPLE
A63: =A9 -> 6672317 | B63: =B9 -> THE GROCERY PEOPLE
A64: =A10 -> 5638271 | B64: =B10 -> THE GROCERY PEOPLE
A65: =A11 -> 5638389 | B65: =B11 -> THE GROCERY PEOPLE
A66: =A12 -> 5639394 | B66: =B12 -> THE GROCERY PEOPLE
A67: =A13 -> 5639528 | B67: =B13 -> THE GROCERY PEOPLE
A68: =A14 -> 5639615 | B68: =B14 -> THE GROCERY PEOPLE
A69: =A15 -> 5639857 | B69: =B15 -> THE GROCERY PEOPLE
A70: =A16 -> 5640349 | B70: =B16 -> THE GROCERY PEOPLE
A71: =A17 -> 5640350 | B71: =B17 -> THE GROCERY PEOPLE
... A109: =A55 | B109: =B55
A110: Department Totals | C110: =SUM(C60:C109) -> 0 | D110: =SUM(D60:D109) -> 0 | E110: =SUM(E60:E109) -> 0 | F110: =SUM(F60:F109) -> 0 | G110: =SUM(G60:G109) -> 0 | H110: =SUM(H60:H109) -> 0 | I110: =SUM(I60:I109) -> 0 | J110: =SUM(J60:J109) -> 0 | K110: =SUM(K60:K109) -> 0 | L110: 0

Sheet Friday WK2 (13)
B1: Freight | C1: Grocery | E1: Meat | F1: Bakery | G1: Bake off | H1: Deli | I1: Produce | J1: Produce Shrink | K1: Dairy | L1: Pharmacy | M1: Receiving Totals | N1: Total
B2: Name: | C2: ='Sunday WK1 (1)'!C2 -> 0.478 | E2: ='Sunday WK1 (1)'!E2 -> 0.099 | F2: ='Sunday WK1 (1)'!F2 -> 0 | G2: ='Sunday WK1 (1)'!G2 -> 0 | H2: ='Sunday WK1 (1)'!H2 -> 0 | I2: ='Sunday WK1 (1)'!I2 -> 0.159 | J2: ='Sunday WK1 (1)'!J2 -> 0.122 | K2: ='Sunday WK1 (1)'!$K$2 -> 0.142 | L2: ='Sunday WK1 (1)'!L2 -> 0 | N2: =SUM(C2:M2) -> 1
B3: SHANNON | C3: =C2*$N$3 -> 0 | E3: =E2*$N$3 -> 0 | F3: =F2*$N$3 -> 0 | G3: =G2*$N$3 -> 0 | H3: =H2*$N$3 -> 0 | I3: =I2*$N$3 -> 0 | J3: =J2*$N$3 -> 0 | K3: =K2*$N$3 -> 0 | L3: =L2*$N$3 -> 0
A4: Receiving Date: | B4: ='Thursday WK2 (12)'!B4+1 -> 46206
A5: Invoice Number | B5: Supplier Name | C5: Grocery Purchases | D5: Tobacco Purchases | E5: Meat Purchases | F5: Bakery Purchases | G5: Bakery In Store | H5: Deli Purchases | I5: Produce Purchases | J5: Produce Shrink | K5: Dairy Purchases | L5: Pharmacy Purchases | M5: GST | N5: Total Invoice**
A6: 53097633101 | B6: COCA COLA CANADA BOTTLING | C6: =N6-D6-E6-F6-G6-H6-I6-J6-K6-L6-M6-D60-E60-F60-G60-H60-I60-J60-K60-L60-C60 -> 6991.49 | M6: 282.5 | N6: 7273.99
A7: 82849831 | B7: OLD DUTCH FOODS | C7: =N7-D7-E7-F7-G7-H7-I7-J7-K7-L7-M7-D61-E61-F61-G61-H61-I61-J61-K61-L61-C61 -> 461.31 | M7: 23.07 | N7: 484.38
A8: 82849832 | B8: OLD DUTCH FOODS | C8: =N8-D8-E8-F8-G8-H8-I8-J8-K8-L8-M8-D62-E62-F62-G62-H62-I62-J62-K62-L62-C62 -> -63.51 | M8: -3.18 | N8: -66.69
A9: 94181775 | B9: FRITO LAY CANADA RETAIL | C9: =N9-D9-E9-F9-G9-H9-I9-J9-K9-L9-M9-D63-E63-F63-G63-H63-I63-J63-K63-L63-C63 -> 729.05 | M9: 36.46 | N9: 765.51
A10: 0117434 | B10: G & L DISTRIBUTORS | C10: =N10-D10-E10-F10-G10-H10-I10-J10-K10-L10-M10-D64-E64-F64-G64-H64-I64-J64-K64-L64-C64 -> 1274.06 | M10: 63.7 | N10: 1337.76
A11: 10484 | B11: ALTA AGRI-FOODS LTD. | C11: =N11-D11-E11-F11-G11-H11-I11-J11-K11-L11-M11-D65-E65-F65-G65-H65-I65-J65-K65-L65-C65 -> 111.84 | K11: 218.72 | N11: 330.56
A12: 6017 | B12: THE GROCERY PEOPLE | C12: =N12-D12-E12-F12-G12-H12-I12-J12-K12-L12-M12-D66-E66-F66-G66-H66-I66-J66-K66-L66-C66 -> -1155 | N12: -1155 | O12: STORE TRANSFER - LLOYDMINSTER
C13: =N13-D13-E13-F13-G13-H13-I13-J13-K13-L13-M13-D67-E67-F67-G67-H67-I67-J67-K67-L67-C67 -> 0
C14: =N14-D14-E14-F14-G14-H14-I14-J14-K14-L14-M14-D68-E68-F68-G68-H68-I68-J68-K68-L68-C68 -> 0
C15: =N15-D15-E15-F15-G15-H15-I15-J15-K15-L15-M15-D69-E69-F69-G69-H69-I69-J69-K69-L69-C69 -> 0
C16: =N16-D16-E16-F16-G16-H16-I16-J16-K16-L16-M16-D70-E70-F70-G70-H70-I70-J70-K70-L70-C70 -> 0
C17: =N17-D17-E17-F17-G17-H17-I17-J17-K17-L17-M17-D71-E71-F71-G71-H71-I71-J71-K71-L71-C71 -> 0
C18: =N18-D18-E18-F18-G18-H18-I18-J18-K18-L18-M18-D72-E72-F72-G72-H72-I72-J72-K72-L72-C72 -> 0
C19: =N19-D19-E19-F19-G19-H19-I19-J19-K19-L19-M19-D73-E73-F73-G73-H73-I73-J73-K73-L73-C73 -> 0
C20: =N20-D20-E20-F20-G20-H20-I20-J20-K20-L20-M20-D74-E74-F74-G74-H74-I74-J74-K74-L74-C74 -> 0
C21: =N21-D21-E21-F21-G21-H21-I21-J21-K21-L21-M21-D75-E75-F75-G75-H75-I75-J75-K75-L75-C75 -> 0
C22: =N22-D22-E22-F22-G22-H22-I22-J22-K22-L22-M22-D76-E76-F76-G76-H76-I76-J76-K76-L76-C76 -> 0
C23: =N23-D23-E23-F23-G23-H23-I23-J23-K23-L23-M23-D77-E77-F77-G77-H77-I77-J77-K77-L77-C77 -> 0
C24: =N24-D24-E24-F24-G24-H24-I24-J24-K24-L24-M24-D78-E78-F78-G78-H78-I78-J78-K78-L78-C78 -> 0
... C55: =N55-D55-E55-F55-G55-H55-I55-J55-K55-L55-M55-D109-E109-F109-G109-H109-I109-J109-K109-L109-C109 -> 0
A56: Freight | B56: THE GROCERY PEOPLE | C56: =C3 -> 0 | E56: =E3 -> 0 | F56: =F3 -> 0 | G56: =G3 -> 0 | H56: =H3 -> 0 | I56: =I3 -> 0 | J56: =J3 -> 0 | K56: =K3 -> 0 | L56: =L3 -> 0 | N56: =SUM(C56:M56)+SUM(C118:J118) -> 0 | O56: BM#8187146, BOL REF#4764061
A57: Department Totals | C57: =SUM(C6:C56) -> 8349.24 | D57: =SUM(D6:D56) -> 0 | E57: =SUM(E6:E56) -> 0 | F57: =SUM(F6:F56) -> 0 | G57: =SUM(G6:G56) -> 0 | H57: =SUM(H6:H56) -> 0 | I57: =SUM(I6:I56) -> 0 | J57: =SUM(J6:J56) -> 0 | ... N57: =SUM(N6:N56) -> 8970.51
N58: =IF(SUM(N6:N56)=SUM(C57:M57)+SUM(C110:L110),"","Sum error")
A59: Invoice Number | B59: Supplier Name | C59: Grocery Supplies | D59: Tobacco Supplies | E59: Meat Supplies | F59: Bakery Supplies | G59: B.In store Supplies | H59: Deli Supplies | I59: Produce Supplies | K59: Dairy Supplies | L59: Pharmacy Supplies
A60: =A6 -> 53097633101 | B60: =B6 -> COCA COLA CANADA BOTTLING
A61: =A7 -> 82849831 | B61: =B7 -> OLD DUTCH FOODS
A62: =A8 -> 82849832 | B62: =B8 -> OLD DUTCH FOODS
A63: =A9 -> 94181775 | B63: =B9 -> FRITO LAY CANADA RETAIL
A64: =A10 -> 0117434 | B64: =B10 -> G & L DISTRIBUTORS
A65: =A11 -> 10484 | B65: =B11 -> ALTA AGRI-FOODS LTD.
A66: =A12 -> 6017 | B66: =B12 -> THE GROCERY PEOPLE
A67: =A13 | B67: =B13
A68: =A14 | B68: =B14
A69: =A15 | B69: =B15
A70: =A16 | B70: =B16
A71: =A17 | B71: =B17
... A109: =A55 | B109: =B55
A110: Department Totals | C110: =SUM(C60:C109) -> 0 | D110: =SUM(D60:D109) -> 0 | E110: =SUM(E60:E109) -> 0 | F110: =SUM(F60:F109) -> 0 | G110: =SUM(G60:G109) -> 0 | H110: =SUM(H60:H109) -> 0 | I110: =SUM(I60:I109) -> 0 | J110: =SUM(J60:J109) -> 0 | K110: =SUM(K60:K109) -> 0 | L110: 0

Sheet Saturday WK2 (14)
B1: Freight | C1: Grocery | E1: Meat | F1: Bakery | G1: Bake off | H1: Deli | I1: Produce | J1: Produce Shrink | K1: Dairy | L1: Pharmacy | M1: Receiving Totals | N1: Total
B2: Name: | C2: ='Sunday WK1 (1)'!C2 -> 0.478 | E2: ='Sunday WK1 (1)'!E2 -> 0.099 | F2: ='Sunday WK1 (1)'!F2 -> 0 | G2: ='Sunday WK1 (1)'!G2 -> 0 | H2: ='Sunday WK1 (1)'!H2 -> 0 | I2: ='Sunday WK1 (1)'!I2 -> 0.159 | J2: ='Sunday WK1 (1)'!J2 -> 0.122 | K2: ='Sunday WK1 (1)'!$K$2 -> 0.142 | L2: ='Sunday WK1 (1)'!L2 -> 0 | N2: =SUM(C2:M2) -> 1
B3: SHANNON | C3: =C2*$N$3 -> 0 | E3: =E2*$N$3 -> 0 | F3: =F2*$N$3 -> 0 | G3: =G2*$N$3 -> 0 | H3: =H2*$N$3 -> 0 | I3: =I2*$N$3 -> 0 | J3: =J2*$N$3 -> 0 | K3: =K2*$N$3 -> 0 | L3: =L2*$N$3 -> 0
A4: Receiving Date: | B4: ='Friday WK2 (13)'!B4+1 -> 46207
A5: Invoice Number | B5: Supplier Name | C5: Grocery Purchases | D5: Tobacco Purchases | E5: Meat Purchases | F5: Bakery Purchases | G5: Bakery In Store | H5: Deli Purchases | I5: Produce Purchases | J5: Produce Shrink | K5: Dairy Purchases | L5: Pharmacy Purchases | M5: GST | N5: Total Invoice**
A6: 126616 | B6: ITALIAN BAKERY | C6: =N6-D6-E6-F6-G6-H6-I6-J6-K6-L6-M6-D60-E60-F60-G60-H60-I60-J60-K60-L60-C60 -> 365.91 | N6: 365.91
C7: =N7-D7-E7-F7-G7-H7-I7-J7-K7-L7-M7-D61-E61-F61-G61-H61-I61-J61-K61-L61-C61 -> 0
C8: =N8-D8-E8-F8-G8-H8-I8-J8-K8-L8-M8-D62-E62-F62-G62-H62-I62-J62-K62-L62-C62 -> 0
C9: =N9-D9-E9-F9-G9-H9-I9-J9-K9-L9-M9-D63-E63-F63-G63-H63-I63-J63-K63-L63-C63 -> 0
C10: =N10-D10-E10-F10-G10-H10-I10-J10-K10-L10-M10-D64-E64-F64-G64-H64-I64-J64-K64-L64-C64 -> 0
C11: =N11-D11-E11-F11-G11-H11-I11-J11-K11-L11-M11-D65-E65-F65-G65-H65-I65-J65-K65-L65-C65 -> 0
C12: =N12-D12-E12-F12-G12-H12-I12-J12-K12-L12-M12-D66-E66-F66-G66-H66-I66-J66-K66-L66-C66 -> 0
C13: =N13-D13-E13-F13-G13-H13-I13-J13-K13-L13-M13-D67-E67-F67-G67-H67-I67-J67-K67-L67-C67 -> 0
C14: =N14-D14-E14-F14-G14-H14-I14-J14-K14-L14-M14-D68-E68-F68-G68-H68-I68-J68-K68-L68-C68 -> 0
C15: =N15-D15-E15-F15-G15-H15-I15-J15-K15-L15-M15-D69-E69-F69-G69-H69-I69-J69-K69-L69-C69 -> 0
C16: =N16-D16-E16-F16-G16-H16-I16-J16-K16-L16-M16-D70-E70-F70-G70-H70-I70-J70-K70-L70-C70 -> 0
C17: =N17-D17-E17-F17-G17-H17-I17-J17-K17-L17-M17-D71-E71-F71-G71-H71-I71-J71-K71-L71-C71 -> 0
C18: =N18-D18-E18-F18-G18-H18-I18-J18-K18-L18-M18-D72-E72-F72-G72-H72-I72-J72-K72-L72-C72 -> 0
... C55: =N55-D55-E55-F55-G55-H55-I55-J55-K55-L55-M55-D109-E109-F109-G109-H109-I109-J109-K109-L109-C109 -> 0
A56: Freight | B56: THE GROCERY PEOPLE | C56: =C3 -> 0 | E56: =E3 -> 0 | F56: =F3 -> 0 | G56: =G3 -> 0 | H56: =H3 -> 0 | I56: =I3 -> 0 | J56: =J3 -> 0 | K56: =K3 -> 0 | L56: =L3 -> 0 | N56: =SUM(C56:M56)+SUM(C118:J118) -> 0
A57: Department Totals | C57: =SUM(C6:C56) -> 365.91 | D57: =SUM(D6:D56) -> 0 | E57: =SUM(E6:E56) -> 0 | F57: =SUM(F6:F56) -> 0 | G57: =SUM(G6:G56) -> 0 | H57: =SUM(H6:H56) -> 0 | I57: =SUM(I6:I56) -> 0 | J57: =SUM(J6:J56) -> 0 | ... N57: =SUM(N6:N56) -> 365.91
N58: =IF(SUM(N6:N56)=SUM(C57:M57)+SUM(D110:L110),"","Sum error")
A59: Invoice Number | B59: Supplier Name | C59: Grocery Supplies | D59: Tobacco Supplies | E59: Meat Supplies | F59: Bakery Supplies | G59: B.In store Supplies | H59: Deli Supplies | I59: Produce Supplies | K59: Dairy Supplies | L59: Pharmacy Supplies
A60: =A6 -> 126616 | B60: =B6 -> ITALIAN BAKERY
A61: =A7 | B61: =B7
A62: =A8 | B62: =B8
A63: =A9 | B63: =B9
A64: =A10 | B64: =B10
A65: =A11 | B65: =B11
A66: =A12 | B66: =B12
A67: =A13 | B67: =B13
A68: =A14 | B68: =B14
A69: =A15 | B69: =B15
A70: =A16 | B70: =B16
A71: =A17 | B71: =B17
... A109: =A55 | B109: =B55
A110: Department Totals | C110: =SUM(C60:C109) -> 0 | D110: =SUM(D60:D109) -> 0 | E110: =SUM(E60:E109) -> 0 | F110: =SUM(F60:F109) -> 0 | G110: =SUM(G60:G109) -> 0 | H110: =SUM(H60:H109) -> 0 | I110: =SUM(I60:I109) -> 0 | J110: =SUM(J60:J109) -> 0 | K110: =SUM(K60:K109) -> 0 | L110: 0

Sheet Sunday WK3 (15)
B1: Freight | C1: Grocery | E1: Meat | F1: Bakery | G1: Bake off | H1: Deli | I1: Produce | J1: Produce Shrink | K1: Dairy | L1: Pharmacy | M1: Receiving Totals | N1: Total
B2: Name: | C2: ='Sunday WK1 (1)'!C2 -> 0.478 | E2: ='Sunday WK1 (1)'!E2 -> 0.099 | F2: ='Sunday WK1 (1)'!F2 -> 0 | G2: ='Sunday WK1 (1)'!G2 -> 0 | H2: ='Sunday WK1 (1)'!H2 -> 0 | I2: ='Sunday WK1 (1)'!I2 -> 0.159 | J2: ='Sunday WK1 (1)'!J2 -> 0.122 | K2: ='Sunday WK1 (1)'!$K$2 -> 0.142 | L2: ='Sunday WK1 (1)'!L2 -> 0 | N2: =SUM(C2:M2) -> 1
B3: SHANNON | C3: =C2*$N$3 -> 175.64588 | E3: =E2*$N$3 -> 36.37854 | F3: =F2*$N$3 -> 0 | G3: =G2*$N$3 -> 0 | H3: =H2*$N$3 -> 0 | I3: =I2*$N$3 -> 58.42614 | J3: =J2*$N$3 -> 44.83012 | K3: =K2*$N$3 -> 52.17932 | L3: =L2*$N$3 -> 0 | N3: 367.46
A4: Receiving Date: | B4: ='Saturday WK2 (14)'!B4+1 -> 46208
A5: Invoice Number | B5: Supplier Name | C5: Grocery Purchases | D5: Tobacco Purchases | E5: Meat Purchases | F5: Bakery Purchases | G5: Bakery In Store | H5: Deli Purchases | I5: Produce Purchases | J5: Produce Shrink | K5: Dairy Purchases | L5: Pharmacy Purchases | M5: GST | N5: Total Invoice**
A6: 4003749852 | B6: SAPUTO DAIRY PRODUCTS | C6: =N6-D6-E6-F6-G6-H6-I6-J6-K6-L6-M6-D60-E60-F60-G60-H60-I60-J60-K60-L60-C60 -> -3.0919711e-13 | K6: 3175.57 | M6: 0.84 | N6: 3176.41
A7: 4003749851 | B7: SAPUTO DAIRY PRODUCTS | C7: =N7-D7-E7-F7-G7-H7-I7-J7-K7-L7-M7-D61-E61-F61-G61-H61-I61-J61-K61-L61-C61 -> 0 | K7: 203.22 | N7: 203.22
A8: 4003731438 | B8: SAPUTO DAIRY PRODUCTS | C8: =N8-D8-E8-F8-G8-H8-I8-J8-K8-L8-M8-D62-E62-F62-G62-H62-I62-J62-K62-L62-C62 -> 0 | K8: 243.86 | N8: 243.86
A9: SO186413 | B9: STAR PRODUCE | C9: =N9-D9-E9-F9-G9-H9-I9-J9-K9-L9-M9-D63-E63-F63-G63-H63-I63-J63-K63-L63-C63 -> -1.7763568e-15 | I9: 250.1 | M9: 8.97 | N9: 259.07
A10: 100352206 | B10: FREYBE GOURMET FOODS | C10: =N10-D10-E10-F10-G10-H10-I10-J10-K10-L10-M10-D64-E64-F64-G64-H64-I64-J64-K64-L64-C64 -> 0 | E10: 643.09 | N10: 643.09
A11: 6676651 | B11: THE GROCERY PEOPLE | C11: =N11-D11-E11-F11-G11-H11-I11-J11-K11-L11-M11-D65-E65-F65-G65-H65-I65-J65-K65-L65-C65 -> 0 | E11: 17.44 | N11: 17.44
A12: 6678810 | B12: THE GROCERY PEOPLE | C12: =N12-D12-E12-F12-G12-H12-I12-J12-K12-L12-M12-D66-E66-F66-G66-H66-I66-J66-K66-L66-C66 -> 40.04 | N12: 40.04
A13: 6679688 | B13: THE GROCERY PEOPLE | C13: =N13-D13-E13-F13-G13-H13-I13-J13-K13-L13-M13-D67-E67-F67-G67-H67-I67-J67-K67-L67-C67 -> 0 | E13: 61.66 | N13: 61.66
A14: 6682144 | B14: THE GROCERY PEOPLE | C14: =N14-D14-E14-F14-G14-H14-I14-J14-K14-L14-M14-D68-E68-F68-G68-H68-I68-J68-K68-L68-C68 -> 25.12 | K14: 164.53 | N14: 189.65
A15: 6682145 | B15: THE GROCERY PEOPLE | C15: =N15-D15-E15-F15-G15-H15-I15-J15-K15-L15-M15-D69-E69-F69-G69-H69-I69-J69-K69-L69-C69 -> 0 | E15: 34.31 | N15: 34.31
A16: 6682146 | B16: THE GROCERY PEOPLE | C16: =N16-D16-E16-F16-G16-H16-I16-J16-K16-L16-M16-D70-E70-F70-G70-H70-I70-J70-K70-L70-C70 -> 0 | E16: 196.73 | N16: 196.73
A17: 6679289 | B17: THE GROCERY PEOPLE | C17: =N17-D17-E17-F17-G17-H17-I17-J17-K17-L17-M17-D71-E71-F71-G71-H71-I71-J71-K71-L71-C71 -> 0 | E17: 38.26 | N17: 38.26
A18: 6676375 | B18: THE GROCERY PEOPLE | C18: =N18-D18-E18-F18-G18-H18-I18-J18-K18-L18-M18-D72-E72-F72-G72-H72-I72-J72-K72-L72-C72 -> 0 | N18: 107.16 | O18: STORE SUPPLIES - FOAMING HAND SOAP
A19: 6678809 | B19: THE GROCERY PEOPLE | C19: =N19-D19-E19-F19-G19-H19-I19-J19-K19-L19-M19-D73-E73-F73-G73-H73-I73-J73-K73-L73-C73 -> 340.86 | N19: 340.86
A20: 6680695 | B20: THE GROCERY PEOPLE | C20: =N20-D20-E20-F20-G20-H20-I20-J20-K20-L20-M20-D74-E74-F74-G74-H74-I74-J74-K74-L74-C74 -> 176.08 | N20: 176.08
A21: 6676376 | B21: THE GROCERY PEOPLE | C21: =N21-D21-E21-F21-G21-H21-I21-J21-K21-L21-M21-D75-E75-F75-G75-H75-I75-J75-K75-L75-C75 -> 0 | E21: 1380.55 | N21: 1380.55
A22: 6680696 | B22: THE GROCERY PEOPLE | C22: =N22-D22-E22-F22-G22-H22-I22-J22-K22-L22-M22-D76-E76-F76-G76-H76-I76-J76-K76-L76-C76 -> 0 | E22: 5734.61 | N22: 5734.61
A23: 5640621 | B23: THE GROCERY PEOPLE | C23: =N23-D23-E23-F23-G23-H23-I23-J23-K23-L23-M23-D77-E77-F77-G77-H77-I77-J77-K77-L77-C77 -> 0 | N23: 353.82 | O23: MEAT SUPPLIES - FOAM TRAYS, DRILOC, STRETCH FILM
A24: 5640936 | B24: THE GROCERY PEOPLE | C24: =N24-D24-E24-F24-G24-H24-I24-J24-K24-L24-M24-D78-E78-F78-G78-H78-I78-J78-K78-L78-C78 -> 0 | E24: 77.04 | N24: 77.04
A25: 5643102 | B25: THE GROCERY PEOPLE | C25: =N25-D25-E25-F25-G25-H25-I25-J25-K25-L25-M25-D79-E79-F79-G79-H79-I79-J79-K79-L79-C79 -> 0 | E25: 2438.94 | N25: 2438.94
A26: 5643103 | B26: THE GROCERY PEOPLE | C26: =N26-D26-E26-F26-G26-H26-I26-J26-K26-L26-M26-D80-E80-F80-G80-H80-I80-J80-K80-L80-C80 -> 1772.08 | N26: 1772.08
A27: 5643508 | B27: THE GROCERY PEOPLE | C27: =N27-D27-E27-F27-G27-H27-I27-J27-K27-L27-M27-D81-E81-F81-G81-H81-I81-J81-K81-L81-C81 -> 15689.13 | N27: 15689.13
A28: 5643590 | B28: THE GROCERY PEOPLE | C28: =N28-D28-E28-F28-G28-H28-I28-J28-K28-L28-M28-D82-E82-F82-G82-H82-I82-J82-K82-L82-C82 -> 2256.46 | N28: 2256.46
A29: 5643740 | B29: THE GROCERY PEOPLE | C29: =N29-D29-E29-F29-G29-H29-I29-J29-K29-L29-M29-D83-E83-F83-G83-H83-I83-J83-K83-L83-C83 -> 111.37 | K29: 2631.8 | N29: 2743.17
A30: 8247090 | B30: THE GROCERY PEOPLE | C30: =N30-D30-E30-F30-G30-H30-I30-J30-K30-L30-M30-D84-E84-F84-G84-H84-I84-J84-K84-L84-C84 -> 0 | E30: 621.7 | N30: 621.7
A31: 8247485 | B31: THE GROCERY PEOPLE | C31: =N31-D31-E31-F31-G31-H31-I31-J31-K31-L31-M31-D85-E85-F85-G85-H85-I85-J85-K85-L85-C85 -> 0 | E31: 726.81 | N31: 726.81
A32: 8247544 | B32: THE GROCERY PEOPLE | C32: =N32-D32-E32-F32-G32-H32-I32-J32-K32-L32-M32-D86-E86-F86-G86-H86-I86-J86-K86-L86-C86 -> 0 | E32: 31.48 | N32: 31.48
A33: 5640678 | B33: THE GROCERY PEOPLE | C33: =N33-D33-E33-F33-G33-H33-I33-J33-K33-L33-M33-D87-E87-F87-G87-H87-I87-J87-K87-L87-C87 -> 278.39 | N33: 278.39
A34: 5640875 | B34: THE GROCERY PEOPLE | C34: =N34-D34-E34-F34-G34-H34-I34-J34-K34-L34-M34-D88-E88-F88-G88-H88-I88-J88-K88-L88-C88 -> 31.19 | N34: 31.19
A35: 5641129 | B35: THE GROCERY PEOPLE | C35: =N35-D35-E35-F35-G35-H35-I35-J35-K35-L35-M35-D89-E89-F89-G89-H89-I89-J89-K89-L89-C89 -> 128.16 | N35: 128.16
A36: 5641130 | B36: THE GROCERY PEOPLE | C36: =N36-D36-E36-F36-G36-H36-I36-J36-K36-L36-M36-D90-E90-F90-G90-H90-I90-J90-K90-L90-C90 -> 93.87 | N36: 93.87
A37: 5641912 | B37: THE GROCERY PEOPLE | C37: =N37-D37-E37-F37-G37-H37-I37-J37-K37-L37-M37-D91-E91-F91-G91-H91-I91-J91-K91-L91-C91 -> 929.86 | N37: 929.86
A38: 5642290 | B38: THE GROCERY PEOPLE | C38: =N38-D38-E38-F38-G38-H38-I38-J38-K38-L38-M38-D92-E92-F92-G92-H92-I92-J92-K92-L92-C92 -> 0 | E38: 761.1 | N38: 761.1
A39: 5642291 | B39: THE GROCERY PEOPLE | C39: =N39-D39-E39-F39-G39-H39-I39-J39-K39-L39-M39-D93-E93-F93-G93-H93-I93-J93-K93-L93-C93 -> 0 | E39: 50.88 | N39: 50.88
A40: 5642411 | B40: THE GROCERY PEOPLE | C40: =N40-D40-E40-F40-G40-H40-I40-J40-K40-L40-M40-D94-E94-F94-G94-H94-I94-J94-K94-L94-C94 -> 68.1 | N40: 68.1
A41: 5643425 | B41: THE GROCERY PEOPLE | C41: =N41-D41-E41-F41-G41-H41-I41-J41-K41-L41-M41-D95-E95-F95-G95-H95-I95-J95-K95-L95-C95 -> 291.04 | N41: 291.04
A42: 5643626 | B42: THE GROCERY PEOPLE | C42: =N42-D42-E42-F42-G42-H42-I42-J42-K42-L42-M42-D96-E96-F96-G96-H96-I96-J96-K96-L96-C96 -> 0 | K42: 13100.22 | N42: 13100.22
A43: 5643507 | B43: THE GROCERY PEOPLE | C43: =N43-D43-E43-F43-G43-H43-I43-J43-K43-L43-M43-D97-E97-F97-G97-H97-I97-J97-K97-L97-C97 -> 163.28 | N43: 163.28
A44: 5643592 | B44: THE GROCERY PEOPLE | C44: =N44-D44-E44-F44-G44-H44-I44-J44-K44-L44-M44-D98-E98-F98-G98-H98-I98-J98-K98-L98-C98 -> 77.25 | N44: 77.25
A45: 5643739 | B45: THE GROCERY PEOPLE | C45: =N45-D45-E45-F45-G45-H45-I45-J45-K45-L45-M45-D99-E99-F99-G99-H99-I99-J99-K99-L99-C99 -> 0 | K45: 1443.7 | N45: 1443.7
A46: 5643101 | B46: THE GROCERY PEOPLE | C46: =N46-D46-E46-F46-G46-H46-I46-J46-K46-L46-M46-D100-E100-F100-G100-H100-I100-J100-K100-L100-C100 -> 2192.29 | N46: 2192.29
A47: 5643866 | B47: THE GROCERY PEOPLE | C47: =N47-D47-E47-F47-G47-H47-I47-J47-K47-L47-M47-D101-E101-F101-G101-H101-I101-J101-K101-L101-C101 -> 0 | I47: 42.4 | N47: 42.4
A48: 5643905 | B48: THE GROCERY PEOPLE | C48: =N48-D48-E48-F48-G48-H48-I48-J48-K48-L48-M48-D102-E102-F102-G102-H102-I102-J102-K102-L102-C102 -> 21.83 | K48: 42.52 | N48: 64.35
A49: 5644070 | B49: THE GROCERY PEOPLE | C49: =N49-D49-E49-F49-G49-H49-I49-J49-K49-L49-M49-D103-E103-F103-G103-H103-I103-J103-K103-L103-C103 -> 0 | I49: 4622.56 | N49: 4622.56
A50: 5644071 | B50: THE GROCERY PEOPLE | C50: =N50-D50-E50-F50-G50-H50-I50-J50-K50-L50-M50-D104-E104-F104-G104-H104-I104-J104-K104-L104-C104 -> 0 | I50: 1370.4 | N50: 1370.4
A51: 5644072 | B51: THE GROCERY PEOPLE | C51: =N51-D51-E51-F51-G51-H51-I51-J51-K51-L51-M51-D105-E105-F105-G105-H105-I105-J105-K105-L105-C105 -> 0 | I51: 40.95 | N51: 40.95
C52: =N52-D52-E52-F52-G52-H52-I52-J52-K52-L52-M52-D106-E106-F106-G106-H106-I106-J106-K106-L106-C106 -> 0
C53: =N53-D53-E53-F53-G53-H53-I53-J53-K53-L53-M53-D107-E107-F107-G107-H107-I107-J107-K107-L107-C107 -> 0
C54: =N54-D54-E54-F54-G54-H54-I54-J54-K54-L54-M54-D108-E108-F108-G108-H108-I108-J108-K108-L108-C108 -> 0
C55: =N55-D55-E55-F55-G55-H55-I55-J55-K55-L55-M55-D109-E109-F109-G109-H109-I109-J109-K109-L109-C109 -> 0
A56: Freight | B56: THE GROCERY PEOPLE | C56: =C3 -> 175.64588 | E56: =E3 -> 36.37854 | F56: =F3 -> 0 | G56: =G3 -> 0 | H56: =H3 -> 0 | I56: =I3 -> 58.42614 | J56: =J3 -> 44.83012 | K56: =K3 -> 52.17932 | L56: =L3 -> 0 | N56: =SUM(C56:M56)+SUM(C118:J118) -> 367.46 | O56: BM#8516790, BOL REF#4855702,4855701,4855698,4855699,4855700
A57: Department Totals | C57: =SUM(C6:C56) -> 24862.046 | D57: =SUM(D6:D56) -> 0 | E57: =SUM(E6:E56) -> 12850.979 | F57: =SUM(F6:F56) -> 0 | G57: =SUM(G6:G56) -> 0 | H57: =SUM(H6:H56) -> 0 | I57: =SUM(I6:I56) -> 6384.8361 | J57: =SUM(J6:J56) -> 44.83012 | ... N57: =SUM(N6:N56) -> 65671.08
N58: =IF(SUM(N6:N56)=SUM(C57:M57)+SUM(C110:L110),"","Sum error")
A59: Invoice Number | B59: Supplier Name | C59: Grocery Supplies | D59: Tobacco Supplies | E59: Meat Supplies | F59: Bakery Supplies | G59: B.In store Supplies | H59: Deli Supplies | I59: Produce Supplies | K59: Dairy Supplies | L59: Pharmacy Supplies
A60: =A6 -> 4003749852 | B60: =B6 -> SAPUTO DAIRY PRODUCTS
A61: =A7 -> 4003749851 | B61: =B7 -> SAPUTO DAIRY PRODUCTS
A62: =A8 -> 4003731438 | B62: =B8 -> SAPUTO DAIRY PRODUCTS
A63: =A9 -> SO186413 | B63: =B9 -> STAR PRODUCE
A64: =A10 -> 100352206 | B64: =B10 -> FREYBE GOURMET FOODS
A65: =A11 -> 6676651 | B65: =B11 -> THE GROCERY PEOPLE
A66: =A12 -> 6678810 | B66: =B12 -> THE GROCERY PEOPLE
A67: =A13 -> 6679688 | B67: =B13 -> THE GROCERY PEOPLE
A68: =A14 -> 6682144 | B68: =B14 -> THE GROCERY PEOPLE
A69: =A15 -> 6682145 | B69: =B15 -> THE GROCERY PEOPLE
A70: =A16 -> 6682146 | B70: =B16 -> THE GROCERY PEOPLE
A71: =A17 -> 6679289 | B71: =B17 -> THE GROCERY PEOPLE
A72: =A18 -> 6676375 | B72: =B18 -> THE GROCERY PEOPLE | C72: 107.16 | M72: STORE SUPPLIES - FOAMING HAND SOAP
A73: =A19 -> 6678809 | B73: =B19 -> THE GROCERY PEOPLE
A74: =A20 -> 6680695 | B74: =B20 -> THE GROCERY PEOPLE
A75: =A21 -> 6676376 | B75: =B21 -> THE GROCERY PEOPLE
A76: =A22 -> 6680696 | B76: =B22 -> THE GROCERY PEOPLE
A77: =A23 -> 5640621 | B77: =B23 -> THE GROCERY PEOPLE | E77: 353.82 | M77: MEAT SUPPLIES - FOAM TRAYS, DRILOC, STRETCH FILM
A78: =A24 -> 5640936 | B78: =B24 -> THE GROCERY PEOPLE
A79: =A25 -> 5643102 | B79: =B25 -> THE GROCERY PEOPLE
A80: =A26 -> 5643103 | B80: =B26 -> THE GROCERY PEOPLE
A81: =A27 -> 5643508 | B81: =B27 -> THE GROCERY PEOPLE
A82: =A28 -> 5643590 | B82: =B28 -> THE GROCERY PEOPLE
A83: =A29 -> 5643740 | B83: =B29 -> THE GROCERY PEOPLE
A84: =A30 -> 8247090 | B84: =B30 -> THE GROCERY PEOPLE
A85: =A31 -> 8247485 | B85: =B31 -> THE GROCERY PEOPLE
A86: =A32 -> 8247544 | B86: =B32 -> THE GROCERY PEOPLE
A87: =A33 -> 5640678 | B87: =B33 -> THE GROCERY PEOPLE
A88: =A34 -> 5640875 | B88: =B34 -> THE GROCERY PEOPLE
A89: =A35 -> 5641129 | B89: =B35 -> THE GROCERY PEOPLE
... A109: =A55 | B109: =B55
A110: Department Totals | C110: =SUM(C60:C109) -> 107.16 | D110: =SUM(D60:D109) -> 0 | E110: =SUM(E60:E109) -> 353.82 | F110: =SUM(F60:F109) -> 0 | G110: =SUM(G60:G109) -> 0 | H110: =SUM(H60:H109) -> 0 | I110: =SUM(I60:I109) -> 0 | J110: =SUM(J60:J109) -> 0 | K110: =SUM(K60:K109) -> 0 | L110: 0

Sheet Monday WK3 (16)
B1: Freight | C1: Grocery | E1: Meat | F1: Bakery | G1: Bake off | H1: Deli | I1: Produce | J1: Produce Shrink | K1: Dairy | L1: Pharmacy | M1: Receiving Totals | N1: Total
B2: Name: | C2: ='Sunday WK1 (1)'!C2 -> 0.478 | E2: ='Sunday WK1 (1)'!E2 -> 0.099 | F2: ='Sunday WK1 (1)'!F2 -> 0 | G2: ='Sunday WK1 (1)'!G2 -> 0 | H2: ='Sunday WK1 (1)'!H2 -> 0 | I2: ='Sunday WK1 (1)'!I2 -> 0.159 | J2: ='Sunday WK1 (1)'!J2 -> 0.122 | K2: ='Sunday WK1 (1)'!$K$2 -> 0.142 | L2: ='Sunday WK1 (1)'!L2 -> 0 | N2: =SUM(C2:M2) -> 1
B3: SHANNON | C3: =C2*$N$3 -> 0 | E3: =E2*$N$3 -> 0 | F3: =F2*$N$3 -> 0 | G3: =G2*$N$3 -> 0 | H3: =H2*$N$3 -> 0 | I3: =I2*$N$3 -> 0 | J3: =J2*$N$3 -> 0 | K3: =K2*$N$3 -> 0 | L3: =L2*$N$3 -> 0
A4: Receiving Date: | B4: ='Sunday WK3 (15)'!B4+1 -> 46209
A5: Invoice Number | B5: Supplier Name | C5: Grocery Purchases | D5: Tobacco Purchases | E5: Meat Purchases | F5: Bakery Purchases | G5: Bakery In Store | H5: Deli Purchases | I5: Produce Purchases | J5: Produce Shrink | K5: Dairy Purchases | L5: Pharmacy Purchases | M5: GST | N5: Total Invoice**
A6: 2246 | B6: NELLA WEST | C6: =N6-D6-E6-F6-G6-H6-I6-J6-K6-L6-M6-D60-E60-F60-G60-H60-I60-J60-K60-L60-C60 -> -622.51 | M6: -31.13 | N6: -653.64
A7: 54319807 | B7: PEPSICO | C7: =N7-D7-E7-F7-G7-H7-I7-J7-K7-L7-M7-D61-E61-F61-G61-H61-I61-J61-K61-L61-C61 -> 682 | M7: 26.38 | N7: 708.38
A8: 54319806 | B8: PEPSICO | C8: =N8-D8-E8-F8-G8-H8-I8-J8-K8-L8-M8-D62-E62-F62-G62-H62-I62-J62-K62-L62-C62 -> 7997.85 | M8: 264.53 | N8: 8262.38
A9: 53166884003 | B9: COCA COLA CANADA BOTTLING | C9: =N9-D9-E9-F9-G9-H9-I9-J9-K9-L9-M9-D63-E63-F63-G63-H63-I63-J63-K63-L63-C63 -> 5418.32 | M9: 220.99 | N9: 5639.31
A10: 226650718709 | B10: CANADA BREAD COMPANY | C10: =N10-D10-E10-F10-G10-H10-I10-J10-K10-L10-M10-D64-E64-F64-G64-H64-I64-J64-K64-L64-C64 -> 1256.59 | M10: 8.6 | N10: 1265.19
A11: 226650718710 | B11: CANADA BREAD COMPANY | C11: =N11-D11-E11-F11-G11-H11-I11-J11-K11-L11-M11-D65-E65-F65-G65-H65-I65-J65-K65-L65-C65 -> -417.28 | M11: -0.74 | N11: -418.02
A12: 2882618701 | B12: DIRECT PLUS FOOD GROUP | C12: =N12-D12-E12-F12-G12-H12-I12-J12-K12-L12-M12-D66-E66-F66-G66-H66-I66-J66-K66-L66-C66 -> 429.34 | N12: 429.34
A13: 2882618702 | B13: DIRECT PLUS FOOD GROUP | C13: =N13-D13-E13-F13-G13-H13-I13-J13-K13-L13-M13-D67-E67-F67-G67-H67-I67-J67-K67-L67-C67 -> 0 | E13: 1738.56 | N13: 1738.56
A14: INV26-04674 | B14: CAPITAL FINE MEATS | C14: =N14-D14-E14-F14-G14-H14-I14-J14-K14-L14-M14-D68-E68-F68-G68-H68-I68-J68-K68-L68-C68 -> 0 | E14: 1412.9 | N14: 1412.9
A15: 126639 | B15: ITALIAN BAKERY | C15: =N15-D15-E15-F15-G15-H15-I15-J15-K15-L15-M15-D69-E69-F69-G69-H69-I69-J69-K69-L69-C69 -> 309.43 | N15: 309.43
A16: 93892064 | B16: FRITO LAY CANADA VENDING | C16: =N16-D16-E16-F16-G16-H16-I16-J16-K16-L16-M16-D70-E70-F70-G70-H70-I70-J70-K70-L70-C70 -> 1797.4 | M16: 89.87 | N16: 1887.27
C17: =N17-D17-E17-F17-G17-H17-I17-J17-K17-L17-M17-D71-E71-F71-G71-H71-I71-J71-K71-L71-C71 -> 0
C18: =N18-D18-E18-F18-G18-H18-I18-J18-K18-L18-M18-D72-E72-F72-G72-H72-I72-J72-K72-L72-C72 -> 0
C19: =N19-D19-E19-F19-G19-H19-I19-J19-K19-L19-M19-D73-E73-F73-G73-H73-I73-J73-K73-L73-C73 -> 0
C20: =N20-D20-E20-F20-G20-H20-I20-J20-K20-L20-M20-D74-E74-F74-G74-H74-I74-J74-K74-L74-C74 -> 0
C21: =N21-D21-E21-F21-G21-H21-I21-J21-K21-L21-M21-D75-E75-F75-G75-H75-I75-J75-K75-L75-C75 -> 0
C22: =N22-D22-E22-F22-G22-H22-I22-J22-K22-L22-M22-D76-E76-F76-G76-H76-I76-J76-K76-L76-C76 -> 0
C23: =N23-D23-E23-F23-G23-H23-I23-J23-K23-L23-M23-D77-E77-F77-G77-H77-I77-J77-K77-L77-C77 -> 0
C24: =N24-D24-E24-F24-G24-H24-I24-J24-K24-L24-M24-D78-E78-F78-G78-H78-I78-J78-K78-L78-C78 -> 0
C25: =N25-D25-E25-F25-G25-H25-I25-J25-K25-L25-M25-D79-E79-F79-G79-H79-I79-J79-K79-L79-C79 -> 0
C26: =N26-D26-E26-F26-G26-H26-I26-J26-K26-L26-M26-D80-E80-F80-G80-H80-I80-J80-K80-L80-C80 -> 0
C27: =N27-D27-E27-F27-G27-H27-I27-J27-K27-L27-M27-D81-E81-F81-G81-H81-I81-J81-K81-L81-C81 -> 0
C28: =N28-D28-E28-F28-G28-H28-I28-J28-K28-L28-M28-D82-E82-F82-G82-H82-I82-J82-K82-L82-C82 -> 0
... C55: =N55-D55-E55-F55-G55-H55-I55-J55-K55-L55-M55-D109-E109-F109-G109-H109-I109-J109-K109-L109-C109 -> 0
A56: Freight | B56: THE GROCERY PEOPLE | C56: =C3 -> 0 | E56: =E3 -> 0 | F56: =F3 -> 0 | G56: =G3 -> 0 | H56: =H3 -> 0 | I56: =I3 -> 0 | J56: =J3 -> 0 | K56: =K3 -> 0 | L56: =L3 -> 0 | N56: =SUM(C56:M56)+SUM(C118:J118) -> 0
A57: Department Totals | C57: =SUM(C6:C56) -> 16851.14 | D57: =SUM(D6:D56) -> 0 | E57: =SUM(E6:E56) -> 3151.46 | F57: =SUM(F6:F56) -> 0 | G57: =SUM(G6:G56) -> 0 | H57: =SUM(H6:H56) -> 0 | I57: =SUM(I6:I56) -> 0 | J57: =SUM(J6:J56) -> 0 | ... N57: =SUM(N6:N56) -> 20581.1
N58: =IF(SUM(N6:N56)=SUM(C57:M57)+SUM(C110:L110),"","Sum error")
A59: Invoice Number | B59: Supplier Name | C59: Grocery Supplies | D59: Tobacco Supplies | E59: Meat Supplies | F59: Bakery Supplies | G59: B.In store Supplies | H59: Deli Supplies | I59: Produce Supplies | K59: Dairy Supplies | L59: Pharmacy Supplies
A60: =A6 -> 2246 | B60: =B6 -> NELLA WEST
A61: =A7 -> 54319807 | B61: =B7 -> PEPSICO
A62: =A8 -> 54319806 | B62: =B8 -> PEPSICO
A63: =A9 -> 53166884003 | B63: =B9 -> COCA COLA CANADA BOTTLING
A64: =A10 -> 226650718709 | B64: =B10 -> CANADA BREAD COMPANY
A65: =A11 -> 226650718710 | B65: =B11 -> CANADA BREAD COMPANY
A66: =A12 -> 2882618701 | B66: =B12 -> DIRECT PLUS FOOD GROUP
A67: =A13 -> 2882618702 | B67: =B13 -> DIRECT PLUS FOOD GROUP
A68: =A14 -> INV26-04674 | B68: =B14 -> CAPITAL FINE MEATS
A69: =A15 -> 126639 | B69: =B15 -> ITALIAN BAKERY
A70: =A16 -> 93892064 | B70: =B16 -> FRITO LAY CANADA VENDING
A71: =A17 | B71: =B17
... A109: =A55 | B109: =B55
A110: Department Totals | C110: =SUM(C60:C109) -> 0 | D110: =SUM(D60:D109) -> 0 | E110: =SUM(E60:E109) -> 0 | F110: =SUM(F60:F109) -> 0 | G110: =SUM(G60:G109) -> 0 | H110: =SUM(H60:H109) -> 0 | I110: =SUM(I60:I109) -> 0 | J110: =SUM(J60:J109) -> 0 | K110: =SUM(K60:K109) -> 0 | L110: 0

Sheet Tuesday WK3 (17)
B1: Freight | C1: Grocery | E1: Meat | F1: Bakery | G1: Bake off | H1: Deli | I1: Produce | J1: Produce Shrink | K1: Dairy | L1: Pharmacy | M1: Receiving Totals | N1: Total
B2: Name: | C2: ='Sunday WK1 (1)'!C2 -> 0.478 | E2: ='Sunday WK1 (1)'!E2 -> 0.099 | F2: ='Sunday WK1 (1)'!F2 -> 0 | G2: ='Sunday WK1 (1)'!G2 -> 0 | H2: ='Sunday WK1 (1)'!H2 -> 0 | I2: ='Sunday WK1 (1)'!I2 -> 0.159 | J2: ='Sunday WK1 (1)'!J2 -> 0.122 | K2: ='Sunday WK1 (1)'!$K$2 -> 0.142 | L2: ='Sunday WK1 (1)'!L2 -> 0 | N2: =SUM(C2:M2) -> 1
B3: SHANNON | C3: =C2*$N$3 -> 186.85976 | E3: =E2*$N$3 -> 38.70108 | F3: =F2*$N$3 -> 0 | G3: =G2*$N$3 -> 0 | H3: =H2*$N$3 -> 0 | I3: =I2*$N$3 -> 62.15628 | J3: =J2*$N$3 -> 47.69224 | K3: =K2*$N$3 -> 55.51064 | L3: =L2*$N$3 -> 0 | N3: 390.92
A4: Receiving Date: | B4: ='Monday WK3 (16)'!$B$4+1 -> 46210
A5: Invoice Number | B5: Supplier Name | C5: Grocery Purchases | D5: Tobacco Purchases | E5: Meat Purchases | F5: Bakery Purchases | G5: Bakery In Store | H5: Deli Purchases | I5: Produce Purchases | J5: Produce Shrink | K5: Dairy Purchases | L5: Pharmacy Purchases | M5: GST | N5: Total Invoice**
A6: TO442 | B6: SAPUTO DAIRY PRODUCTS | C6: =N6-D6-E6-F6-G6-H6-I6-J6-K6-L6-M6-D60-E60-F60-G60-H60-I60-J60-K60-L60-C60 -> 0 | K6: -126.81 | N6: -126.81
A7: 4000258837 | B7: SAPUTO DAIRY PRODUCTS | C7: =N7-D7-E7-F7-G7-H7-I7-J7-K7-L7-M7-D61-E61-F61-G61-H61-I61-J61-K61-L61-C61 -> 0 | K7: -40.61 | N7: -40.61
A8: 6683608 | B8: THE GROCERY PEOPLE | C8: =N8-D8-E8-F8-G8-H8-I8-J8-K8-L8-M8-D62-E62-F62-G62-H62-I62-J62-K62-L62-C62 -> 134.68 | N8: 134.68
A9: 6685009 | B9: THE GROCERY PEOPLE | C9: =N9-D9-E9-F9-G9-H9-I9-J9-K9-L9-M9-D63-E63-F63-G63-H63-I63-J63-K63-L63-C63 -> 432.38 | N9: 432.38
A10: 6685246 | B10: THE GROCERY PEOPLE | C10: =N10-D10-E10-F10-G10-H10-I10-J10-K10-L10-M10-D64-E64-F64-G64-H64-I64-J64-K64-L64-C64 -> 0 | N10: 111.44 | O10: STORE SUPPLIES - KAY FOAMING HAND SOAP
A11: 6685789 | B11: THE GROCERY PEOPLE | C11: =N11-D11-E11-F11-G11-H11-I11-J11-K11-L11-M11-D65-E65-F65-G65-H65-I65-J65-K65-L65-C65 -> -7.1054274e-15 | E11: 99.66 | K11: 33.51 | N11: 133.17
A12: 5644808 | B12: THE GROCERY PEOPLE | C12: =N12-D12-E12-F12-G12-H12-I12-J12-K12-L12-M12-D66-E66-F66-G66-H66-I66-J66-K66-L66-C66 -> 0 | E12: 301.3 | N12: 301.3
A13: 5644827 | B13: THE GROCERY PEOPLE | C13: =N13-D13-E13-F13-G13-H13-I13-J13-K13-L13-M13-D67-E67-F67-G67-H67-I67-J67-K67-L67-C67 -> 0 | E13: 930.72 | N13: 930.72
A14: 5645168 | B14: THE GROCERY PEOPLE | C14: =N14-D14-E14-F14-G14-H14-I14-J14-K14-L14-M14-D68-E68-F68-G68-H68-I68-J68-K68-L68-C68 -> 3046.5 | N14: 3046.5
A15: 5645262 | B15: THE GROCERY PEOPLE | C15: =N15-D15-E15-F15-G15-H15-I15-J15-K15-L15-M15-D69-E69-F69-G69-H69-I69-J69-K69-L69-C69 -> 13373.85 | N15: 13373.85
A16: 5645264 | B16: THE GROCERY PEOPLE | C16: =N16-D16-E16-F16-G16-H16-I16-J16-K16-L16-M16-D70-E70-F70-G70-H70-I70-J70-K70-L70-C70 -> 138.02 | N16: 138.02
A17: 5645343 | B17: THE GROCERY PEOPLE | C17: =N17-D17-E17-F17-G17-H17-I17-J17-K17-L17-M17-D71-E71-F71-G71-H71-I71-J71-K71-L71-C71 -> 333.71 | E17: 62.51 | K17: 1698.77 | N17: 2094.99
A18: 5645344 | B18: THE GROCERY PEOPLE | C18: =N18-D18-E18-F18-G18-H18-I18-J18-K18-L18-M18-D72-E72-F72-G72-H72-I72-J72-K72-L72-C72 -> 0 | K18: 291.25 | N18: 291.25
A19: 8248372 | B19: THE GROCERY PEOPLE | C19: =N19-D19-E19-F19-G19-H19-I19-J19-K19-L19-M19-D73-E73-F73-G73-H73-I73-J73-K73-L73-C73 -> 0 | E19: 7165.37 | N19: 7165.37
A20: 5645167 | B20: THE GROCERY PEOPLE | C20: =N20-D20-E20-F20-G20-H20-I20-J20-K20-L20-M20-D74-E74-F74-G74-H74-I74-J74-K74-L74-C74 -> 2993.22 | N20: 2993.22
A21: 5645955 | B21: THE GROCERY PEOPLE | C21: =N21-D21-E21-F21-G21-H21-I21-J21-K21-L21-M21-D75-E75-F75-G75-H75-I75-J75-K75-L75-C75 -> 0 | I21: 3902.32 | N21: 3902.32
A22: 5646230 | B22: THE GROCERY PEOPLE | C22: =N22-D22-E22-F22-G22-H22-I22-J22-K22-L22-M22-D76-E76-F76-G76-H76-I76-J76-K76-L76-C76 -> 0 | I22: 84 | N22: 84
A23: 6669955 | B23: FEDERATED CO-OPERATIVES | C23: =N23-D23-E23-F23-G23-H23-I23-J23-K23-L23-M23-D77-E77-F77-G77-H77-I77-J77-K77-L77-C77 -> 9.66 | N23: 9.66
A24: 6670981 | B24: FEDERATED CO-OPERATIVES | C24: =N24-D24-E24-F24-G24-H24-I24-J24-K24-L24-M24-D78-E78-F78-G78-H78-I78-J78-K78-L78-C78 -> 18.4 | N24: 18.4
A25: 6676411 | B25: FEDERATED CO-OPERATIVES | C25: =N25-D25-E25-F25-G25-H25-I25-J25-K25-L25-M25-D79-E79-F79-G79-H79-I79-J79-K79-L79-C79 -> 48.46 | N25: 48.46
A26: 4003757420 | B26: SAPUTO DAIRY PRODUCTS | C26: =N26-D26-E26-F26-G26-H26-I26-J26-K26-L26-M26-D80-E80-F80-G80-H80-I80-J80-K80-L80-C80 -> 1.0913492e-13 | K26: 3616.25 | M26: 0.13 | N26: 3616.38
A27: 118900 | B27: KENNELLI SPRINGS | C27: =N27-D27-E27-F27-G27-H27-I27-J27-K27-L27-M27-D81-E81-F81-G81-H81-I81-J81-K81-L81-C81 -> 167 | M27: 0.75 | N27: 167.75
A28: 94183777 | B28: FRITO LAY CANADA RETAIL | C28: =N28-D28-E28-F28-G28-H28-I28-J28-K28-L28-M28-D82-E82-F82-G82-H82-I82-J82-K82-L82-C82 -> 538.6 | M28: 26.93 | N28: 565.53
A29: 77684160 | B29: FRITO LAY CANADA RETAIL | C29: =N29-D29-E29-F29-G29-H29-I29-J29-K29-L29-M29-D83-E83-F83-G83-H83-I83-J83-K83-L83-C83 -> -147.86 | M29: -7.4 | N29: -155.26
A30: 7726188001 | B30: COMPLETE DISTRIBUTION NETWORK | C30: =N30-D30-E30-F30-G30-H30-I30-J30-K30-L30-M30-D84-E84-F84-G84-H84-I84-J84-K84-L84-C84 -> 4801.54 | E30: 198.06 | M30: 141.62 | N30: 5141.22
A31: 179193 | B31: CW SHASKY & ASSOCIATES | C31: =N31-D31-E31-F31-G31-H31-I31-J31-K31-L31-M31-D85-E85-F85-G85-H85-I85-J85-K85-L85-C85 -> 7324.7 | M31: 8.75 | N31: 7333.45
A32: 89659 | B32: GECKO BEVERAGES | C32: =N32-D32-E32-F32-G32-H32-I32-J32-K32-L32-M32-D86-E86-F86-G86-H86-I86-J86-K86-L86-C86 -> 3331.5 | M32: 44.78 | N32: 3376.28
C33: =N33-D33-E33-F33-G33-H33-I33-J33-K33-L33-M33-D87-E87-F87-G87-H87-I87-J87-K87-L87-C87 -> 0
C34: =N34-D34-E34-F34-G34-H34-I34-J34-K34-L34-M34-D88-E88-F88-G88-H88-I88-J88-K88-L88-C88 -> 0
C35: =N35-D35-E35-F35-G35-H35-I35-J35-K35-L35-M35-D89-E89-F89-G89-H89-I89-J89-K89-L89-C89 -> 0
C36: =N36-D36-E36-F36-G36-H36-I36-J36-K36-L36-M36-D90-E90-F90-G90-H90-I90-J90-K90-L90-C90 -> 0
C37: =N37-D37-E37-F37-G37-H37-I37-J37-K37-L37-M37-D91-E91-F91-G91-H91-I91-J91-K91-L91-C91 -> 0
C38: =N38-D38-E38-F38-G38-H38-I38-J38-K38-L38-M38-D92-E92-F92-G92-H92-I92-J92-K92-L92-C92 -> 0
C39: =N39-D39-E39-F39-G39-H39-I39-J39-K39-L39-M39-D93-E93-F93-G93-H93-I93-J93-K93-L93-C93 -> 0
C40: =N40-D40-E40-F40-G40-H40-I40-J40-K40-L40-M40-D94-E94-F94-G94-H94-I94-J94-K94-L94-C94 -> 0
C41: =N41-D41-E41-F41-G41-H41-I41-J41-K41-L41-M41-D95-E95-F95-G95-H95-I95-J95-K95-L95-C95 -> 0
C42: =N42-D42-E42-F42-G42-H42-I42-J42-K42-L42-M42-D96-E96-F96-G96-H96-I96-J96-K96-L96-C96 -> 0
C43: =N43-D43-E43-F43-G43-H43-I43-J43-K43-L43-M43-D97-E97-F97-G97-H97-I97-J97-K97-L97-C97 -> 0
C44: =N44-D44-E44-F44-G44-H44-I44-J44-K44-L44-M44-D98-E98-F98-G98-H98-I98-J98-K98-L98-C98 -> 0
... C55: =N55-D55-E55-F55-G55-H55-I55-J55-K55-L55-M55-D109-E109-F109-G109-H109-I109-J109-K109-L109-C109 -> 0
A56: Freight | B56: THE GROCERY PEOPLE | C56: =C3 -> 186.85976 | E56: =E3 -> 38.70108 | F56: =F3 -> 0 | G56: =G3 -> 0 | H56: =H3 -> 0 | I56: =I3 -> 62.15628 | J56: =J3 -> 47.69224 | K56: =K3 -> 55.51064 | L56: =L3 -> 0 | N56: =SUM(C56:M56)+SUM(C118:J118) -> 390.92 | O56: BM#8523771, BOL REF#4862604,4862605,4862606,4862642
A57: Department Totals | C57: =SUM(C6:C56) -> 36731.22 | D57: =SUM(D6:D56) -> 0 | E57: =SUM(E6:E56) -> 8796.3211 | F57: =SUM(F6:F56) -> 0 | G57: =SUM(G6:G56) -> 0 | H57: =SUM(H6:H56) -> 0 | I57: =SUM(I6:I56) -> 4048.4763 | J57: =SUM(J6:J56) -> 47.69224 | ... N57: =SUM(N6:N56) -> 55478.58
N58: =IF(SUM(N6:N56)=SUM(C57:M57)+SUM(C110:K110),"","Sum error")
A59: Invoice Number | B59: Supplier Name | C59: Grocery Supplies | D59: Tobacco Supplies | E59: Meat Supplies | F59: Bakery Supplies | G59: B.In store Supplies | H59: Deli Supplies | I59: Produce Supplies | K59: Dairy Supplies | L59: Pharmacy Supplies
A60: =A6 -> TO442 | B60: =B6 -> SAPUTO DAIRY PRODUCTS
A61: =A7 -> 4000258837 | B61: =B7 -> SAPUTO DAIRY PRODUCTS
A62: =A8 -> 6683608 | B62: =B8 -> THE GROCERY PEOPLE
A63: =A9 -> 6685009 | B63: =B9 -> THE GROCERY PEOPLE
A64: =A10 -> 6685246 | B64: =B10 -> THE GROCERY PEOPLE | C64: 111.44 | M64: STORE SUPPLIES - KAY FOAMING HAND SOAP
A65: =A11 -> 6685789 | B65: =B11 -> THE GROCERY PEOPLE
A66: =A12 -> 5644808 | B66: =B12 -> THE GROCERY PEOPLE
A67: =A13 -> 5644827 | B67: =B13 -> THE GROCERY PEOPLE
A68: =A14 -> 5645168 | B68: =B14 -> THE GROCERY PEOPLE
A69: =A15 -> 5645262 | B69: =B15 -> THE GROCERY PEOPLE
A70: =A16 -> 5645264 | B70: =B16 -> THE GROCERY PEOPLE
A71: =A17 -> 5645343 | B71: =B17 -> THE GROCERY PEOPLE
A72: =A18 -> 5645344 | B72: =B18 -> THE GROCERY PEOPLE
A73: =A19 -> 8248372 | B73: =B19 -> THE GROCERY PEOPLE
A74: =A20 -> 5645167 | B74: =B20 -> THE GROCERY PEOPLE
A75: =A21 -> 5645955 | B75: =B21 -> THE GROCERY PEOPLE
A76: =A22 -> 5646230 | B76: =B22 -> THE GROCERY PEOPLE
... A109: =A55 | B109: =B55
A110: Department Totals | C110: =SUM(C60:C109) -> 111.44 | D110: =SUM(D60:D109) -> 0 | E110: =SUM(E60:E109) -> 0 | F110: =SUM(F60:F109) -> 0 | G110: =SUM(G60:G109) -> 0 | H110: =SUM(H60:H109) -> 0 | I110: =SUM(I60:I109) -> 0 | J110: =SUM(J60:J109) -> 0 | K110: =SUM(K60:K109) -> 0 | L110: 0

Sheet Wednesday WK3 (18)
B1: Freight | C1: Grocery | E1: Meat | F1: Bakery | G1: Bake off | H1: Deli | I1: Produce | J1: Produce Shrink | K1: Dairy | L1: Pharmacy | M1: Receiving Totals | N1: Total
B2: Name: | C2: ='Sunday WK1 (1)'!C2 -> 0.478 | E2: ='Sunday WK1 (1)'!E2 -> 0.099 | F2: ='Sunday WK1 (1)'!F2 -> 0 | G2: ='Sunday WK1 (1)'!G2 -> 0 | H2: ='Sunday WK1 (1)'!H2 -> 0 | I2: ='Sunday WK1 (1)'!I2 -> 0.159 | J2: ='Sunday WK1 (1)'!J2 -> 0.122 | K2: ='Sunday WK1 (1)'!$K$2 -> 0.142 | L2: ='Sunday WK1 (1)'!L2 -> 0 | N2: =SUM(C2:M2) -> 1
B3: SHANNON | C3: =C2*$N$3 -> 0 | E3: =E2*$N$3 -> 0 | F3: =F2*$N$3 -> 0 | G3: =G2*$N$3 -> 0 | H3: =H2*$N$3 -> 0 | I3: =I2*$N$3 -> 0 | J3: =J2*$N$3 -> 0 | K3: =K2*$N$3 -> 0 | L3: =L2*$N$3 -> 0
A4: Receiving Date: | B4: ='Tuesday WK3 (17)'!$B$4+1 -> 46211
A5: Invoice Number | B5: Supplier Name | C5: Grocery Purchases | D5: Tobacco Purchases | E5: Meat Purchases | F5: Bakery Purchases | G5: Bakery In Store | H5: Deli Purchases | I5: Produce Purchases | J5: Produce Shrink | K5: Dairy Purchases | L5: Pharmacy Purchases | M5: GST | N5: Total Invoice**
A6: 82849859 | B6: OLD DUTCH FOODS | C6: =N6-D6-E6-F6-G6-H6-I6-J6-K6-L6-M6-D60-E60-F60-G60-H60-I60-J60-K60-L60-C60 -> 519.38 | M6: 25.97 | N6: 545.35
A7: INV26-04757 | B7: CAPITAL FINE MEATS | C7: =N7-D7-E7-F7-G7-H7-I7-J7-K7-L7-M7-D61-E61-F61-G61-H61-I61-J61-K61-L61-C61 -> 0 | E7: 1849.5 | N7: 1849.5
A8: SO2514225 | B8: HARLAN FAIRBANKS | C8: =N8-D8-E8-F8-G8-H8-I8-J8-K8-L8-M8-D62-E62-F62-G62-H62-I62-J62-K62-L62-C62 -> 1257.15 | M8: 35.69 | N8: 1292.84
A9: 00023365 | B9: SEVEN SEAS FISH CO | C9: =N9-D9-E9-F9-G9-H9-I9-J9-K9-L9-M9-D63-E63-F63-G63-H63-I63-J63-K63-L63-C63 -> 539.75 | N9: 539.75
C10: =N10-D10-E10-F10-G10-H10-I10-J10-K10-L10-M10-D64-E64-F64-G64-H64-I64-J64-K64-L64-C64 -> 0
C11: =N11-D11-E11-F11-G11-H11-I11-J11-K11-L11-M11-D65-E65-F65-G65-H65-I65-J65-K65-L65-C65 -> 0
C12: =N12-D12-E12-F12-G12-H12-I12-J12-K12-L12-M12-D66-E66-F66-G66-H66-I66-J66-K66-L66-C66 -> 0
C13: =N13-D13-E13-F13-G13-H13-I13-J13-K13-L13-M13-D67-E67-F67-G67-H67-I67-J67-K67-L67-C67 -> 0
C14: =N14-D14-E14-F14-G14-H14-I14-J14-K14-L14-M14-D68-E68-F68-G68-H68-I68-J68-K68-L68-C68 -> 0
C15: =N15-D15-E15-F15-G15-H15-I15-J15-K15-L15-M15-D69-E69-F69-G69-H69-I69-J69-K69-L69-C69 -> 0
C16: =N16-D16-E16-F16-G16-H16-I16-J16-K16-L16-M16-D70-E70-F70-G70-H70-I70-J70-K70-L70-C70 -> 0
C17: =N17-D17-E17-F17-G17-H17-I17-J17-K17-L17-M17-D71-E71-F71-G71-H71-I71-J71-K71-L71-C71 -> 0
C18: =N18-D18-E18-F18-G18-H18-I18-J18-K18-L18-M18-D72-E72-F72-G72-H72-I72-J72-K72-L72-C72 -> 0
C19: =N19-D19-E19-F19-G19-H19-I19-J19-K19-L19-M19-D73-E73-F73-G73-H73-I73-J73-K73-L73-C73 -> 0
C20: =N20-D20-E20-F20-G20-H20-I20-J20-K20-L20-M20-D74-E74-F74-G74-H74-I74-J74-K74-L74-C74 -> 0
C21: =N21-D21-E21-F21-G21-H21-I21-J21-K21-L21-M21-D75-E75-F75-G75-H75-I75-J75-K75-L75-C75 -> 0
... C55: =N55-D55-E55-F55-G55-H55-I55-J55-K55-L55-M55-D109-E109-F109-G109-H109-I109-J109-K109-L109-C109 -> 0
A56: Freight | B56: THE GROCERY PEOPLE | C56: =C3 -> 0 | E56: =E3 -> 0 | F56: =F3 -> 0 | G56: =G3 -> 0 | H56: =H3 -> 0 | I56: =I3 -> 0 | J56: =J3 -> 0 | K56: =K3 -> 0 | L56: =L3 -> 0 | N56: =SUM(C56:M56)+SUM(C118:J118) -> 0
A57: Department Totals | C57: =SUM(C6:C56) -> 2316.28 | D57: =SUM(D6:D56) -> 0 | E57: =SUM(E6:E56) -> 1849.5 | F57: =SUM(F6:F56) -> 0 | G57: =SUM(G6:G56) -> 0 | H57: =SUM(H6:H56) -> 0 | I57: =SUM(I6:I56) -> 0 | J57: =SUM(J6:J56) -> 0 | ... N57: =SUM(N6:N56) -> 4227.44
N58: =IF(SUM(N6:N56)=SUM(C57:M57)+SUM(D110:L110),"","Sum error")
A59: Invoice Number | B59: Supplier Name | C59: Grocery Supplies | D59: Tobacco Supplies | E59: Meat Supplies | F59: Bakery Supplies | G59: B.In store Supplies | H59: Deli Supplies | I59: Produce Supplies | K59: Dairy Supplies | L59: Pharmacy Supplies
A60: =A6 -> 82849859 | B60: =B6 -> OLD DUTCH FOODS
A61: =A7 -> INV26-04757 | B61: =B7 -> CAPITAL FINE MEATS
A62: =A8 -> SO2514225 | B62: =B8 -> HARLAN FAIRBANKS
A63: =A9 -> 00023365 | B63: =B9 -> SEVEN SEAS FISH CO
A64: =A10 | B64: =B10
A65: =A11 | B65: =B11
A66: =A12 | B66: =B12
A67: =A13 | B67: =B13
A68: =A14 | B68: =B14
A69: =A15 | B69: =B15
A70: =A16 | B70: =B16
A71: =A17 | B71: =B17
... A109: =A55 | B109: =B55
A110: Department Totals | C110: =SUM(C60:C109) -> 0 | D110: =SUM(D60:D109) -> 0 | E110: =SUM(E60:E109) -> 0 | F110: =SUM(F60:F109) -> 0 | G110: =SUM(G60:G109) -> 0 | H110: =SUM(H60:H109) -> 0 | I110: =SUM(I60:I109) -> 0 | J110: =SUM(J60:J109) -> 0 | K110: =SUM(K60:K109) -> 0 | L110: 0

Sheet Thursday WK3 (19)
B1: Freight | C1: Grocery | E1: Meat | F1: Bakery | G1: Bake off | H1: Deli | I1: Produce | J1: Produce Shrink | K1: Dairy | L1: Pharmacy | M1: Receiving Totals | N1: Total
B2: Name: | C2: ='Sunday WK1 (1)'!C2 -> 0.478 | E2: ='Sunday WK1 (1)'!E2 -> 0.099 | F2: ='Sunday WK1 (1)'!F2 -> 0 | G2: ='Sunday WK1 (1)'!G2 -> 0 | H2: ='Sunday WK1 (1)'!H2 -> 0 | I2: ='Sunday WK1 (1)'!I2 -> 0.159 | J2: ='Sunday WK1 (1)'!J2 -> 0.122 | K2: ='Sunday WK1 (1)'!$K$2 -> 0.142 | L2: ='Sunday WK1 (1)'!L2 -> 0 | N2: =SUM(C2:M2) -> 1
B3: SHANNON | C3: =C2*$N$3 -> 261.90098 | E3: =E2*$N$3 -> 54.24309 | F3: =F2*$N$3 -> 0 | G3: =G2*$N$3 -> 0 | H3: =H2*$N$3 -> 0 | I3: =I2*$N$3 -> 87.11769 | J3: =J2*$N$3 -> 66.84502 | K3: =K2*$N$3 -> 77.80322 | L3: =L2*$N$3 -> 0 | N3: 547.91
A4: Receiving Date: | B4: ='Wednesday WK3 (18)'!$B$4+1 -> 46212
A5: Invoice Number | B5: Supplier Name | C5: Grocery Purchases | D5: Tobacco Purchases | E5: Meat Purchases | F5: Bakery Purchases | G5: Bakery In Store | H5: Deli Purchases | I5: Produce Purchases | J5: Produce Shrink | K5: Dairy Purchases | L5: Pharmacy Purchases | M5: GST | N5: Total Invoice**
A6: 4003765649 | B6: SAPUTO DAIRY PRODUCTS | C6: =N6-D6-E6-F6-G6-H6-I6-J6-K6-L6-M6-D60-E60-F60-G60-H60-I60-J60-K60-L60-C60 -> 0 | K6: 54.6 | N6: 54.6
A7: 4003773251 | B7: SAPUTO DAIRY PRODUCTS | C7: =N7-D7-E7-F7-G7-H7-I7-J7-K7-L7-M7-D61-E61-F61-G61-H61-I61-J61-K61-L61-C61 -> -1.0913492e-13 | K7: 3199.75 | M7: 0.37 | N7: 3200.12
A8: 573137 | B8: CFI FOODS LTD | C8: =N8-D8-E8-F8-G8-H8-I8-J8-K8-L8-M8-D62-E62-F62-G62-H62-I62-J62-K62-L62-C62 -> 12127.8 | M8: 11.25 | N8: 12139.05
A9: 964065 | B9: HARVEST MEATS | C9: =N9-D9-E9-F9-G9-H9-I9-J9-K9-L9-M9-D63-E63-F63-G63-H63-I63-J63-K63-L63-C63 -> 0 | E9: 289.34 | N9: 289.34
A10: 3283863 | B10: LILYDALE SOFINA FOODS | C10: =N10-D10-E10-F10-G10-H10-I10-J10-K10-L10-M10-D64-E64-F64-G64-H64-I64-J64-K64-L64-C64 -> 0 | E10: 20.16 | N10: 20.16
A11: 6689252 | B11: THE GROCERY PEOPLE | C11: =N11-D11-E11-F11-G11-H11-I11-J11-K11-L11-M11-D65-E65-F65-G65-H65-I65-J65-K65-L65-C65 -> 0 | E11: 5329.91 | N11: 5329.91
A12: 6687835 | B12: THE GROCERY PEOPLE | C12: =N12-D12-E12-F12-G12-H12-I12-J12-K12-L12-M12-D66-E66-F66-G66-H66-I66-J66-K66-L66-C66 -> 0 | E12: 51.26 | N12: 51.26
A13: 6687836 | B13: THE GROCERY PEOPLE | C13: =N13-D13-E13-F13-G13-H13-I13-J13-K13-L13-M13-D67-E67-F67-G67-H67-I67-J67-K67-L67-C67 -> 0 | E13: 154.97 | N13: 154.97
A14: 6688409 | B14: THE GROCERY PEOPLE | C14: =N14-D14-E14-F14-G14-H14-I14-J14-K14-L14-M14-D68-E68-F68-G68-H68-I68-J68-K68-L68-C68 -> 376.21 | E14: 41.99 | N14: 418.2
A15: 6691251 | B15: THE GROCERY PEOPLE | C15: =N15-D15-E15-F15-G15-H15-I15-J15-K15-L15-M15-D69-E69-F69-G69-H69-I69-J69-K69-L69-C69 -> 0 | K15: 245.19 | N15: 245.19
A16: 6691252 | B16: THE GROCERY PEOPLE | C16: =N16-D16-E16-F16-G16-H16-I16-J16-K16-L16-M16-D70-E70-F70-G70-H70-I70-J70-K70-L70-C70 -> 0 | K16: 18.47 | N16: 18.47
A17: 6688318 | B17: THE GROCERY PEOPLE | C17: =N17-D17-E17-F17-G17-H17-I17-J17-K17-L17-M17-D71-E71-F71-G71-H71-I71-J71-K71-L71-C71 -> 95.52 | N17: 95.52
A18: 5647503 | B18: THE GROCERY PEOPLE | C18: =N18-D18-E18-F18-G18-H18-I18-J18-K18-L18-M18-D72-E72-F72-G72-H72-I72-J72-K72-L72-C72 -> 6241.36 | N18: 6241.36
A19: 5647791 | B19: THE GROCERY PEOPLE | C19: =N19-D19-E19-F19-G19-H19-I19-J19-K19-L19-M19-D73-E73-F73-G73-H73-I73-J73-K73-L73-C73 -> 1363.21 | N19: 1363.21
A20: 5647952 | B20: THE GROCERY PEOPLE | C20: =N20-D20-E20-F20-G20-H20-I20-J20-K20-L20-M20-D74-E74-F74-G74-H74-I74-J74-K74-L74-C74 -> 4777.11 | N20: 4777.11
A21: 5648240 | B21: THE GROCERY PEOPLE | C21: =N21-D21-E21-F21-G21-H21-I21-J21-K21-L21-M21-D75-E75-F75-G75-H75-I75-J75-K75-L75-C75 -> 12896.75 | N21: 12896.75
A22: 5648356 | B22: THE GROCERY PEOPLE | C22: =N22-D22-E22-F22-G22-H22-I22-J22-K22-L22-M22-D76-E76-F76-G76-H76-I76-J76-K76-L76-C76 -> 31.96 | K22: 2043.54 | N22: 2075.5
A23: 8248666 | B23: THE GROCERY PEOPLE | C23: =N23-D23-E23-F23-G23-H23-I23-J23-K23-L23-M23-D77-E77-F77-G77-H77-I77-J77-K77-L77-C77 -> 0 | E23: 877.26 | N23: 877.26
A24: 8249585 | B24: THE GROCERY PEOPLE | C24: =N24-D24-E24-F24-G24-H24-I24-J24-K24-L24-M24-D78-E78-F78-G78-H78-I78-J78-K78-L78-C78 -> 0 | E24: 656.21 | N24: 656.21
A25: 8250038 | B25: THE GROCERY PEOPLE | C25: =N25-D25-E25-F25-G25-H25-I25-J25-K25-L25-M25-D79-E79-F79-G79-H79-I79-J79-K79-L79-C79 -> 0 | E25: 66.35 | N25: 66.35
A26: 8250087 | B26: THE GROCERY PEOPLE | C26: =N26-D26-E26-F26-G26-H26-I26-J26-K26-L26-M26-D80-E80-F80-G80-H80-I80-J80-K80-L80-C80 -> 0 | E26: 53.52 | N26: 53.52
A27: 5646370 | B27: THE GROCERY PEOPLE | C27: =N27-D27-E27-F27-G27-H27-I27-J27-K27-L27-M27-D81-E81-F81-G81-H81-I81-J81-K81-L81-C81 -> 1595.81 | N27: 1595.81
A28: 5647261 | B28: THE GROCERY PEOPLE | C28: =N28-D28-E28-F28-G28-H28-I28-J28-K28-L28-M28-D82-E82-F82-G82-H82-I82-J82-K82-L82-C82 -> 161.75 | E28: 3302.26 | N28: 3464.01
A29: 5645759 | B29: THE GROCERY PEOPLE | C29: =N29-D29-E29-F29-G29-H29-I29-J29-K29-L29-M29-D83-E83-F83-G83-H83-I83-J83-K83-L83-C83 -> 37.43 | N29: 37.43
A30: 5646250 | B30: THE GROCERY PEOPLE | C30: =N30-D30-E30-F30-G30-H30-I30-J30-K30-L30-M30-D84-E84-F84-G84-H84-I84-J84-K84-L84-C84 -> 92.57 | N30: 92.57
A31: 5647200 | B31: THE GROCERY PEOPLE | C31: =N31-D31-E31-F31-G31-H31-I31-J31-K31-L31-M31-D85-E85-F85-G85-H85-I85-J85-K85-L85-C85 -> 87 | N31: 87
A32: 5647950 | B32: THE GROCERY PEOPLE | C32: =N32-D32-E32-F32-G32-H32-I32-J32-K32-L32-M32-D86-E86-F86-G86-H86-I86-J86-K86-L86-C86 -> 122.08 | N32: 122.08
A33: 5647951 | B33: THE GROCERY PEOPLE | C33: =N33-D33-E33-F33-G33-H33-I33-J33-K33-L33-M33-D87-E87-F87-G87-H87-I87-J87-K87-L87-C87 -> 11110.26 | N33: 11110.26
A34: 5648089 | B34: THE GROCERY PEOPLE | C34: =N34-D34-E34-F34-G34-H34-I34-J34-K34-L34-M34-D88-E88-F88-G88-H88-I88-J88-K88-L88-C88 -> 1755 | N34: 1755
A35: 5648678 | B35: THE GROCERY PEOPLE | C35: =N35-D35-E35-F35-G35-H35-I35-J35-K35-L35-M35-D89-E89-F89-G89-H89-I89-J89-K89-L89-C89 -> 21.83 | E35: 26.04 | K35: 76.22 | N35: 124.09
A36: 5648962 | B36: THE GROCERY PEOPLE | C36: =N36-D36-E36-F36-G36-H36-I36-J36-K36-L36-M36-D90-E90-F90-G90-H90-I90-J90-K90-L90-C90 -> 0 | I36: 3521.24 | N36: 3521.24
A37: 5648978 | B37: THE GROCERY PEOPLE | C37: =N37-D37-E37-F37-G37-H37-I37-J37-K37-L37-M37-D91-E91-F91-G91-H91-I91-J91-K91-L91-C91 -> 0 | I37: 117.77 | N37: 117.77
A38: 5649068 | B38: THE GROCERY PEOPLE | C38: =N38-D38-E38-F38-G38-H38-I38-J38-K38-L38-M38-D92-E92-F92-G92-H92-I92-J92-K92-L92-C92 -> 0 | I38: 65 | N38: 65
A39: 5649184 | B39: THE GROCERY PEOPLE | C39: =N39-D39-E39-F39-G39-H39-I39-J39-K39-L39-M39-D93-E93-F93-G93-H93-I93-J93-K93-L93-C93 -> 0 | I39: 120.27 | N39: 120.27
A40: 5647503A | B40: THE GROCERY PEOPLE | C40: =N40-D40-E40-F40-G40-H40-I40-J40-K40-L40-M40-D94-E94-F94-G94-H94-I94-J94-K94-L94-C94 -> 16956.1 | N40: 16956.1
A41: 53224643003 | B41: COCA COLA CANADA BOTTLING | C41: =N41-D41-E41-F41-G41-H41-I41-J41-K41-L41-M41-D95-E95-F95-G95-H95-I95-J95-K95-L95-C95 -> 6566.56 | M41: 235.79 | N41: 6802.35
A42: 126728 | B42: ITALIAN BAKERY | C42: =N42-D42-E42-F42-G42-H42-I42-J42-K42-L42-M42-D96-E96-F96-G96-H96-I96-J96-K96-L96-C96 -> 361.51 | N42: 361.51
A43: 0117562 | B43: G & L DISTRIBUTORS | C43: =N43-D43-E43-F43-G43-H43-I43-J43-K43-L43-M43-D97-E97-F97-G97-H97-I97-J97-K97-L97-C97 -> 2146.27 | M43: 107.31 | N43: 2253.58
A44: 226650719094 | B44: CANADA BREAD COMPANY | C44: =N44-D44-E44-F44-G44-H44-I44-J44-K44-L44-M44-D98-E98-F98-G98-H98-I98-J98-K98-L98-C98 -> 498.24 | N44: 498.24
A45: 226650719095 | B45: CANADA BREAD COMPANY | C45: =N45-D45-E45-F45-G45-H45-I45-J45-K45-L45-M45-D99-E99-F99-G99-H99-I99-J99-K99-L99-C99 -> -379.21 | N45: -379.21
A46: 2882619002 | B46: DIRECT PLUS FOOD GROUP | C46: =N46-D46-E46-F46-G46-H46-I46-J46-K46-L46-M46-D100-E100-F100-G100-H100-I100-J100-K100-L100-C100 -> 45 | N46: 45
A47: 2882619001 | B47: DIRECT PLUS FOOD GROUP | C47: =N47-D47-E47-F47-G47-H47-I47-J47-K47-L47-M47-D101-E101-F101-G101-H101-I101-J101-K101-L101-C101 -> -2.1849189e-13 | E47: 3291.05 | M47: 5.49 | N47: 3296.54
A48: 2882619003 | B48: DIRECT PLUS FOOD GROUP | C48: =N48-D48-E48-F48-G48-H48-I48-J48-K48-L48-M48-D102-E102-F102-G102-H102-I102-J102-K102-L102-C102 -> -16.25 | N48: -16.25
A49: 2882619004 | B49: DIRECT PLUS FOOD GROUP | C49: =N49-D49-E49-F49-G49-H49-I49-J49-K49-L49-M49-D103-E103-F103-G103-H103-I103-J103-K103-L103-C103 -> 0 | E49: -130.53 | N49: -130.53
C50: =N50-D50-E50-F50-G50-H50-I50-J50-K50-L50-M50-D104-E104-F104-G104-H104-I104-J104-K104-L104-C104 -> 0
C51: =N51-D51-E51-F51-G51-H51-I51-J51-K51-L51-M51-D105-E105-F105-G105-H105-I105-J105-K105-L105-C105 -> 0
C52: =N52-D52-E52-F52-G52-H52-I52-J52-K52-L52-M52-D106-E106-F106-G106-H106-I106-J106-K106-L106-C106 -> 0
C53: =N53-D53-E53-F53-G53-H53-I53-J53-K53-L53-M53-D107-E107-F107-G107-H107-I107-J107-K107-L107-C107 -> 0
C54: =N54-D54-E54-F54-G54-H54-I54-J54-K54-L54-M54-D108-E108-F108-G108-H108-I108-J108-K108-L108-C108 -> 0
C55: =N55-D55-E55-F55-G55-H55-I55-J55-K55-L55-M55-D109-E109-F109-G109-H109-I109-J109-K109-L109-C109 -> 0
A56: Freight | B56: THE GROCERY PEOPLE | C56: =C3 -> 261.90098 | E56: =E3 -> 54.24309 | F56: =F3 -> 0 | G56: =G3 -> 0 | H56: =H3 -> 0 | I56: =I3 -> 87.11769 | J56: =J3 -> 66.84502 | K56: =K3 -> 77.80322 | L56: =L3 -> 0 | N56: =SUM(C56:M56)+SUM(C118:J118) -> 547.91 | O56: BM#8533044, BOL REF #4858273,4858276,4858275,4858274, BM#8533091, BOL REF#4858284,4858283
A57: Department Totals | C57: =SUM(C6:C56) -> 79333.771 | D57: =SUM(D6:D56) -> 0 | E57: =SUM(E6:E56) -> 14084.033 | F57: =SUM(F6:F56) -> 0 | G57: =SUM(G6:G56) -> 0 | H57: =SUM(H6:H56) -> 0 | I57: =SUM(I6:I56) -> 3911.3977 | J57: =SUM(J6:J56) -> 66.84502 | ... N57: =SUM(N6:N56) -> 103471.83
N58: =IF(SUM(N6:N56)=SUM(C57:M57)+SUM(C110:K110),"","Sum error")
A59: Invoice Number | B59: Supplier Name | C59: Grocery Supplies | D59: Tobacco Supplies | E59: Meat Supplies | F59: Bakery Supplies | G59: B.In store Supplies | H59: Deli Supplies | I59: Produce Supplies | K59: Dairy Supplies | L59: Pharmacy Supplies
A60: =A6 -> 4003765649 | B60: =B6 -> SAPUTO DAIRY PRODUCTS
A61: =A7 -> 4003773251 | B61: =B7 -> SAPUTO DAIRY PRODUCTS
A62: =A8 -> 573137 | B62: =B8 -> CFI FOODS LTD
A63: =A9 -> 964065 | B63: =B9 -> HARVEST MEATS
A64: =A10 -> 3283863 | B64: =B10 -> LILYDALE SOFINA FOODS
A65: =A11 -> 6689252 | B65: =B11 -> THE GROCERY PEOPLE
A66: =A12 -> 6687835 | B66: =B12 -> THE GROCERY PEOPLE
A67: =A13 -> 6687836 | B67: =B13 -> THE GROCERY PEOPLE
A68: =A14 -> 6688409 | B68: =B14 -> THE GROCERY PEOPLE
A69: =A15 -> 6691251 | B69: =B15 -> THE GROCERY PEOPLE
A70: =A16 -> 6691252 | B70: =B16 -> THE GROCERY PEOPLE
A71: =A17 -> 6688318 | B71: =B17 -> THE GROCERY PEOPLE
... A109: =A55 | B109: =B55
A110: Department Totals | C110: =SUM(C60:C109) -> 0 | D110: =SUM(D60:D109) -> 0 | E110: =SUM(E60:E109) -> 0 | F110: =SUM(F60:F109) -> 0 | G110: =SUM(G60:G109) -> 0 | H110: =SUM(H60:H109) -> 0 | I110: =SUM(I60:I109) -> 0 | J110: =SUM(J60:J109) -> 0 | K110: =SUM(K60:K109) -> 0 | L110: 0

Sheet Friday WK3 (20)
B1: Freight | C1: Grocery | E1: Meat | F1: Bakery | G1: Bake off | H1: Deli | I1: Produce | J1: Produce Shrink | K1: Dairy | L1: Pharmacy | M1: Receiving Totals | N1: Total
B2: Name: | C2: ='Sunday WK1 (1)'!C2 -> 0.478 | E2: ='Sunday WK1 (1)'!E2 -> 0.099 | F2: 0 | G2: 0 | H2: 0 | I2: ='Sunday WK1 (1)'!I2 -> 0.159 | J2: ='Sunday WK1 (1)'!J2 -> 0.122 | K2: ='Sunday WK1 (1)'!$K$2 -> 0.142 | L2: 0 | N2: =SUM(C2:M2) -> 1
B3: SHANNON | C3: =C2*$N$3 -> 0 | E3: =E2*$N$3 -> 0 | F3: =F2*$N$3 -> 0 | G3: =G2*$N$3 -> 0 | H3: =H2*$N$3 -> 0 | I3: =I2*$N$3 -> 0 | J3: =J2*$N$3 -> 0 | K3: =K2*$N$3 -> 0 | L3: =L2*$N$3 -> 0 | N3: 0
A4: Receiving Date: | B4: ='Thursday WK3 (19)'!$B$4+1 -> 46213
A5: Invoice Number | B5: Supplier Name | C5: Grocery Purchases | D5: Tobacco Purchases | E5: Meat Purchases | F5: Bakery Purchases | G5: Bakery In Store | H5: Deli Purchases | I5: Produce Purchases | J5: Produce Shrink | K5: Dairy Purchases | L5: Pharmacy Purchases | M5: GST | N5: Total Invoice**
A6: 82849874 | B6: OLD DUTCH FOODS | C6: =N6-D6-E6-F6-G6-H6-I6-J6-K6-L6-M6-D60-E60-F60-G60-H60-I60-J60-K60-L60-C60 -> 671.45 | M6: 33.57 | N6: 705.02
A7: 82849875 | B7: OLD DUTCH FOODS | C7: =N7-D7-E7-F7-G7-H7-I7-J7-K7-L7-M7-D61-E61-F61-G61-H61-I61-J61-K61-L61-C61 -> -41.51 | M7: -2.08 | N7: -43.59
A8: 95463140 | B8: FRITO LAY CANADA RETAIL | C8: =N8-D8-E8-F8-G8-H8-I8-J8-K8-L8-M8-D62-E62-F62-G62-H62-I62-J62-K62-L62-C62 -> 605.02 | M8: 30.24 | N8: 635.26
C9: =N9-D9-E9-F9-G9-H9-I9-J9-K9-L9-M9-D63-E63-F63-G63-H63-I63-J63-K63-L63-C63 -> 0
C10: =N10-D10-E10-F10-G10-H10-I10-J10-K10-L10-M10-D64-E64-F64-G64-H64-I64-J64-K64-L64-C64 -> 0
C11: =N11-D11-E11-F11-G11-H11-I11-J11-K11-L11-M11-D65-E65-F65-G65-H65-I65-J65-K65-L65-C65 -> 0
C12: =N12-D12-E12-F12-G12-H12-I12-J12-K12-L12-M12-D66-E66-F66-G66-H66-I66-J66-K66-L66-C66 -> 0
C13: =N13-D13-E13-F13-G13-H13-I13-J13-K13-L13-M13-D67-E67-F67-G67-H67-I67-J67-K67-L67-C67 -> 0
C14: =N14-D14-E14-F14-G14-H14-I14-J14-K14-L14-M14-D68-E68-F68-G68-H68-I68-J68-K68-L68-C68 -> 0
C15: =N15-D15-E15-F15-G15-H15-I15-J15-K15-L15-M15-D69-E69-F69-G69-H69-I69-J69-K69-L69-C69 -> 0
C16: =N16-D16-E16-F16-G16-H16-I16-J16-K16-L16-M16-D70-E70-F70-G70-H70-I70-J70-K70-L70-C70 -> 0
C17: =N17-D17-E17-F17-G17-H17-I17-J17-K17-L17-M17-D71-E71-F71-G71-H71-I71-J71-K71-L71-C71 -> 0
C18: =N18-D18-E18-F18-G18-H18-I18-J18-K18-L18-M18-D72-E72-F72-G72-H72-I72-J72-K72-L72-C72 -> 0
C19: =N19-D19-E19-F19-G19-H19-I19-J19-K19-L19-M19-D73-E73-F73-G73-H73-I73-J73-K73-L73-C73 -> 0
C20: =N20-D20-E20-F20-G20-H20-I20-J20-K20-L20-M20-D74-E74-F74-G74-H74-I74-J74-K74-L74-C74 -> 0
... C55: =N55-D55-E55-F55-G55-H55-I55-J55-K55-L55-M55-D109-E109-F109-G109-H109-I109-J109-K109-L109-C109 -> 0
A56: Freight | B56: THE GROCERY PEOPLE | C56: =C3 -> 0 | E56: =E3 -> 0 | F56: =F3 -> 0 | G56: =G3 -> 0 | H56: =H3 -> 0 | I56: =I3 -> 0 | J56: =J3 -> 0 | K56: =K3 -> 0 | L56: =L3 -> 0 | N56: =SUM(C56:M56)+SUM(C118:J118) -> 0 | O56: BM#8424672, BOL REF #4826301
A57: Department Totals | C57: =SUM(C6:C56) -> 1234.96 | D57: =SUM(D6:D56) -> 0 | E57: =SUM(E6:E56) -> 0 | F57: =SUM(F6:F56) -> 0 | G57: =SUM(G6:G56) -> 0 | H57: =SUM(H6:H56) -> 0 | I57: =SUM(I6:I56) -> 0 | J57: =SUM(J6:J56) -> 0 | ... N57: =SUM(N6:N56) -> 1296.69
N58: =IF(SUM(N6:N56)=SUM(C57:M57)+SUM(D110:L110),"","Sum error")
A59: Invoice Number | B59: Supplier Name | C59: Grocery Supplies | D59: Tobacco Supplies | E59: Meat Supplies | F59: Bakery Supplies | G59: B.In store Supplies | H59: Deli Supplies | I59: Produce Supplies | K59: Dairy Supplies | L59: Pharmacy Supplies
A60: =A6 -> 82849874 | B60: =B6 -> OLD DUTCH FOODS
A61: =A7 -> 82849875 | B61: =B7 -> OLD DUTCH FOODS
A62: =A8 -> 95463140 | B62: =B8 -> FRITO LAY CANADA RETAIL
A63: =A9 | B63: =B9
A64: =A10 | B64: =B10
A65: =A11 | B65: =B11
A66: =A12 | B66: =B12
A67: =A13 | B67: =B13
A68: =A14 | B68: =B14
A69: =A15 | B69: =B15
A70: =A16 | B70: =B16
A71: =A17 | B71: =B17
... A109: =A55 | B109: =B55
A110: Department Totals | C110: =SUM(C60:C109) -> 0 | D110: =SUM(D60:D109) -> 0 | E110: =SUM(E60:E109) -> 0 | F110: =SUM(F60:F109) -> 0 | G110: =SUM(G60:G109) -> 0 | H110: =SUM(H60:H109) -> 0 | I110: =SUM(I60:I109) -> 0 | J110: =SUM(J60:J109) -> 0 | K110: =SUM(K60:K109) -> 0 | L110: 0

Sheet Saturday WK3 (21)
B1: Freight | C1: Grocery | E1: Meat | F1: Bakery | G1: Bake off | H1: Deli | I1: Produce | J1: Produce Shrink | K1: Dairy | L1: Pharmacy | M1: Receiving Totals | N1: Total
B2: Name: | C2: ='Sunday WK1 (1)'!C2 -> 0.478 | E2: ='Sunday WK1 (1)'!E2 -> 0.099 | F2: 0 | G2: 0 | H2: 0 | I2: ='Sunday WK1 (1)'!I2 -> 0.159 | J2: ='Sunday WK1 (1)'!J2 -> 0.122 | K2: ='Sunday WK1 (1)'!$K$2 -> 0.142 | L2: 0 | N2: =SUM(C2:M2) -> 1
B3: SHANNON | C3: =C2*$N$3 -> 0 | E3: =E2*$N$3 -> 0 | F3: =F2*$N$3 -> 0 | G3: =G2*$N$3 -> 0 | H3: =H2*$N$3 -> 0 | I3: =I2*$N$3 -> 0 | J3: =J2*$N$3 -> 0 | K3: =K2*$N$3 -> 0 | L3: =L2*$N$3 -> 0
A4: Receiving Date: | B4: ='Friday WK3 (20)'!$B$4+1 -> 46214
A5: Invoice Number | B5: Supplier Name | C5: Grocery Purchases | D5: Tobacco Purchases | E5: Meat Purchases | F5: Bakery Purchases | G5: Bakery In Store | H5: Deli Purchases | I5: Produce Purchases | J5: Produce Shrink | K5: Dairy Purchases | L5: Pharmacy Purchases | M5: GST | N5: Total Invoice**
A6: 126800 | B6: ITALIAN BAKERY | C6: =N6-D6-E6-F6-G6-H6-I6-J6-K6-L6-M6-D60-E60-F60-G60-H60-I60-J60-K60-L60-C60 -> 237.21 | N6: 237.21
A7: 6018 | B7: THE GROCERY PEOPLE | C7: =N7-D7-E7-F7-G7-H7-I7-J7-K7-L7-M7-D61-E61-F61-G61-H61-I61-J61-K61-L61-C61 -> -1540 | N7: -1540 | O7: STR TRSF - LLOYMINSTER C & C
C8: =N8-D8-E8-F8-G8-H8-I8-J8-K8-L8-M8-D62-E62-F62-G62-H62-I62-J62-K62-L62-C62 -> 0
C9: =N9-D9-E9-F9-G9-H9-I9-J9-K9-L9-M9-D63-E63-F63-G63-H63-I63-J63-K63-L63-C63 -> 0
C10: =N10-D10-E10-F10-G10-H10-I10-J10-K10-L10-M10-D64-E64-F64-G64-H64-I64-J64-K64-L64-C64 -> 0
C11: =N11-D11-E11-F11-G11-H11-I11-J11-K11-L11-M11-D65-E65-F65-G65-H65-I65-J65-K65-L65-C65 -> 0
C12: =N12-D12-E12-F12-G12-H12-I12-J12-K12-L12-M12-D66-E66-F66-G66-H66-I66-J66-K66-L66-C66 -> 0
C13: =N13-D13-E13-F13-G13-H13-I13-J13-K13-L13-M13-D67-E67-F67-G67-H67-I67-J67-K67-L67-C67 -> 0
C14: =N14-D14-E14-F14-G14-H14-I14-J14-K14-L14-M14-D68-E68-F68-G68-H68-I68-J68-K68-L68-C68 -> 0
C15: =N15-D15-E15-F15-G15-H15-I15-J15-K15-L15-M15-D69-E69-F69-G69-H69-I69-J69-K69-L69-C69 -> 0
C16: =N16-D16-E16-F16-G16-H16-I16-J16-K16-L16-M16-D70-E70-F70-G70-H70-I70-J70-K70-L70-C70 -> 0
C17: =N17-D17-E17-F17-G17-H17-I17-J17-K17-L17-M17-D71-E71-F71-G71-H71-I71-J71-K71-L71-C71 -> 0
C18: =N18-D18-E18-F18-G18-H18-I18-J18-K18-L18-M18-D72-E72-F72-G72-H72-I72-J72-K72-L72-C72 -> 0
C19: =N19-D19-E19-F19-G19-H19-I19-J19-K19-L19-M19-D73-E73-F73-G73-H73-I73-J73-K73-L73-C73 -> 0
... C55: =N55-D55-E55-F55-G55-H55-I55-J55-K55-L55-M55-D109-E109-F109-G109-H109-I109-J109-K109-L109-C109 -> 0
A56: Freight | B56: THE GROCERY PEOPLE | C56: =C3 -> 0 | E56: =E3 -> 0 | F56: =F3 -> 0 | G56: =G3 -> 0 | H56: =H3 -> 0 | I56: =I3 -> 0 | J56: =J3 -> 0 | K56: =K3 -> 0 | L56: =L3 -> 0 | N56: =SUM(C56:M56)+SUM(C118:J118) -> 0
A57: Department Totals | C57: =SUM(C6:C56) -> -1302.79 | D57: =SUM(D6:D56) -> 0 | E57: =SUM(E6:E56) -> 0 | F57: =SUM(F6:F56) -> 0 | G57: =SUM(G6:G56) -> 0 | H57: =SUM(H6:H56) -> 0 | I57: =SUM(I6:I56) -> 0 | J57: =SUM(J6:J56) -> 0 | ... N57: =SUM(N6:N56) -> -1302.79
N58: =IF(SUM(N6:N56)=SUM(C57:M57)+SUM(D110:L110),"","Sum error")
A59: Invoice Number | B59: Supplier Name | C59: Grocery Supplies | D59: Tobacco Supplies | E59: Meat Supplies | F59: Bakery Supplies | G59: B.In store Supplies | H59: Deli Supplies | I59: Produce Supplies | K59: Dairy Supplies | L59: Pharmacy Supplies
A60: =A6 -> 126800 | B60: =B6 -> ITALIAN BAKERY | O60: test
A61: =A7 -> 6018 | B61: =B7 -> THE GROCERY PEOPLE | O61: points
A62: =A8 | B62: =B8 | O62: trays
A63: =A9 | B63: =B9
A64: =A10 | B64: =B10
A65: =A11 | B65: =B11
A66: =A12 | B66: =B12
A67: =A13 | B67: =B13
A68: =A14 | B68: =B14
A69: =A15 | B69: =B15
A70: =A16 | B70: =B16
A71: =A17 | B71: =B17
A72: =A18 | B72: =B18
A73: =A19 | B73: =B19
A74: =A20 | B74: =B20
... A109: =A55 | B109: =B55
A110: Department Totals | C110: =SUM(C60:C109) -> 0 | D110: =SUM(D60:D109) -> 0 | E110: =SUM(E60:E109) -> 0 | F110: =SUM(F60:F109) -> 0 | G110: =SUM(G60:G109) -> 0 | H110: =SUM(H60:H109) -> 0 | I110: =SUM(I60:I109) -> 0 | J110: =SUM(J60:J109) -> 0 | K110: =SUM(K60:K109) -> 0 | L110: 0

Sheet Sunday WK4 (22)
B1: Freight | C1: Grocery | E1: Meat | F1: Bakery | G1: Bake off | H1: Deli | I1: Produce | J1: Produce Shrink | K1: Dairy | L1: Pharmacy | M1: Receiving Totals | N1: Total
B2: Name: | C2: ='Sunday WK1 (1)'!C2 -> 0.478 | E2: ='Sunday WK1 (1)'!E2 -> 0.099 | F2: 0 | G2: 0 | H2: 0 | I2: ='Sunday WK1 (1)'!I2 -> 0.159 | J2: ='Sunday WK1 (1)'!J2 -> 0.122 | K2: ='Sunday WK1 (1)'!$K$2 -> 0.142 | L2: 0 | N2: =SUM(C2:M2) -> 1
B3: SHANNON | C3: =C2*$N$3 -> 159.1023 | E3: =E2*$N$3 -> 32.95215 | F3: =F2*$N$3 -> 0 | G3: =G2*$N$3 -> 0 | H3: =H2*$N$3 -> 0 | I3: =I2*$N$3 -> 52.92315 | J3: =J2*$N$3 -> 40.6077 | K3: =K2*$N$3 -> 47.2647 | L3: =L2*$N$3 -> 0 | N3: 332.85
A4: Receiving Date: | B4: ='Saturday WK3 (21)'!B4+1 -> 46215
A5: Invoice Number | B5: Supplier Name | C5: Grocery Purchases | D5: Tobacco Purchases | E5: Meat Purchases | F5: Bakery Purchases | G5: Bakery In Store | H5: Deli Purchases | I5: Produce Purchases | J5: Produce Shrink | K5: Dairy Purchases | L5: Pharmacy Purchases | M5: GST | N5: Total Invoice**
A6: SO186688 | B6: STAR PRODUCE | C6: =N6-D6-E6-F6-G6-H6-I6-J6-K6-L6-M6-D60-E60-F60-G60-H60-I60-J60-K60-L60-C60 -> -3.5527137e-14 | I6: 578.2 | M6: 18.29 | N6: 596.49
A7: 4003799869 | B7: SAPUTO DAIRY PRODUCTS | C7: =N7-D7-E7-F7-G7-H7-I7-J7-K7-L7-M7-D61-E61-F61-G61-H61-I61-J61-K61-L61-C61 -> 0 | K7: 81.29 | N7: 81.29
A8: 4003799870 | B8: SAPUTO DAIRY PRODUCTS | C8: =N8-D8-E8-F8-G8-H8-I8-J8-K8-L8-M8-D62-E62-F62-G62-H62-I62-J62-K62-L62-C62 -> 3.6415315e-14 | K8: 3368.81 | M8: 0.71 | N8: 3369.52
A9: 965136 | B9: HARVEST MEATS | C9: =N9-D9-E9-F9-G9-H9-I9-J9-K9-L9-M9-D63-E63-F63-G63-H63-I63-J63-K63-L63-C63 -> 0 | E9: 80.3 | N9: 80.3
A10: 965063 | B10: HARVEST MEATS | C10: =N10-D10-E10-F10-G10-H10-I10-J10-K10-L10-M10-D64-E64-F64-G64-H64-I64-J64-K64-L64-C64 -> 0 | E10: 1108.66 | N10: 1108.66
A11: 3284739 | B11: LILYDALE SOFINA FOODS | C11: =N11-D11-E11-F11-G11-H11-I11-J11-K11-L11-M11-D65-E65-F65-G65-H65-I65-J65-K65-L65-C65 -> 0 | E11: 23.51 | N11: 23.51
A12: 3285602 | B12: LILYDALE SOFINA FOODS | C12: =N12-D12-E12-F12-G12-H12-I12-J12-K12-L12-M12-D66-E66-F66-G66-H66-I66-J66-K66-L66-C66 -> 0 | E12: 23.51 | N12: 23.51
A13: 3285581 | B13: LILYDALE SOFINA FOODS | C13: =N13-D13-E13-F13-G13-H13-I13-J13-K13-L13-M13-D67-E67-F67-G67-H67-I67-J67-K67-L67-C67 -> 0 | E13: 172.31 | N13: 172.31
A14: 5648748 | B14: THE GROCERY PEOPLE | C14: =N14-D14-E14-F14-G14-H14-I14-J14-K14-L14-M14-D68-E68-F68-G68-H68-I68-J68-K68-L68-C68 -> 9.98 | N14: 9.98
A15: 5651283 | B15: THE GROCERY PEOPLE | C15: =N15-D15-E15-F15-G15-H15-I15-J15-K15-L15-M15-D69-E69-F69-G69-H69-I69-J69-K69-L69-C69 -> 291.29 | E15: 2524.6 | N15: 2815.89
A16: 5651284 | B16: THE GROCERY PEOPLE | C16: =N16-D16-E16-F16-G16-H16-I16-J16-K16-L16-M16-D70-E70-F70-G70-H70-I70-J70-K70-L70-C70 -> 0 | N16: 308.3 | O16: MEAT SUPPLIES - FOAM TRAYS
A17: 5651372 | B17: THE GROCERY PEOPLE | C17: =N17-D17-E17-F17-G17-H17-I17-J17-K17-L17-M17-D71-E71-F71-G71-H71-I71-J71-K71-L71-C71 -> 1472.6 | N17: 1472.6
A18: 5651617 | B18: THE GROCERY PEOPLE | C18: =N18-D18-E18-F18-G18-H18-I18-J18-K18-L18-M18-D72-E72-F72-G72-H72-I72-J72-K72-L72-C72 -> 5100.53 | N18: 5100.53
A19: 5651803 | B19: THE GROCERY PEOPLE | C19: =N19-D19-E19-F19-G19-H19-I19-J19-K19-L19-M19-D73-E73-F73-G73-H73-I73-J73-K73-L73-C73 -> 191.6 | N19: 191.6
A20: 5651811 | B20: THE GROCERY PEOPLE | C20: =N20-D20-E20-F20-G20-H20-I20-J20-K20-L20-M20-D74-E74-F74-G74-H74-I74-J74-K74-L74-C74 -> 0 | K20: 411.39 | N20: 411.39
A21: 5652137 | B21: THE GROCERY PEOPLE | C21: =N21-D21-E21-F21-G21-H21-I21-J21-K21-L21-M21-D75-E75-F75-G75-H75-I75-J75-K75-L75-C75 -> 4114.4 | N21: 4114.4
A22: 5652139 | B22: THE GROCERY PEOPLE | C22: =N22-D22-E22-F22-G22-H22-I22-J22-K22-L22-M22-D76-E76-F76-G76-H76-I76-J76-K76-L76-C76 -> 5646.79 | N22: 5646.79
A23: 5652141 | B23: THE GROCERY PEOPLE | C23: =N23-D23-E23-F23-G23-H23-I23-J23-K23-L23-M23-D77-E77-F77-G77-H77-I77-J77-K77-L77-C77 -> 98.7 | K23: 3048.91 | N23: 3147.61
A24: 5652142 | B24: THE GROCERY PEOPLE | C24: =N24-D24-E24-F24-G24-H24-I24-J24-K24-L24-M24-D78-E78-F78-G78-H78-I78-J78-K78-L78-C78 -> 0 | K24: 116.87 | N24: 116.87
A25: 8251323 | B25: THE GROCERY PEOPLE | C25: =N25-D25-E25-F25-G25-H25-I25-J25-K25-L25-M25-D79-E79-F79-G79-H79-I79-J79-K79-L79-C79 -> 0 | E25: 835.03 | N25: 835.03
A26: 8251759 | B26: THE GROCERY PEOPLE | C26: =N26-D26-E26-F26-G26-H26-I26-J26-K26-L26-M26-D80-E80-F80-G80-H80-I80-J80-K80-L80-C80 -> 0 | E26: 1636.37 | N26: 1636.37
A27: 8251887 | B27: THE GROCERY PEOPLE | C27: =N27-D27-E27-F27-G27-H27-I27-J27-K27-L27-M27-D81-E81-F81-G81-H81-I81-J81-K81-L81-C81 -> 0 | E27: 94.45 | N27: 94.45
A28: 8251908 | B28: THE GROCERY PEOPLE | C28: =N28-D28-E28-F28-G28-H28-I28-J28-K28-L28-M28-D82-E82-F82-G82-H82-I82-J82-K82-L82-C82 -> 0 | E28: 66.35 | N28: 66.35
A29: 6697433 | B29: THE GROCERY PEOPLE | C29: =N29-D29-E29-F29-G29-H29-I29-J29-K29-L29-M29-D83-E83-F83-G83-H83-I83-J83-K83-L83-C83 -> 0 | E29: 4573.04 | N29: 4573.04
A30: 5650082 | B30: THE GROCERY PEOPLE | C30: =N30-D30-E30-F30-G30-H30-I30-J30-K30-L30-M30-D84-E84-F84-G84-H84-I84-J84-K84-L84-C84 -> 488.22 | N30: 488.22
A31: 5648677 | B31: THE GROCERY PEOPLE | C31: =N31-D31-E31-F31-G31-H31-I31-J31-K31-L31-M31-D85-E85-F85-G85-H85-I85-J85-K85-L85-C85 -> 108.68 | N31: 108.68
A32: 5649082 | B32: THE GROCERY PEOPLE | C32: =N32-D32-E32-F32-G32-H32-I32-J32-K32-L32-M32-D86-E86-F86-G86-H86-I86-J86-K86-L86-C86 -> 238.62 | N32: 238.62
A33: 5650191 | B33: THE GROCERY PEOPLE | C33: =N33-D33-E33-F33-G33-H33-I33-J33-K33-L33-M33-D87-E87-F87-G87-H87-I87-J87-K87-L87-C87 -> 136.2 | N33: 136.2
A34: 5650718 | B34: THE GROCERY PEOPLE | C34: =N34-D34-E34-F34-G34-H34-I34-J34-K34-L34-M34-D88-E88-F88-G88-H88-I88-J88-K88-L88-C88 -> 321.1 | N34: 321.1
A35: 5651024 | B35: THE GROCERY PEOPLE | C35: =N35-D35-E35-F35-G35-H35-I35-J35-K35-L35-M35-D89-E89-F89-G89-H89-I89-J89-K89-L89-C89 -> 0 | K35: 56.42 | N35: 56.42
A36: 5651025 | B36: THE GROCERY PEOPLE | C36: =N36-D36-E36-F36-G36-H36-I36-J36-K36-L36-M36-D90-E90-F90-G90-H90-I90-J90-K90-L90-C90 -> 338.64 | N36: 338.64
A37: 5651026 | B37: THE GROCERY PEOPLE | C37: =N37-D37-E37-F37-G37-H37-I37-J37-K37-L37-M37-D91-E91-F91-G91-H91-I91-J91-K91-L91-C91 -> 250.38 | N37: 250.38
A38: 5651027 | B38: THE GROCERY PEOPLE | C38: =N38-D38-E38-F38-G38-H38-I38-J38-K38-L38-M38-D92-E92-F92-G92-H92-I92-J92-K92-L92-C92 -> 166.92 | N38: 166.92
A39: 5651548 | B39: THE GROCERY PEOPLE | C39: =N39-D39-E39-F39-G39-H39-I39-J39-K39-L39-M39-D93-E93-F93-G93-H93-I93-J93-K93-L93-C93 -> 47.64 | N39: 47.64
A40: 5651832 | B40: THE GROCERY PEOPLE | C40: =N40-D40-E40-F40-G40-H40-I40-J40-K40-L40-M40-D94-E94-F94-G94-H94-I94-J94-K94-L94-C94 -> 432.32 | N40: 432.32
A41: 5651833 | B41: THE GROCERY PEOPLE | C41: =N41-D41-E41-F41-G41-H41-I41-J41-K41-L41-M41-D95-E95-F95-G95-H95-I95-J95-K95-L95-C95 -> 97.64 | N41: 97.64
A42: 5651952 | B42: THE GROCERY PEOPLE | C42: =N42-D42-E42-F42-G42-H42-I42-J42-K42-L42-M42-D96-E96-F96-G96-H96-I96-J96-K96-L96-C96 -> 1442 | N42: 1442
A43: 5652050 | B43: THE GROCERY PEOPLE | C43: =N43-D43-E43-F43-G43-H43-I43-J43-K43-L43-M43-D97-E97-F97-G97-H97-I97-J97-K97-L97-C97 -> 175.35 | N43: 175.35
A44: 5652051 | B44: THE GROCERY PEOPLE | C44: =N44-D44-E44-F44-G44-H44-I44-J44-K44-L44-M44-D98-E98-F98-G98-H98-I98-J98-K98-L98-C98 -> 250.62 | N44: 250.62
A45: 5647665 | B45: THE GROCERY PEOPLE | C45: =N45-D45-E45-F45-G45-H45-I45-J45-K45-L45-M45-D99-E99-F99-G99-H99-I99-J99-K99-L99-C99 -> 0 | I45: 242.69 | N45: 242.69
A46: 5652283 | B46: THE GROCERY PEOPLE | C46: =N46-D46-E46-F46-G46-H46-I46-J46-K46-L46-M46-D100-E100-F100-G100-H100-I100-J100-K100-L100-C100 -> 0 | I46: 8059.69 | N46: 8059.69
A47: 5652376 | B47: THE GROCERY PEOPLE | C47: =N47-D47-E47-F47-G47-H47-I47-J47-K47-L47-M47-D101-E101-F101-G101-H101-I101-J101-K101-L101-C101 -> 0 | I47: 193.8 | N47: 193.8
A48: 5652529 | B48: THE GROCERY PEOPLE | C48: =N48-D48-E48-F48-G48-H48-I48-J48-K48-L48-M48-D102-E102-F102-G102-H102-I102-J102-K102-L102-C102 -> 0 | I48: 260.2 | N48: 260.2
A49: 5652530 | B49: THE GROCERY PEOPLE | C49: =N49-D49-E49-F49-G49-H49-I49-J49-K49-L49-M49-D103-E103-F103-G103-H103-I103-J103-K103-L103-C103 -> 0 | I49: 44.95 | N49: 44.95
A50: 6692868 | B50: THE GROCERY PEOPLE | C50: =N50-D50-E50-F50-G50-H50-I50-J50-K50-L50-M50-D104-E104-F104-G104-H104-I104-J104-K104-L104-C104 -> 28.33 | N50: 28.33
A51: 6693625 | B51: THE GROCERY PEOPLE | C51: =N51-D51-E51-F51-G51-H51-I51-J51-K51-L51-M51-D105-E105-F105-G105-H105-I105-J105-K105-L105-C105 -> 1173.65 | E51: 41.99 | N51: 1215.64
A52: 6694535 | B52: THE GROCERY PEOPLE | C52: =N52-D52-E52-F52-G52-H52-I52-J52-K52-L52-M52-D106-E106-F106-G106-H106-I106-J106-K106-L106-C106 -> 0 | E52: 141.92 | N52: 141.92
A53: 6695360 | B53: THE GROCERY PEOPLE | C53: =N53-D53-E53-F53-G53-H53-I53-J53-K53-L53-M53-D107-E107-F107-G107-H107-I107-J107-K107-L107-C107 -> 0 | K53: 78.96 | N53: 78.96
A54: 6694333 | B54: THE GROCERY PEOPLE | C54: =N54-D54-E54-F54-G54-H54-I54-J54-K54-L54-M54-D108-E108-F108-G108-H108-I108-J108-K108-L108-C108 -> 0 | E54: 77.8 | K54: 158.49 | N54: 236.29
C55: =N55-D55-E55-F55-G55-H55-I55-J55-K55-L55-M55-D109-E109-F109-G109-H109-I109-J109-K109-L109-C109 -> 0
A56: Freight | B56: THE GROCERY PEOPLE | C56: =C3 -> 159.1023 | E56: =E3 -> 32.95215 | F56: =F3 -> 0 | G56: =G3 -> 0 | H56: =H3 -> 0 | I56: =I3 -> 52.92315 | J56: =J3 -> 40.6077 | K56: =K3 -> 47.2647 | L56: =L3 -> 0 | N56: =SUM(C56:M56)+SUM(C118:J118) -> 332.85 | O56: BM#8542794, BOL REF#4866681,4866679,4866680,4866682,4866678,
A57: Department Totals | C57: =SUM(C6:C56) -> 22781.302 | D57: =SUM(D6:D56) -> 0 | E57: =SUM(E6:E56) -> 11432.792 | F57: =SUM(F6:F56) -> 0 | G57: =SUM(G6:G56) -> 0 | H57: =SUM(H6:H56) -> 0 | I57: =SUM(I6:I56) -> 9432.4532 | J57: =SUM(J6:J56) -> 40.6077 | ... N57: =SUM(N6:N56) -> 51382.86
N58: =IF(SUM(N6:N56)=SUM(C57:M57)+SUM(C110:L110),"","Sum error")
A59: Invoice Number | B59: Supplier Name | C59: Grocery Supplies | D59: Tobacco Supplies | E59: Meat Supplies | F59: Bakery Supplies | G59: B.In store Supplies | H59: Deli Supplies | I59: Produce Supplies | K59: Dairy Supplies | L59: Pharmacy Supplies
A60: =A6 -> SO186688 | B60: =B6 -> STAR PRODUCE
A61: =A7 -> 4003799869 | B61: =B7 -> SAPUTO DAIRY PRODUCTS
A62: =A8 -> 4003799870 | B62: =B8 -> SAPUTO DAIRY PRODUCTS
A63: =A9 -> 965136 | B63: =B9 -> HARVEST MEATS
A64: =A10 -> 965063 | B64: =B10 -> HARVEST MEATS
A65: =A11 -> 3284739 | B65: =B11 -> LILYDALE SOFINA FOODS
A66: =A12 -> 3285602 | B66: =B12 -> LILYDALE SOFINA FOODS
A67: =A13 -> 3285581 | B67: =B13 -> LILYDALE SOFINA FOODS
A68: =A14 -> 5648748 | B68: =B14 -> THE GROCERY PEOPLE
A69: =A15 -> 5651283 | B69: =B15 -> THE GROCERY PEOPLE
A70: =A16 -> 5651284 | B70: =B16 -> THE GROCERY PEOPLE | E70: 308.3 | M70: MEAT SUPPLIES - FOAM TRAYS
A71: =A17 -> 5651372 | B71: =B17 -> THE GROCERY PEOPLE
A72: =A18 -> 5651617 | B72: =B18 -> THE GROCERY PEOPLE
A73: =A19 -> 5651803 | B73: =B19 -> THE GROCERY PEOPLE
A74: =A20 -> 5651811 | B74: =B20 -> THE GROCERY PEOPLE
A75: =A21 -> 5652137 | B75: =B21 -> THE GROCERY PEOPLE
A76: =A22 -> 5652139 | B76: =B22 -> THE GROCERY PEOPLE
A77: =A23 -> 5652141 | B77: =B23 -> THE GROCERY PEOPLE
A78: =A24 -> 5652142 | B78: =B24 -> THE GROCERY PEOPLE
A79: =A25 -> 8251323 | B79: =B25 -> THE GROCERY PEOPLE
A80: =A26 -> 8251759 | B80: =B26 -> THE GROCERY PEOPLE
A81: =A27 -> 8251887 | B81: =B27 -> THE GROCERY PEOPLE
A82: =A28 -> 8251908 | B82: =B28 -> THE GROCERY PEOPLE
... A109: =A55 | B109: =B55
A110: Department Totals | C110: =SUM(C60:C109) -> 0 | D110: =SUM(D60:D109) -> 0 | E110: =SUM(E60:E109) -> 308.3 | F110: =SUM(F60:F109) -> 0 | G110: =SUM(G60:G109) -> 0 | H110: =SUM(H60:H109) -> 0 | I110: =SUM(I60:I109) -> 0 | J110: =SUM(J60:J109) -> 0 | K110: =SUM(K60:K109) -> 0 | L110: 0

Sheet Monday WK4 (23)
B1: Freight | C1: Grocery | E1: Meat | F1: Bakery | G1: Bake off | H1: Deli | I1: Produce | J1: Produce Shrink | K1: Dairy | L1: Pharmacy | M1: Receiving Totals | N1: Total
B2: Name: | C2: ='Sunday WK1 (1)'!C2 -> 0.478 | E2: ='Sunday WK1 (1)'!E2 -> 0.099 | F2: 0 | G2: 0 | H2: 0 | I2: ='Sunday WK1 (1)'!I2 -> 0.159 | J2: ='Sunday WK1 (1)'!J2 -> 0.122 | K2: ='Sunday WK1 (1)'!$K$2 -> 0.142 | L2: 0 | N2: =SUM(C2:M2) -> 1
B3: SHANNON | C3: =C2*$N$3 -> 0 | E3: =E2*$N$3 -> 0 | F3: =F2*$N$3 -> 0 | G3: =G2*$N$3 -> 0 | H3: =H2*$N$3 -> 0 | I3: =I2*$N$3 -> 0 | J3: =J2*$N$3 -> 0 | K3: =K2*$N$3 -> 0 | L3: =L2*$N$3 -> 0
A4: Receiving Date: | B4: ='Sunday WK4 (22)'!$B$4+1 -> 46216
A5: Invoice Number | B5: Supplier Name | C5: Grocery Purchases | D5: Tobacco Purchases | E5: Meat Purchases | F5: Bakery Purchases | G5: Bakery In Store | H5: Deli Purchases | I5: Produce Purchases | J5: Produce Shrink | K5: Dairy Purchases | L5: Pharmacy Purchases | M5: GST | N5: Total Invoice**
A6: 4000259074 | B6: SAPUTO DAIRY PRODUCTS | C6: =N6-D6-E6-F6-G6-H6-I6-J6-K6-L6-M6-D60-E60-F60-G60-H60-I60-J60-K60-L60-C60 -> 0 | K6: -36.42 | N6: -36.42
A7: 3281619401 | B7: ARCTIC GLACIER | C7: =N7-D7-E7-F7-G7-H7-I7-J7-K7-L7-M7-D61-E61-F61-G61-H61-I61-J61-K61-L61-C61 -> 1753.92 | N7: 1753.92
A8: 54468907 | B8: PEPSICO | C8: =N8-D8-E8-F8-G8-H8-I8-J8-K8-L8-M8-D62-E62-F62-G62-H62-I62-J62-K62-L62-C62 -> 8941.8 | M8: 302.29 | N8: 9244.09
A9: 82849885 | B9: OLD DUTCH FOODS | C9: =N9-D9-E9-F9-G9-H9-I9-J9-K9-L9-M9-D63-E63-F63-G63-H63-I63-J63-K63-L63-C63 -> 751.86 | M9: 26.25 | N9: 778.11
A10: 226650719417 | B10: CANADA BREAD COMPANY | C10: =N10-D10-E10-F10-G10-H10-I10-J10-K10-L10-M10-D64-E64-F64-G64-H64-I64-J64-K64-L64-C64 -> 923.05 | N10: 923.05
A11: 226650719418 | B11: CANADA BREAD COMPANY | C11: =N11-D11-E11-F11-G11-H11-I11-J11-K11-L11-M11-D65-E65-F65-G65-H65-I65-J65-K65-L65-C65 -> -65 | M11: -1.11 | N11: -66.11
A12: 53268109003 | B12: COCA COLA CANADA BOTTLING | C12: =N12-D12-E12-F12-G12-H12-I12-J12-K12-L12-M12-D66-E66-F66-G66-H66-I66-J66-K66-L66-C66 -> 9585.06 | M12: 407.06 | N12: 9992.12
A13: INV26-04868 | B13: CAPITAL FINE MEATS | C13: =N13-D13-E13-F13-G13-H13-I13-J13-K13-L13-M13-D67-E67-F67-G67-H67-I67-J67-K67-L67-C67 -> 0 | E13: 520.97 | N13: 520.97
A14: 126824 | B14: ITALIAN BAKERY | C14: =N14-D14-E14-F14-G14-H14-I14-J14-K14-L14-M14-D68-E68-F68-G68-H68-I68-J68-K68-L68-C68 -> 344.46 | N14: 344.46
C15: =N15-D15-E15-F15-G15-H15-I15-J15-K15-L15-M15-D69-E69-F69-G69-H69-I69-J69-K69-L69-C69 -> 0
C16: =N16-D16-E16-F16-G16-H16-I16-J16-K16-L16-M16-D70-E70-F70-G70-H70-I70-J70-K70-L70-C70 -> 0
C17: =N17-D17-E17-F17-G17-H17-I17-J17-K17-L17-M17-D71-E71-F71-G71-H71-I71-J71-K71-L71-C71 -> 0
C18: =N18-D18-E18-F18-G18-H18-I18-J18-K18-L18-M18-D72-E72-F72-G72-H72-I72-J72-K72-L72-C72 -> 0
C19: =N19-D19-E19-F19-G19-H19-I19-J19-K19-L19-M19-D73-E73-F73-G73-H73-I73-J73-K73-L73-C73 -> 0
C20: =N20-D20-E20-F20-G20-H20-I20-J20-K20-L20-M20-D74-E74-F74-G74-H74-I74-J74-K74-L74-C74 -> 0
C21: =N21-D21-E21-F21-G21-H21-I21-J21-K21-L21-M21-D75-E75-F75-G75-H75-I75-J75-K75-L75-C75 -> 0
C22: =N22-D22-E22-F22-G22-H22-I22-J22-K22-L22-M22-D76-E76-F76-G76-H76-I76-J76-K76-L76-C76 -> 0
C23: =N23-D23-E23-F23-G23-H23-I23-J23-K23-L23-M23-D77-E77-F77-G77-H77-I77-J77-K77-L77-C77 -> 0
C24: =N24-D24-E24-F24-G24-H24-I24-J24-K24-L24-M24-D78-E78-F78-G78-H78-I78-J78-K78-L78-C78 -> 0
C25: =N25-D25-E25-F25-G25-H25-I25-J25-K25-L25-M25-D79-E79-F79-G79-H79-I79-J79-K79-L79-C79 -> 0
C26: =N26-D26-E26-F26-G26-H26-I26-J26-K26-L26-M26-D80-E80-F80-G80-H80-I80-J80-K80-L80-C80 -> 0
... C55: =N55-D55-E55-F55-G55-H55-I55-J55-K55-L55-M55-D109-E109-F109-G109-H109-I109-J109-K109-L109-C109 -> 0
A56: Freight | B56: THE GROCERY PEOPLE | C56: =C3 -> 0 | E56: =E3 -> 0 | F56: =F3 -> 0 | G56: =G3 -> 0 | H56: =H3 -> 0 | I56: =I3 -> 0 | J56: =J3 -> 0 | K56: =K3 -> 0 | L56: =L3 -> 0 | N56: =SUM(C56:M56)+SUM(C118:J118) -> 0
A57: Department Totals | C57: =SUM(C6:C56) -> 22235.15 | D57: =SUM(D6:D56) -> 0 | E57: =SUM(E6:E56) -> 520.97 | F57: =SUM(F6:F56) -> 0 | G57: =SUM(G6:G56) -> 0 | H57: =SUM(H6:H56) -> 0 | I57: =SUM(I6:I56) -> 0 | J57: =SUM(J6:J56) -> 0 | ... N57: =SUM(N6:N56) -> 23454.19
N58: =IF(SUM(N6:N56)=SUM(C57:M57)+SUM(D110:L110),"","Sum error")
A59: Invoice Number | B59: Supplier Name | C59: Grocery Supplies | D59: Tobacco Supplies | E59: Meat Supplies | F59: Bakery Supplies | G59: B.In store Supplies | H59: Deli Supplies | I59: Produce Supplies | K59: Dairy Supplies | L59: Pharmacy Supplies
A60: =A6 -> 4000259074 | B60: =B6 -> SAPUTO DAIRY PRODUCTS
A61: =A7 -> 3281619401 | B61: =B7 -> ARCTIC GLACIER
B62: =B8 -> PEPSICO
B63: =B9 -> OLD DUTCH FOODS
A64: =A10 -> 226650719417 | B64: =B10 -> CANADA BREAD COMPANY
A65: =A11 -> 226650719418 | B65: =B11 -> CANADA BREAD COMPANY
A66: =A12 -> 53268109003 | B66: =B12 -> COCA COLA CANADA BOTTLING
A67: =A13 -> INV26-04868 | B67: =B13 -> CAPITAL FINE MEATS
A68: =A14 -> 126824 | B68: =B14 -> ITALIAN BAKERY
A69: =A15 | B69: =B15
A70: =A16 | B70: =B16
A71: =A17 | B71: =B17
A72: =A18 | B72: =B18
A73: =A19 | B73: =B19
A74: =A20 | B74: =B20
A75: =A21 | B75: =B21
... A109: =A55 | B109: =B55
A110: Department Totals | C110: =SUM(C60:C109) -> 0 | D110: =SUM(D60:D109) -> 0 | E110: =SUM(E60:E109) -> 0 | F110: =SUM(F60:F109) -> 0 | G110: =SUM(G60:G109) -> 0 | H110: =SUM(H60:H109) -> 0 | I110: =SUM(I60:I109) -> 0 | J110: =SUM(J60:J109) -> 0 | K110: =SUM(K60:K109) -> 0 | L110: 0

Sheet Tuesday WK4 (24)
B1: Freight | C1: Grocery | E1: Meat | F1: Bakery | G1: Bake off | H1: Deli | I1: Produce | J1: Produce Shrink | K1: Dairy | L1: Pharmacy | M1: Receiving Totals | N1: Total
B2: Name: | C2: ='Sunday WK1 (1)'!C2 -> 0.478 | E2: ='Sunday WK1 (1)'!E2 -> 0.099 | F2: 0 | G2: 0 | H2: 0 | I2: ='Sunday WK1 (1)'!I2 -> 0.159 | J2: ='Sunday WK1 (1)'!J2 -> 0.122 | K2: ='Sunday WK1 (1)'!$K$2 -> 0.142 | L2: 0 | N2: =SUM(C2:M2) -> 1
B3: SHANNON | C3: =C2*$N$3 -> 129.06478 | E3: =E2*$N$3 -> 26.73099 | F3: =F2*$N$3 -> 0 | G3: =G2*$N$3 -> 0 | H3: =H2*$N$3 -> 0 | I3: =I2*$N$3 -> 42.93159 | J3: =J2*$N$3 -> 32.94122 | K3: =K2*$N$3 -> 38.34142 | L3: =L2*$N$3 -> 0 | N3: 270.01
A4: Receiving Date: | B4: ='Monday WK4 (23)'!$B$4+1 -> 46217
A5: Invoice Number | B5: Supplier Name | C5: Grocery Purchases | D5: Tobacco Purchases | E5: Meat Purchases | F5: Bakery Purchases | G5: Bakery In Store | H5: Deli Purchases | I5: Produce Purchases | J5: Produce Shrink | K5: Dairy Purchases | L5: Pharmacy Purchases | M5: GST | N5: Total Invoice**
A6: 4003807742 | B6: SAPUTO DAIRY PRODUCTS | C6: =N6-D6-E6-F6-G6-H6-I6-J6-K6-L6-M6-D60-E60-F60-G60-H60-I60-J60-K60-L60-C60 -> -1.1823875e-13 | K6: 1924.39 | M6: 0.13 | N6: 1924.52
A7: 5653634 | B7: THE GROCERY PEOPLE | C7: =N7-D7-E7-F7-G7-H7-I7-J7-K7-L7-M7-D61-E61-F61-G61-H61-I61-J61-K61-L61-C61 -> 2325.37 | N7: 2325.37
A8: 5653683 | B8: THE GROCERY PEOPLE | C8: =N8-D8-E8-F8-G8-H8-I8-J8-K8-L8-M8-D62-E62-F62-G62-H62-I62-J62-K62-L62-C62 -> 6957.48 | N8: 6957.48
A9: 5653712 | B9: THE GROCERY PEOPLE | C9: =N9-D9-E9-F9-G9-H9-I9-J9-K9-L9-M9-D63-E63-F63-G63-H63-I63-J63-K63-L63-C63 -> 70.5 | K9: 2493.61 | N9: 2564.11
A10: 8252831 | B10: THE GROCERY PEOPLE | C10: =N10-D10-E10-F10-G10-H10-I10-J10-K10-L10-M10-D64-E64-F64-G64-H64-I64-J64-K64-L64-C64 -> 0 | E10: 2144.43 | N10: 2144.43
A11: 8252914 | B11: THE GROCERY PEOPLE | C11: =N11-D11-E11-F11-G11-H11-I11-J11-K11-L11-M11-D65-E65-F65-G65-H65-I65-J65-K65-L65-C65 -> 0 | E11: 314.72 | N11: 314.72
A12: 5653216 | B12: THE GROCERY PEOPLE | C12: =N12-D12-E12-F12-G12-H12-I12-J12-K12-L12-M12-D66-E66-F66-G66-H66-I66-J66-K66-L66-C66 -> 152.44 | E12: 3161.92 | N12: 3314.36
A13: 5653394 | B13: THE GROCERY PEOPLE | C13: =N13-D13-E13-F13-G13-H13-I13-J13-K13-L13-M13-D67-E67-F67-G67-H67-I67-J67-K67-L67-C67 -> 0 | E13: 1604.7 | N13: 1604.7
A14: 5653453 | B14: THE GROCERY PEOPLE | C14: =N14-D14-E14-F14-G14-H14-I14-J14-K14-L14-M14-D68-E68-F68-G68-H68-I68-J68-K68-L68-C68 -> 0 | E14: 88.58 | N14: 88.58
A15: 5653506 | B15: THE GROCERY PEOPLE | C15: =N15-D15-E15-F15-G15-H15-I15-J15-K15-L15-M15-D69-E69-F69-G69-H69-I69-J69-K69-L69-C69 -> 0 | E15: 309.04 | N15: 309.04
A16: 5653711 | B16: THE GROCERY PEOPLE | C16: =N16-D16-E16-F16-G16-H16-I16-J16-K16-L16-M16-D70-E70-F70-G70-H70-I70-J70-K70-L70-C70 -> 0 | K16: 548.7 | N16: 548.7
A17: 5652674 | B17: THE GROCERY PEOPLE | C17: =N17-D17-E17-F17-G17-H17-I17-J17-K17-L17-M17-D71-E71-F71-G71-H71-I71-J71-K71-L71-C71 -> 0 | I17: 54.99 | N17: 54.99
A18: 5654123 | B18: THE GROCERY PEOPLE | C18: =N18-D18-E18-F18-G18-H18-I18-J18-K18-L18-M18-D72-E72-F72-G72-H72-I72-J72-K72-L72-C72 -> 22.43 | K18: 138.29 | N18: 160.72
A19: 5654308 | B19: THE GROCERY PEOPLE | C19: =N19-D19-E19-F19-G19-H19-I19-J19-K19-L19-M19-D73-E73-F73-G73-H73-I73-J73-K73-L73-C73 -> 0 | I19: 4069.67 | N19: 4069.67
A20: 6699576 | B20: THE GROCERY PEOPLE | C20: =N20-D20-E20-F20-G20-H20-I20-J20-K20-L20-M20-D74-E74-F74-G74-H74-I74-J74-K74-L74-C74 -> 0 | E20: 56.86 | N20: 56.86
A21: 6701953 | B21: THE GROCERY PEOPLE | C21: =N21-D21-E21-F21-G21-H21-I21-J21-K21-L21-M21-D75-E75-F75-G75-H75-I75-J75-K75-L75-C75 -> 1521.8 | N21: 1521.8
A22: 6701954 | B22: THE GROCERY PEOPLE | C22: =N22-D22-E22-F22-G22-H22-I22-J22-K22-L22-M22-D76-E76-F76-G76-H76-I76-J76-K76-L76-C76 -> 5.5 | N22: 5.5
A23: 6701955 | B23: THE GROCERY PEOPLE | C23: =N23-D23-E23-F23-G23-H23-I23-J23-K23-L23-M23-D77-E77-F77-G77-H77-I77-J77-K77-L77-C77 -> 320.39 | N23: 320.39
A24: 6703548 | B24: THE GROCERY PEOPLE | C24: =N24-D24-E24-F24-G24-H24-I24-J24-K24-L24-M24-D78-E78-F78-G78-H78-I78-J78-K78-L78-C78 -> 0 | K24: 334.95 | N24: 334.95
A25: 119525 | B25: KENNELLI SPRINGS | C25: =N25-D25-E25-F25-G25-H25-I25-J25-K25-L25-M25-D79-E79-F79-G79-H79-I79-J79-K79-L79-C79 -> 285 | M25: 0.75 | N25: 285.75
A26: 7726195003 | B26: UNITED DISTRIBUTION NETWORK | C26: =N26-D26-E26-F26-G26-H26-I26-J26-K26-L26-M26-D80-E80-F80-G80-H80-I80-J80-K80-L80-C80 -> 8902.42 | M26: 325.14 | N26: 9227.56
A27: 7726195004 | B27: UNITED DISTRIBUTION NETWORK | C27: =N27-D27-E27-F27-G27-H27-I27-J27-K27-L27-M27-D81-E81-F81-G81-H81-I81-J81-K81-L81-C81 -> 1080 | M27: 51.6 | N27: 1131.6
A28: 7726195005 | B28: UNITED DISTRIBUTION NETWORK | C28: =N28-D28-E28-F28-G28-H28-I28-J28-K28-L28-M28-D82-E82-F82-G82-H82-I82-J82-K82-L82-C82 -> 431.78 | M28: 21.59 | N28: 453.37
A29: 7726195006 | B29: UNITED DISTRIBUTION NETWORK | C29: =N29-D29-E29-F29-G29-H29-I29-J29-K29-L29-M29-D83-E83-F83-G83-H83-I83-J83-K83-L83-C83 -> 138.66 | M29: 6.93 | N29: 145.59
A30: 96287176 | B30: FRITO LAY CANADA RETAIL | C30: =N30-D30-E30-F30-G30-H30-I30-J30-K30-L30-M30-D84-E84-F84-G84-H84-I84-J84-K84-L84-C84 -> 872.1 | M30: 40.8 | N30: 912.9
A31: 77684243 | B31: FRITO LAY CANADA RETAIL | C31: =N31-D31-E31-F31-G31-H31-I31-J31-K31-L31-M31-D85-E85-F85-G85-H85-I85-J85-K85-L85-C85 -> -119.746 | M31: -5.99 | N31: -125.736
C32: =N32-D32-E32-F32-G32-H32-I32-J32-K32-L32-M32-D86-E86-F86-G86-H86-I86-J86-K86-L86-C86 -> 0
C33: =N33-D33-E33-F33-G33-H33-I33-J33-K33-L33-M33-D87-E87-F87-G87-H87-I87-J87-K87-L87-C87 -> 0
C34: =N34-D34-E34-F34-G34-H34-I34-J34-K34-L34-M34-D88-E88-F88-G88-H88-I88-J88-K88-L88-C88 -> 0
C35: =N35-D35-E35-F35-G35-H35-I35-J35-K35-L35-M35-D89-E89-F89-G89-H89-I89-J89-K89-L89-C89 -> 0
C36: =N36-D36-E36-F36-G36-H36-I36-J36-K36-L36-M36-D90-E90-F90-G90-H90-I90-J90-K90-L90-C90 -> 0
C37: =N37-D37-E37-F37-G37-H37-I37-J37-K37-L37-M37-D91-E91-F91-G91-H91-I91-J91-K91-L91-C91 -> 0
C38: =N38-D38-E38-F38-G38-H38-I38-J38-K38-L38-M38-D92-E92-F92-G92-H92-I92-J92-K92-L92-C92 -> 0
C39: =N39-D39-E39-F39-G39-H39-I39-J39-K39-L39-M39-D93-E93-F93-G93-H93-I93-J93-K93-L93-C93 -> 0
C40: =N40-D40-E40-F40-G40-H40-I40-J40-K40-L40-M40-D94-E94-F94-G94-H94-I94-J94-K94-L94-C94 -> 0
C41: =N41-D41-E41-F41-G41-H41-I41-J41-K41-L41-M41-D95-E95-F95-G95-H95-I95-J95-K95-L95-C95 -> 0
C42: =N42-D42-E42-F42-G42-H42-I42-J42-K42-L42-M42-D96-E96-F96-G96-H96-I96-J96-K96-L96-C96 -> 0
C43: =N43-D43-E43-F43-G43-H43-I43-J43-K43-L43-M43-D97-E97-F97-G97-H97-I97-J97-K97-L97-C97 -> 0
... C55: =N55-D55-E55-F55-G55-H55-I55-J55-K55-L55-M55-D109-E109-F109-G109-H109-I109-J109-K109-L109-C109 -> 0
A56: Freight | B56: THE GROCERY PEOPLE | C56: =C3 -> 129.06478 | E56: =E3 -> 26.73099 | F56: =F3 -> 0 | G56: =G3 -> 0 | H56: =H3 -> 0 | I56: =I3 -> 42.93159 | J56: =J3 -> 32.94122 | K56: =K3 -> 38.34142 | L56: =L3 -> 0 | N56: =SUM(C56:M56)+SUM(C118:J118) -> 270.01 | O56: BM#8549150, BOL REF#4867925,4867923,4867924,4867926,4867922
A57: Department Totals | C57: =SUM(C6:C56) -> 23095.189 | D57: =SUM(D6:D56) -> 0 | E57: =SUM(E6:E56) -> 7706.981 | F57: =SUM(F6:F56) -> 0 | G57: =SUM(G6:G56) -> 0 | H57: =SUM(H6:H56) -> 0 | I57: =SUM(I6:I56) -> 4167.5916 | J57: =SUM(J6:J56) -> 32.94122 | ... N57: =SUM(N6:N56) -> 40921.934
N58: =IF(SUM(N6:N56)=SUM(C57:M57)+SUM(C110:K110),"","Sum error")
A59: Invoice Number | B59: Supplier Name | C59: Grocery Supplies | D59: Tobacco Supplies | E59: Meat Supplies | F59: Bakery Supplies | G59: B.In store Supplies | H59: Deli Supplies | I59: Produce Supplies | K59: Dairy Supplies | L59: Pharmacy Supplies
A60: =A6 -> 4003807742 | B60: =B6 -> SAPUTO DAIRY PRODUCTS
A61: =A7 -> 5653634 | B61: =B7 -> THE GROCERY PEOPLE
A62: =A8 -> 5653683 | B62: =B8 -> THE GROCERY PEOPLE
A63: =A9 -> 5653712 | B63: =B9 -> THE GROCERY PEOPLE
A64: =A10 -> 8252831 | B64: =B10 -> THE GROCERY PEOPLE
A65: =A11 -> 8252914 | B65: =B11 -> THE GROCERY PEOPLE
A66: =A12 -> 5653216 | B66: =B12 -> THE GROCERY PEOPLE
A67: =A13 -> 5653394 | B67: =B13 -> THE GROCERY PEOPLE
A68: =A14 -> 5653453 | B68: =B14 -> THE GROCERY PEOPLE
A69: =A15 -> 5653506 | B69: =B15 -> THE GROCERY PEOPLE
A70: =A16 -> 5653711 | B70: =B16 -> THE GROCERY PEOPLE
A71: =A17 -> 5652674 | B71: =B17 -> THE GROCERY PEOPLE
... A109: =A55 | B109: =B55
A110: Department Totals | C110: =SUM(C60:C109) -> 0 | D110: =SUM(D60:D109) -> 0 | E110: =SUM(E60:E109) -> 0 | F110: =SUM(F60:F109) -> 0 | G110: =SUM(G60:G109) -> 0 | H110: =SUM(H60:H109) -> 0 | I110: =SUM(I60:I109) -> 0 | J110: =SUM(J60:J109) -> 0 | K110: =SUM(K60:K109) -> 0 | L110: 0

Sheet Wednesday WK4 (25)
B1: Freight | C1: Grocery | E1: Meat | F1: Bakery | G1: Bake off | H1: Deli | I1: Produce | J1: Produce Shrink | K1: Dairy | L1: Pharmacy | M1: Receiving Totals | N1: Total
B2: Name: | C2: ='Sunday WK1 (1)'!C2 -> 0.478 | E2: ='Sunday WK1 (1)'!E2 -> 0.099 | F2: ='Sunday WK1 (1)'!F2 -> 0 | G2: ='Sunday WK1 (1)'!G2 -> 0 | H2: ='Sunday WK1 (1)'!H2 -> 0 | I2: ='Sunday WK1 (1)'!I2 -> 0.159 | J2: ='Sunday WK1 (1)'!J2 -> 0.122 | K2: ='Sunday WK1 (1)'!$K$2 -> 0.142 | L2: 0 | N2: =SUM(C2:M2) -> 1
B3: SHANNON | C3: =C2*$N$3 -> 36.69606 | E3: =E2*$N$3 -> 7.60023 | F3: =F2*$N$3 -> 0 | G3: =G2*$N$3 -> 0 | H3: =H2*$N$3 -> 0 | I3: =I2*$N$3 -> 12.20643 | J3: =J2*$N$3 -> 9.36594 | K3: =K2*$N$3 -> 10.90134 | L3: =L2*$N$3 -> 0 | N3: 76.77
A4: Receiving Date: | B4: ='Tuesday WK4 (24)'!$B$4+1 -> 46218
A5: Invoice Number | B5: Supplier Name | C5: Grocery Purchases | D5: Tobacco Purchases | E5: Meat Purchases | F5: Bakery Purchases | G5: Bakery In Store | H5: Deli Purchases | I5: Produce Purchases | J5: Produce Shrink | K5: Dairy Purchases | L5: Pharmacy Purchases | M5: GST | N5: Total Invoice**
A6: 9599934 | B6: THE GROCERY PEOPLE | C6: =N6-D6-E6-F6-G6-H6-I6-J6-K6-L6-M6-D60-E60-F60-G60-H60-I60-J60-K60-L60-C60 -> 0 | K6: -35.05 | N6: -35.05 | O6: DAMAGED - SPARKS EGGS, DARIFARM CHEESE
A7: 9599932 | B7: THE GROCERY PEOPLE | C7: =N7-D7-E7-F7-G7-H7-I7-J7-K7-L7-M7-D61-E61-F61-G61-H61-I61-J61-K61-L61-C61 -> 0 | K7: -5.87 | N7: -5.87 | O7: SHORTAGE - OIKOS HI PRO, OVERAGE - OIKOS 2 % PLAIN
A8: 9599930 | B8: THE GROCERY PEOPLE | C8: =N8-D8-E8-F8-G8-H8-I8-J8-K8-L8-M8-D62-E62-F62-G62-H62-I62-J62-K62-L62-C62 -> 0 | K8: 180.9 | N8: 180.9 | O8: OVERAGE - INT DEL FV, SHORTAGE - INT DEL CARM
A9: 9599926 | B9: THE GROCERY PEOPLE | C9: =N9-D9-E9-F9-G9-H9-I9-J9-K9-L9-M9-D63-E63-F63-G63-H63-I63-J63-K63-L63-C63 -> 0 | K9: -63.57 | N9: -63.57 | O9: DAMAGED - CENT 18PK EGGS, EO ALMOND
A10: 9599929 | B10: THE GROCERY PEOPLE | C10: =N10-D10-E10-F10-G10-H10-I10-J10-K10-L10-M10-D64-E64-F64-G64-H64-I64-J64-K64-L64-C64 -> 0 | K10: -39.14 | N10: -39.14 | O10: SHORTAGE - OLYMPIC PLAIN, OVERAGE - LIBERTE
A11: 9501795 | B11: THE GROCERY PEOPLE | C11: =N11-D11-E11-F11-G11-H11-I11-J11-K11-L11-M11-D65-E65-F65-G65-H65-I65-J65-K65-L65-C65 -> 0 | K11: -16.93 | N11: -16.93 | O11: SHORTED - IOGO MULTI
A12: 9501794 | B12: THE GROCERY PEOPLE | C12: =N12-D12-E12-F12-G12-H12-I12-J12-K12-L12-M12-D66-E66-F66-G66-H66-I66-J66-K66-L66-C66 -> 0 | K12: -7.28 | M12: 0 | N12: -7.28 | O12: SHORTED - CG STRW YOG, OVERAGE - IOGO MULTI
A13: 9501793 | B13: THE GROCERY PEOPLE | C13: =N13-D13-E13-F13-G13-H13-I13-J13-K13-L13-M13-D67-E67-F67-G67-H67-I67-J67-K67-L67-C67 -> 0 | K13: -23.75 | N13: -23.75 | O13: SHORTED - ACTIVIA FIBRE
A14: 9502057 | B14: THE GROCERY PEOPLE | C14: =N14-D14-E14-F14-G14-H14-I14-J14-K14-L14-M14-D68-E68-F68-G68-H68-I68-J68-K68-L68-C68 -> 0 | I14: -322.6 | N14: -322.6 | O14: POOR QUALITY - ROMAINE LETTUCE
A15: 9502056 | B15: THE GROCERY PEOPLE | C15: =N15-D15-E15-F15-G15-H15-I15-J15-K15-L15-M15-D69-E69-F69-G69-H69-I69-J69-K69-L69-C69 -> 0 | I15: -213.2 | N15: -213.2 | O15: POOR QUALITY - HEAD LETTUCE
A16: 9501688 | B16: THE GROCERY PEOPLE | C16: =N16-D16-E16-F16-G16-H16-I16-J16-K16-L16-M16-D70-E70-F70-G70-H70-I70-J70-K70-L70-C70 -> 0 | I16: -174.85 | N16: -174.85 | O16: POOR QUALITY - ESCAROLE LETTUCE, LEMONS
A17: 9598475 | B17: THE GROCERY PEOPLE | C17: =N17-D17-E17-F17-G17-H17-I17-J17-K17-L17-M17-D71-E71-F71-G71-H71-I71-J71-K71-L71-C71 -> -60.3 | N17: -60.3 | O17: PRODUCT RECALL - ROGERS SYRUP
A18: 9599820 | B18: THE GROCERY PEOPLE | C18: =N18-D18-E18-F18-G18-H18-I18-J18-K18-L18-M18-D72-E72-F72-G72-H72-I72-J72-K72-L72-C72 -> -221.45 | N18: -221.45 | O18: POOR QUALITY - SILICONE PARCHMENT ROLL
A19: 9595551 | B19: THE GROCERY PEOPLE | C19: =N19-D19-E19-F19-G19-H19-I19-J19-K19-L19-M19-D73-E73-F73-G73-H73-I73-J73-K73-L73-C73 -> 0 | K19: -23.76 | N19: -23.76 | O19: SHORTED - ACTIVIA BLUE FRUIT
A20: 9597120 | B20: THE GROCERY PEOPLE | C20: =N20-D20-E20-F20-G20-H20-I20-J20-K20-L20-M20-D74-E74-F74-G74-H74-I74-J74-K74-L74-C74 -> 0 | K20: -276.77 | N20: -276.77 | O20: SHORTED - HRD BOIL EGG, KRAFT CHEESE CHDR/MOZZA, DAMAGED - KRAFT CHEESE CHDR/MOZZA SHRED
A21: 6037 | B21: THE GROCERY PEOPLE | C21: =N21-D21-E21-F21-G21-H21-I21-J21-K21-L21-M21-D75-E75-F75-G75-H75-I75-J75-K75-L75-C75 -> -2310 | N21: -2310 | O21: STORE TRANSFER - HIGH LEVEL
C22: =N22-D22-E22-F22-G22-H22-I22-J22-K22-L22-M22-D76-E76-F76-G76-H76-I76-J76-K76-L76-C76 -> 0
C23: =N23-D23-E23-F23-G23-H23-I23-J23-K23-L23-M23-D77-E77-F77-G77-H77-I77-J77-K77-L77-C77 -> 0
C24: =N24-D24-E24-F24-G24-H24-I24-J24-K24-L24-M24-D78-E78-F78-G78-H78-I78-J78-K78-L78-C78 -> 0
C25: =N25-D25-E25-F25-G25-H25-I25-J25-K25-L25-M25-D79-E79-F79-G79-H79-I79-J79-K79-L79-C79 -> 0
C26: =N26-D26-E26-F26-G26-H26-I26-J26-K26-L26-M26-D80-E80-F80-G80-H80-I80-J80-K80-L80-C80 -> 0
C27: =N27-D27-E27-F27-G27-H27-I27-J27-K27-L27-M27-D81-E81-F81-G81-H81-I81-J81-K81-L81-C81 -> 0
C28: =N28-D28-E28-F28-G28-H28-I28-J28-K28-L28-M28-D82-E82-F82-G82-H82-I82-J82-K82-L82-C82 -> 0
C29: =N29-D29-E29-F29-G29-H29-I29-J29-K29-L29-M29-D83-E83-F83-G83-H83-I83-J83-K83-L83-C83 -> 0
C30: =N30-D30-E30-F30-G30-H30-I30-J30-K30-L30-M30-D84-E84-F84-G84-H84-I84-J84-K84-L84-C84 -> 0
C31: =N31-D31-E31-F31-G31-H31-I31-J31-K31-L31-M31-D85-E85-F85-G85-H85-I85-J85-K85-L85-C85 -> 0
C32: =N32-D32-E32-F32-G32-H32-I32-J32-K32-L32-M32-D86-E86-F86-G86-H86-I86-J86-K86-L86-C86 -> 0
C33: =N33-D33-E33-F33-G33-H33-I33-J33-K33-L33-M33-D87-E87-F87-G87-H87-I87-J87-K87-L87-C87 -> 0
... C55: =N55-D55-E55-F55-G55-H55-I55-J55-K55-L55-M55-D109-E109-F109-G109-H109-I109-J109-K109-L109-C109 -> 0
A56: Freight | B56: THE GROCERY PEOPLE | C56: =C3 -> 36.69606 | E56: =E3 -> 7.60023 | F56: =F3 -> 0 | G56: =G3 -> 0 | H56: =H3 -> 0 | I56: =I3 -> 12.20643 | J56: =J3 -> 9.36594 | K56: =K3 -> 10.90134 | L56: =L3 -> 0 | N56: =SUM(C56:M56)+SUM(C118:J118) -> 76.77 | O56: CLAIM #9599930
A57: Department Totals | C57: =SUM(C6:C56) -> -2555.0539 | D57: =SUM(D6:D56) -> 0 | E57: =SUM(E6:E56) -> 7.60023 | F57: =SUM(F6:F56) -> 0 | G57: =SUM(G6:G56) -> 0 | H57: =SUM(H6:H56) -> 0 | I57: =SUM(I6:I56) -> -698.44357 | J57: =SUM(J6:J56) -> 9.36594 | ... N57: =SUM(N6:N56) -> -3536.85
N58: =IF(SUM(N6:N56)=SUM(C57:M57)+SUM(D110:L110),"","Sum error")
A59: Invoice Number | B59: Supplier Name | C59: Grocery Supplies | D59: Tobacco Supplies | E59: Meat Supplies | F59: Bakery Supplies | G59: B.In store Supplies | H59: Deli Supplies | I59: Produce Supplies | K59: Dairy Supplies | L59: Pharmacy Supplies
A60: =A6 -> 9599934 | B60: =B6 -> THE GROCERY PEOPLE
A61: =A7 -> 9599932 | B61: =B7 -> THE GROCERY PEOPLE
A62: =A8 -> 9599930 | B62: =B8 -> THE GROCERY PEOPLE
A63: =A9 -> 9599926 | B63: =B9 -> THE GROCERY PEOPLE
A64: =A10 -> 9599929 | B64: =B10 -> THE GROCERY PEOPLE
A65: =A11 -> 9501795 | B65: =B11 -> THE GROCERY PEOPLE
A66: =A12 -> 9501794 | B66: =B12 -> THE GROCERY PEOPLE
A67: =A13 -> 9501793 | B67: =B13 -> THE GROCERY PEOPLE
A68: =A14 -> 9502057 | B68: =B14 -> THE GROCERY PEOPLE
A69: =A15 -> 9502056 | B69: =B15 -> THE GROCERY PEOPLE
A70: =A16 -> 9501688 | B70: =B16 -> THE GROCERY PEOPLE
A71: =A17 -> 9598475 | B71: =B17 -> THE GROCERY PEOPLE
... A109: =A55 | B109: =B55
A110: Department Totals | C110: =SUM(C60:C109) -> 0 | D110: =SUM(D60:D109) -> 0 | E110: =SUM(E60:E109) -> 0 | F110: =SUM(F60:F109) -> 0 | G110: =SUM(G60:G109) -> 0 | H110: =SUM(H60:H109) -> 0 | I110: =SUM(I60:I109) -> 0 | J110: =SUM(J60:J109) -> 0 | K110: =SUM(K60:K109) -> 0 | L110: 0

Sheet Thursday WK4 (26)
B1: Freight | C1: Grocery | E1: Meat | F1: Bakery | G1: Bake off | H1: Deli | I1: Produce | J1: Produce Shrink | K1: Dairy | L1: Pharmacy | M1: Receiving Totals | N1: Total
B2: Name: | C2: ='Sunday WK1 (1)'!C2 -> 0.478 | E2: ='Sunday WK1 (1)'!E2 -> 0.099 | F2: ='Sunday WK1 (1)'!F2 -> 0 | G2: ='Sunday WK1 (1)'!G2 -> 0 | H2: ='Sunday WK1 (1)'!H2 -> 0 | I2: ='Sunday WK1 (1)'!I2 -> 0.159 | J2: ='Sunday WK1 (1)'!J2 -> 0.122 | K2: ='Sunday WK1 (1)'!$K$2 -> 0.142 | L2: 0 | N2: =SUM(C2:M2) -> 1
B3: SHANNON | C3: =C2*$N$3 -> 136.54548 | E3: =E2*$N$3 -> 28.28034 | F3: =F2*$N$3 -> 0 | G3: =G2*$N$3 -> 0 | H3: =H2*$N$3 -> 0 | I3: =I2*$N$3 -> 45.41994 | J3: =J2*$N$3 -> 34.85052 | K3: =K2*$N$3 -> 40.56372 | L3: =L2*$N$3 -> 0 | N3: 285.66
A4: Receiving Date: | B4: ='Wednesday WK4 (25)'!$B$4+1 -> 46219
A5: Invoice Number | B5: Supplier Name | C5: Grocery Purchases | D5: Tobacco Purchases | E5: Meat Purchases | F5: Bakery Purchases | G5: Bakery In Store | H5: Deli Purchases | I5: Produce Purchases | J5: Produce Shrink | K5: Dairy Purchases | L5: Pharmacy Purchases | M5: GST | N5: Total Invoice**
A6: 900018499 | B6: FREYBE GOURMET FOODS | C6: =N6-D6-E6-F6-G6-H6-I6-J6-K6-L6-M6-D60-E60-F60-G60-H60-I60-J60-K60-L60-C60 -> 0 | E6: -232 | N6: -232
A7: 900018500 | B7: FREYBE GOURMET FOODS | C7: =N7-D7-E7-F7-G7-H7-I7-J7-K7-L7-M7-D61-E61-F61-G61-H61-I61-J61-K61-L61-C61 -> 0 | E7: -86.47 | N7: -86.47
A8: 4003825419 | B8: SAPUTO DAIRY PRODUCTS | C8: =N8-D8-E8-F8-G8-H8-I8-J8-K8-L8-M8-D62-E62-F62-G62-H62-I62-J62-K62-L62-C62 -> 0 | K8: 109.2 | N8: 109.2
A9: 4003825420 | B9: SAPUTO DAIRY PRODUCTS | C9: =N9-D9-E9-F9-G9-H9-I9-J9-K9-L9-M9-D63-E63-F63-G63-H63-I63-J63-K63-L63-C63 -> 0 | K9: 81.29 | N9: 81.29
A10: 4003825422 | B10: SAPUTO DAIRY PRODUCTS | C10: =N10-D10-E10-F10-G10-H10-I10-J10-K10-L10-M10-D64-E64-F64-G64-H64-I64-J64-K64-L64-C64 -> 1.2734258e-13 | K10: 2115.16 | M10: 0.61 | N10: 2115.77
A11: 3286349 | B11: LILYDALE SOFINA FOODS | C11: =N11-D11-E11-F11-G11-H11-I11-J11-K11-L11-M11-D65-E65-F65-G65-H65-I65-J65-K65-L65-C65 -> 0 | E11: 64.01 | N11: 64.01
A12: 3286350 | B12: LILYDALE SOFINA FOODS | C12: =N12-D12-E12-F12-G12-H12-I12-J12-K12-L12-M12-D66-E66-F66-G66-H66-I66-J66-K66-L66-C66 -> 0 | E12: 464.15 | N12: 464.15
A13: 773686 | B13: PACIFIC FRESH FISH | C13: =N13-D13-E13-F13-G13-H13-I13-J13-K13-L13-M13-D67-E67-F67-G67-H67-I67-J67-K67-L67-C67 -> 114 | N13: 114
A14: SO186928 | B14: STAR PRODUCE | C14: =N14-D14-E14-F14-G14-H14-I14-J14-K14-L14-M14-D68-E68-F68-G68-H68-I68-J68-K68-L68-C68 -> 2.3092639e-14 | I14: 372.7 | M14: 15.1 | N14: 387.8
A15: 5655533 | B15: THE GROCERY PEOPLE | C15: =N15-D15-E15-F15-G15-H15-I15-J15-K15-L15-M15-D69-E69-F69-G69-H69-I69-J69-K69-L69-C69 -> 86.9 | N15: 86.9
A16: 5655652 | B16: THE GROCERY PEOPLE | C16: =N16-D16-E16-F16-G16-H16-I16-J16-K16-L16-M16-D70-E70-F70-G70-H70-I70-J70-K70-L70-C70 -> 0 | K16: 251.61 | N16: 251.61
A17: 5656206 | B17: THE GROCERY PEOPLE | C17: =N17-D17-E17-F17-G17-H17-I17-J17-K17-L17-M17-D71-E71-F71-G71-H71-I71-J71-K71-L71-C71 -> 2008.33 | N17: 2008.33
A18: 5656304 | B18: THE GROCERY PEOPLE | C18: =N18-D18-E18-F18-G18-H18-I18-J18-K18-L18-M18-D72-E72-F72-G72-H72-I72-J72-K72-L72-C72 -> 5872.3 | N18: 5872.3
A19: 5656366 | B19: THE GROCERY PEOPLE | C19: =N19-D19-E19-F19-G19-H19-I19-J19-K19-L19-M19-D73-E73-F73-G73-H73-I73-J73-K73-L73-C73 -> 1941.3 | N19: 1941.3
A20: 5656371 | B20: THE GROCERY PEOPLE | C20: =N20-D20-E20-F20-G20-H20-I20-J20-K20-L20-M20-D74-E74-F74-G74-H74-I74-J74-K74-L74-C74 -> 0 | K20: 876.57 | N20: 876.57
A21: 5656372 | B21: THE GROCERY PEOPLE | C21: =N21-D21-E21-F21-G21-H21-I21-J21-K21-L21-M21-D75-E75-F75-G75-H75-I75-J75-K75-L75-C75 -> 53.38 | N21: 53.38
A22: 8254324 | B22: THE GROCERY PEOPLE | C22: =N22-D22-E22-F22-G22-H22-I22-J22-K22-L22-M22-D76-E76-F76-G76-H76-I76-J76-K76-L76-C76 -> 0 | E22: 339.6 | N22: 339.6
A23: 8254482 | B23: THE GROCERY PEOPLE | C23: =N23-D23-E23-F23-G23-H23-I23-J23-K23-L23-M23-D77-E77-F77-G77-H77-I77-J77-K77-L77-C77 -> 0 | E23: 773.55 | N23: 773.55
A24: 5655672 | B24: THE GROCERY PEOPLE | C24: =N24-D24-E24-F24-G24-H24-I24-J24-K24-L24-M24-D78-E78-F78-G78-H78-I78-J78-K78-L78-C78 -> 410.22 | E24: 1872.18 | N24: 2282.4
A25: 5654413 | B25: THE GROCERY PEOPLE | C25: =N25-D25-E25-F25-G25-H25-I25-J25-K25-L25-M25-D79-E79-F79-G79-H79-I79-J79-K79-L79-C79 -> 56.88 | N25: 56.88
A26: 5654637 | B26: THE GROCERY PEOPLE | C26: =N26-D26-E26-F26-G26-H26-I26-J26-K26-L26-M26-D80-E80-F80-G80-H80-I80-J80-K80-L80-C80 -> 4726 | N26: 4726
A27: 5654638 | B27: THE GROCERY PEOPLE | C27: =N27-D27-E27-F27-G27-H27-I27-J27-K27-L27-M27-D81-E81-F81-G81-H81-I81-J81-K81-L81-C81 -> 222.42 | N27: 222.42
A28: 5655536 | B28: THE GROCERY PEOPLE | C28: =N28-D28-E28-F28-G28-H28-I28-J28-K28-L28-M28-D82-E82-F82-G82-H82-I82-J82-K82-L82-C82 -> 38.67 | N28: 38.67
